Workbook

Sheet Leia-me
A1: QIMO · Estudo de viabilidade — navio boutique próprio × charter
A3: Objetivo: comparar COMPRAR USADO × CONSTRUIR NOVO × CONTINUAR FRETANDO para operar grupos privados QIMO na Grécia/Mediterrâneo.
A4: Data-base: outubro/2026. Moeda: € (USD convertido a 1,15; BRL a 5,85).
A6: COMO USAR
A7: 1) Edite somente as células em AZUL (inputs). Amarelo = premissas-chave (semanas, semanas QIMO, tarifa, preço do navio, combustível, alíquota, hurdle).
A8: 2) Preto = fórmula. Verde = link de outra aba. Não sobrescreva fórmulas.
A9: 3) Tudo recalcula: Projecao (18 blocos = 6 opções × 3 cenários), Sensib_Semanas, Buy_Build_Charter, Financiamento e Painel.
A11: ABAS
A12: Painel — resultados-chave (TIR, VPL, payback, break-even, semanas p/ possuir = fretar, alavancagem).
A13: Premissas — gerais, cenários e as 6 opções de navio (A/B/C × novo/usado), com tipo e fonte de cada número.
A14: Tripulacao — quadro de tripulação por configuração, salários e custo anual.
A15: CAPEX_Construcao — breakdown de construção nova em 3 padrões (Premium funcional / Luxury boutique / Ultra-luxury) e custo por região.
... A31: • A margem da QIMO na venda da viagem ao cliente final existe nos dois modelos e não entra na comparação.

Sheet Painel
A1: QIMO · Navio Boutique — Painel executivo (atualiza com as Premissas)
A2: Devemos investir em um navio próprio? Leia as linhas de TIR, VPL e semanas para possuir = fretar.
A4: 1. Resultados por opção e cenário
A5: Opção / cenário | B5: CAPEX | C5: Receita a3 | D5: EBITDA a3 | E5: Margem a3 | F5: TIR 10a | G5: VPL @hurdle | H5: Payback | I5: Break-even (sem.) | J5: ROIC médio
A6: C · 36 cab/72 pax · NOVO · Conservador | B6: =Projecao!$C$41 -> 47709000 | C6: =Projecao!$C$37 -> 5039636.3 | D6: =Projecao!$C$36 -> -414300.38 | E6: =Projecao!$C$38 -> -0.082208388 | F6: =Projecao!$C$31 -> -0.11933694 | G6: =Projecao!$C$32 -> -50614480 | H6: =Projecao!$C$33 -> > 10 | I6: =Projecao!$C$40 -> 22.336282 | J6: =Projecao!$C$35 -> -0.044653027
A7: C · 36 cab/72 pax · NOVO · Base | B7: =Projecao!$C$82 -> 47709000 | C7: =Projecao!$C$78 -> 7463640 | D7: =Projecao!$C$77 -> 2338197.2 | E7: =Projecao!$C$79 -> 0.3132784 | F7: =Projecao!$C$72 -> -0.017419323 | G7: =Projecao!$C$73 -> -31517619 | H7: =Projecao!$C$74 -> > 10 | I7: =Projecao!$C$81 -> 15.763871 | J7: =Projecao!$C$76 -> 0.0026538678
A8: C · 36 cab/72 pax · NOVO · Otimista | B8: =Projecao!$C$123 -> 47709000 | C8: =Projecao!$C$119 -> 9746923.8 | D8: =Projecao!$C$118 -> 4819256.2 | E8: =Projecao!$C$120 -> 0.49443869 | F8: =Projecao!$C$113 -> 0.032259973 | G8: =Projecao!$C$114 -> -19656752 | H8: =Projecao!$C$115 -> > 10 | I8: =Projecao!$C$122 -> 12.454355 | J8: =Projecao!$C$117 -> 0.046518913
A9: C · 36 cab/72 pax · USADO · Conservador | B9: =Projecao!$C$164 -> 21400000 | C9: =Projecao!$C$160 -> 4553087.7 | D9: =Projecao!$C$159 -> -970317.6 | E9: =Projecao!$C$161 -> -0.21311199 | F9: =Projecao!$C$154 -> negativa | G9: =Projecao!$C$155 -> -29267829 | H9: =Projecao!$C$156 -> > 10 | I9: =Projecao!$C$163 -> 26.341705 | J9: =Projecao!$C$158 -> -0.0761848
A10: C · 36 cab/72 pax · USADO · Base | B10: =Projecao!$C$205 -> 21400000 | C10: =Projecao!$C$201 -> 6739969.5 | D10: =Projecao!$C$200 -> 1551373.5 | E10: =Projecao!$C$202 -> 0.23017515 | F10: =Projecao!$C$195 -> -0.026968782 | G10: =Projecao!$C$196 -> -13109788 | H10: =Projecao!$C$197 -> > 10 | I10: =Projecao!$C$204 -> 18.266043 | J10: =Projecao!$C$199 -> 0.013531768
A11: C · 36 cab/72 pax · USADO · Otimista | B11: =Projecao!$C$246 -> 21400000 | C11: =Projecao!$C$242 -> 8798058.1 | D11: =Projecao!$C$241 -> 3810395 | E11: =Projecao!$C$243 -> 0.433095 | F11: =Projecao!$C$236 -> 0.075121747 | G11: =Projecao!$C$237 -> -2822134.2 | H11: =Projecao!$C$238 -> 9.6168718 | I11: =Projecao!$C$245 -> 14.321994 | J11: =Projecao!$C$240 -> 0.095732345
A12: B · 24 cab/48 pax · NOVO · Conservador | B12: =Projecao!$C$287 -> 31940000 | C12: =Projecao!$C$283 -> 2918346.3 | D12: =Projecao!$C$282 -> -1073654.5 | E12: =Projecao!$C$284 -> -0.36789824 | F12: =Projecao!$C$277 -> negativa | G12: =Projecao!$C$278 -> -38999309 | H12: =Projecao!$C$279 -> > 10 | I12: =Projecao!$C$286 -> 31.43617 | J12: =Projecao!$C$281 -> -0.062035231
A13: B · 24 cab/48 pax · NOVO · Base | B13: =Projecao!$C$328 -> 31940000 | C13: =Projecao!$C$324 -> 4309957.9 | D13: =Projecao!$C$323 -> 569735.33 | E13: =Projecao!$C$325 -> 0.13219046 | F13: =Projecao!$C$318 -> -0.057523175 | G13: =Projecao!$C$319 -> -27191281 | H13: =Projecao!$C$320 -> > 10 | I13: =Projecao!$C$327 -> 21.445952 | J13: =Projecao!$C$322 -> -0.019153332
A14: B · 24 cab/48 pax · NOVO · Otimista | B14: =Projecao!$C$369 -> 31940000 | C14: =Projecao!$C$365 -> 5621226.2 | D14: =Projecao!$C$364 -> 2031811.2 | E14: =Projecao!$C$366 -> 0.36145337 | F14: =Projecao!$C$359 -> 0.0032103243 | G14: =Projecao!$C$360 -> -18303452 | H14: =Projecao!$C$361 -> > 10 | I14: =Projecao!$C$368 -> 16.693118 | J14: =Projecao!$C$363 -> 0.02020407
A15: B · 24 cab/48 pax · USADO · Conservador | B15: =Projecao!$C$410 -> 10600000 | C15: =Projecao!$C$406 -> 2593980.5 | D15: =Projecao!$C$405 -> -1368005.2 | E15: =Projecao!$C$407 -> -0.52737683 | F15: =Projecao!$C$400 -> negativa | G15: =Projecao!$C$401 -> -20795451 | H15: =Projecao!$C$402 -> > 10 | I15: =Projecao!$C$409 -> 37.614393 | J15: =Projecao!$C$404 -> -0.13618629
A16: B · 24 cab/48 pax · USADO · Base | B16: =Projecao!$C$451 -> 10600000 | C16: =Projecao!$C$447 -> 3827510.9 | D16: =Projecao!$C$446 -> 114574.67 | E16: =Projecao!$C$448 -> 0.029934512 | F16: =Projecao!$C$441 -> -0.13555315 | G16: =Projecao!$C$442 -> -10853228 | H16: =Projecao!$C$443 -> > 10 | I16: =Projecao!$C$450 -> 24.924682 | J16: =Projecao!$C$445 -> -0.031004396
A17: B · 24 cab/48 pax · USADO · Otimista | B17: =Projecao!$C$492 -> 10600000 | C17: =Projecao!$C$488 -> 4988649.1 | D17: =Projecao!$C$487 -> 1425156.1 | E17: =Projecao!$C$489 -> 0.28567976 | F17: =Projecao!$C$482 -> 0.026922799 | G17: =Projecao!$C$483 -> -3929847.9 | H17: =Projecao!$C$484 -> > 10 | I17: =Projecao!$C$491 -> 19.17078 | J17: =Projecao!$C$486 -> 0.06400252
A18: A · 20 cab/40 pax · NOVO · Conservador | B18: =Projecao!$C$533 -> 27370000 | C18: =Projecao!$C$529 -> 2109814.7 | D18: =Projecao!$C$528 -> -1343996.3 | E18: =Projecao!$C$530 -> -0.63702103 | F18: =Projecao!$C$523 -> negativa | G18: =Projecao!$C$524 -> -36046078 | H18: =Projecao!$C$525 -> > 10 | I18: =Projecao!$C$532 -> 42.151773 | J18: =Projecao!$C$527 -> -0.072707038
A19: A · 20 cab/40 pax · NOVO · Base | B19: =Projecao!$C$574 -> 27370000 | C19: =Projecao!$C$570 -> 3106488 | D19: =Projecao!$C$569 -> -124297.43 | E19: =Projecao!$C$571 -> -0.040012204 | F19: =Projecao!$C$564 -> -0.089715565 | G19: =Projecao!$C$565 -> -27152100 | H19: =Projecao!$C$566 -> > 10 | I19: =Projecao!$C$573 -> 27.468537 | J19: =Projecao!$C$568 -> -0.034705738
A20: A · 20 cab/40 pax · NOVO · Otimista | B20: =Projecao!$C$615 -> 27370000 | C20: =Projecao!$C$611 -> 4045822.4 | D20: =Projecao!$C$610 -> 949351.71 | E20: =Projecao!$C$612 -> 0.23464987 | F20: =Projecao!$C$605 -> -0.020016109 | G20: =Projecao!$C$606 -> -19069890 | H20: =Projecao!$C$607 -> > 10 | I20: =Projecao!$C$614 -> 20.981602 | J20: =Projecao!$C$609 -> -7.506941e-05
A21: A · 18 cab/36 pax · USADO · Conservador | B21: =Projecao!$C$656 -> 10000000 | C21: =Projecao!$C$652 -> 1812563.9 | D21: =Projecao!$C$651 -> -1451158.7 | E21: =Projecao!$C$653 -> -0.80061105 | F21: =Projecao!$C$646 -> negativa | G21: =Projecao!$C$647 -> -20202033 | H21: =Projecao!$C$648 -> > 10 | I21: =Projecao!$C$655 -> 49.466319 | J21: =Projecao!$C$650 -> -0.14632006
A22: A · 18 cab/36 pax · USADO · Base | B22: =Projecao!$C$697 -> 10000000 | C22: =Projecao!$C$693 -> 2675248.5 | D22: =Projecao!$C$692 -> -373568.54 | E22: =Projecao!$C$694 -> -0.13963882 | F22: =Projecao!$C$687 -> negativa | G22: =Projecao!$C$688 -> -12893628 | H22: =Projecao!$C$689 -> > 10 | I22: =Projecao!$C$696 -> 31.275573 | J22: =Projecao!$C$691 -> -0.06379819
A23: A · 18 cab/36 pax · USADO · Otimista | B23: =Projecao!$C$738 -> 10000000 | C23: =Projecao!$C$734 -> 3486234.7 | D23: =Projecao!$C$733 -> 566536.98 | E23: =Projecao!$C$735 -> 0.16250684 | F23: =Projecao!$C$728 -> -0.034384191 | G23: =Projecao!$C$729 -> -6642691 | H23: =Projecao!$C$730 -> > 10 | I23: =Projecao!$C$737 -> 23.635509 | J23: =Projecao!$C$732 -> 0.0099647583
A25: 2. Possuir × fretar (cenário Base)
B26: C · 36 cab/72 pax · NOVO | C26: C · 36 cab/72 pax · USADO | D26: B · 24 cab/48 pax · NOVO | E26: B · 24 cab/48 pax · USADO | F26: A · 20 cab/40 pax · NOVO | G26: A · 18 cab/36 pax · USADO
A27: Semanas p/ possuir = fretar | B27: =Buy_Build_Charter!B14 -> 41.664627 | C27: =Buy_Build_Charter!C14 -> 31.992325 | D27: =Buy_Build_Charter!D14 -> 53.901322 | E27: =Buy_Build_Charter!E14 -> 38.319572 | F27: =Buy_Build_Charter!F14 -> 70.039246 | G27: =Buy_Build_Charter!G14 -> 49.643183
A28: Custo próprio vs tarifa @26 sem. | B28: =Buy_Build_Charter!B17 -> 0.49148544 | C28: =Buy_Build_Charter!C17 -> 0.18329418 | D28: =Buy_Build_Charter!D17 -> 0.83118056 | E28: =Buy_Build_Charter!E17 -> 0.35275618 | F28: =Buy_Build_Charter!F17 -> 1.2302753 | G28: =Buy_Build_Charter!G17 -> 0.64744667
A29: Custo próprio vs tarifa @30 sem. | B29: =Buy_Build_Charter!B19 -> 0.31718566 | C29: =Buy_Build_Charter!C19 -> 0.052816005 | D29: =Buy_Build_Charter!D19 -> 0.61708447 | E29: =Buy_Build_Charter!E19 -> 0.20645818 | F29: =Buy_Build_Charter!F19 -> 0.96939416 | G29: =Buy_Build_Charter!G19 -> 0.46618899
A30: CAPEX máx. justificável @26 sem. | B30: =Buy_Build_Charter!B21 -> 12419489 | C30: =Buy_Build_Charter!C21 -> 7568858.7 | D30: =Buy_Build_Charter!D21 -> 2953740 | E30: =Buy_Build_Charter!E21 -> 200401.97 | F30: =Buy_Build_Charter!F21 -> 0 | G30: =Buy_Build_Charter!G21 -> 0
A31: CAPEX máx. justificável @30 sem. | B31: =Buy_Build_Charter!B22 -> 17127342 | C31: =Buy_Build_Charter!C22 -> 11468382 | D31: =Buy_Build_Charter!D22 -> 5486712.9 | E31: =Buy_Build_Charter!E22 -> 2228386.8 | F31: =Buy_Build_Charter!F22 -> 891808.34 | G31: =Buy_Build_Charter!G22 -> 0
A32: CAPEX do caso | B32: =Buy_Build_Charter!B6 -> 47709000 | C32: =Buy_Build_Charter!C6 -> 21400000 | D32: =Buy_Build_Charter!D6 -> 31940000 | E32: =Buy_Build_Charter!E6 -> 10600000 | F32: =Buy_Build_Charter!F6 -> 27370000 | G32: =Buy_Build_Charter!G6 -> 10000000
A34: 3. Charter — custo efetivo para a QIMO (Base)
A35: Navio | B35: Tarifa/sem. | C35: Navio (tarifa+APA+IVA) | D35: Total semana | E35: Por passageiro
A36: 72 pax (Voyager) | B36: =Charter!C7 -> 280000 | C36: =Charter!C13 -> 403200 | D36: =Charter!C14 -> 463600 | E36: =Charter!C16 -> 6438.8889
A37: 48–49 pax | B37: =Charter!C21 -> 135000 | C37: =Charter!C27 -> 194400 | D37: =Charter!C28 -> 229950 | E37: =Charter!C30 -> 4692.8571
A38: 36–40 pax | B38: =Charter!C35 -> 95000 | C38: =Charter!C41 -> 136800 | D38: =Charter!C42 -> 162500 | E38: =Charter!C44 -> 4513.8889
A40: 4. Alavancagem — TIR do acionista (cenário Base)
A41: Opção | B41: 100% equity | C41: 50/50 | D41: 30/70 | E41: Equity 30/70 | F41: DSCR mín 50/50 | G41: DSCR mín 30/70 | H41: Serv. dívida 30/70
A42: C · 36 cab/72 pax · USADO | B42: =Financiamento!$C$16 -> -0.026968782 | C42: =Financiamento!$C$34 -> negativa | D42: =Financiamento!$C$52 -> negativa | E42: =Financiamento!$C$51 -> 6420000 | F42: =Financiamento!$C$35 -> 0.58019412 | G42: =Financiamento!$C$53 -> 0.41442437 | H42: =Financiamento!$C$54 -> 2010316
A43: C · 36 cab/72 pax · NOVO | B43: =Financiamento!$C$70 -> -0.017419323 | C43: =Financiamento!$C$88 -> negativa | D43: =Financiamento!$C$106 -> negativa | E43: =Financiamento!$C$105 -> 14312700 | F43: =Financiamento!$C$89 -> 0.46948988 | G43: =Financiamento!$C$107 -> 0.33534991 | H43: =Financiamento!$C$108 -> 4481783.5
A44: B · 24 cab/48 pax · USADO | B44: =Financiamento!$C$124 -> -0.13555315 | C44: =Financiamento!$C$142 -> negativa | D44: =Financiamento!$C$160 -> negativa | E44: =Financiamento!$C$159 -> 3180000 | F44: =Financiamento!$C$143 -> -0.33346973 | G44: =Financiamento!$C$161 -> -0.23819266 | H44: =Financiamento!$C$162 -> 995764

Sheet Premissas
A1: QIMO · Navio Boutique — Premissas (editáveis)
A2: Azul = input editável · Preto = fórmula · Verde = link de outra aba · Amarelo = premissa-chave. Tipo: CONFIRMADO / ESTIMATIVA / PREMISSA. Valores em € (2026) salvo indicação.
A4: A. PREMISSAS GERAIS
A5: Parâmetro | B5: Valor | C5: Unidade | D5: Tipo | J5: Fonte / racional
A6: Câmbio EUR/USD | B6: 1.15 | C6: USD por € | D6: CONFIRMADO | J6: 1,1469 em 16/09/2026 (poundsterlinglive.com/history/EUR-USD-2026); arredondado para 1,15
A7: Câmbio EUR/BRL | B7: 5.85 | C7: BRL por € | D7: CONFIRMADO | J7: ≈5,84 no início de out/2026 (longforecast.com/eur-to-brl)
A8: Inflação de tarifas (a.a.) | B8: 0.025 | C8: % | D8: PREMISSA | J8: Reajuste anual de tarifas de charter/cabine
A9: Inflação de custos (a.a.) | B9: 0.03 | C9: % | D9: PREMISSA | J9: Acordos salariais gregos +5% (2025) e +2% (2026); IBF +3,5% (2026)
A10: Taxa de desconto / hurdle (€, desalavancada) | B10: 0.1 | C10: % | D10: PREMISSA | J10: Ativo de nicho, 1º navio, operador novo: EURIBOR ~2,4% + prêmio de risco de ativo/operador
A11: Alíquota efetiva de IR sobre lucro (CFC Brasil) | B11: 0.34 | C11: % | D11: PREMISSA | J11: Lei 12.973/2014: lucro da controlada no exterior tributado anualmente no Brasil (IRPJ+CSLL 34%), com crédito do imposto pago lá fora. A tonnage tax local NÃO reduz a carga final. Validar com tributarista
A12: Comissão de broker/agência (charter e cabines de terceiros) | B12: 0.15 | C12: % | D12: ESTIMATIVA | J12: Prática de mercado: 10–20%; 15% central
A13: Receita líquida a bordo (margem bebidas premium/spa/extras) | B13: 150 | C13: €/pax-semana | D13: PREMISSA | J13: Margem sobre APA/consumo extra; conservador
A14: Ocupação média de leitos (alimentação/consumo) | B14: 0.9 | C14: % | D14: PREMISSA | J14: Grupos privados raramente lotam 100% dos leitos
A15: Alimentação de hóspedes (full board de luxo) | B15: 55 | C15: €/pax-dia | D15: ESTIMATIVA | J15: Benchmark de €45–65/pax-dia para small ship de luxo no Med (pesquisa OPEX)
A16: Lavanderia, amenities, consumíveis | B16: 10 | C16: €/pax-dia | D16: ESTIMATIVA | J16: €8–12/pax-dia
A17: Alimentação da tripulação | B17: 13 | C17: €/tripulante-dia | D17: ESTIMATIVA | J17: €12–15/tripulante-dia
... A25: Balloon no vencimento | B25: 0.3 | C25: % da dívida | D25: ESTIMATIVA | J25: Estrutura usual com balão
A27: B. CENÁRIOS (Conservador / Base / Otimista)
A28: Parâmetro | B28: Conservador | C28: Base | D28: Otimista | E28: Unidade | F28: Tipo | J28: Fonte / racional
A29: Semanas operadas por ano (regime) | B29: 20 | C29: 26 | D29: 30 | E29: semanas | F29: PREMISSA | J29: Temporada Med = ~28–30 semanas (abr–out). Variety opera Grécia sex a sex, abr–out
A30: …das quais: semanas QIMO (uso próprio) | B30: 6 | C30: 8 | D30: 12 | E30: semanas | F30: PREMISSA | J30: Volume QIMO a validar internamente — principal driver estratégico
A31: …das quais: semanas de venda de cabines | B31: 4 | C31: 4 | D31: 4 | E31: semanas | F31: PREMISSA | J31: Semanas de ombro vendidas por cabine
A32: Multiplicador de tarifa (vs. base de mercado) | B32: 0.9 | C32: 1 | D32: 1.1 | E32: x | F32: PREMISSA | J32: Captura a faixa baixa/alta das tarifas confirmadas
A33: Multiplicador de OPEX | B33: 1.1 | C33: 1 | D33: 0.95 | E33: x | F33: PREMISSA | J33: Faixa de OPEX da pesquisa: €5,2–6,8M p/ 72 pax
A34: Preço do MGO | B34: 1400 | C34: 1000 | D34: 750 | E34: US$/t | F34: CONFIRMADO (faixa) | J34: Pireu MGO: US$683–690/t (abr/26) → US$1.657/t (18/09/26, choque no Oriente Médio) (shipandbunker.com)
A35: Valor residual ano 10 — navio NOVO (% do CAPEX) | B35: 0.45 | C35: 0.55 | D35: 0.65 | E35: % | F35: ESTIMATIVA | J35: 45–65% em mercado normal; 25–40% em mercado estressado (pesquisa de estaleiros, §5)
A36: Valor residual ano 10 — navio USADO (% do CAPEX) | B36: 0.4 | C36: 0.5 | D36: 0.6 | E36: % | F36: ESTIMATIVA | J36: Navios pequenos antigos mantêm valor nominal (ex.: Galileo, 1992, ainda vale ~€7M)
A37: Ramp-up do ano 1 (% das semanas) | B37: 0.75 | C37: 0.85 | D37: 0.95 | E37: % | F37: PREMISSA | J37: Primeiro ano de operador novo
A38: Ocupação das semanas de venda por cabine | B38: 0.65 | C38: 0.75 | D38: 0.85 | E38: % | F38: PREMISSA
A40: C. OPÇÕES DE EMBARCAÇÃO (tamanho × modelo)
A41: Parâmetro | B41: C · 36 cab/72 pax · NOVO | C41: C · 36 cab/72 pax · USADO | D41: B · 24 cab/48 pax · NOVO | E41: B · 24 cab/48 pax · USADO | F41: A · 20 cab/40 pax · NOVO | G41: A · 18 cab/36 pax · USADO | H41: Unidade | I41: Tipo | J41: Fonte / racional
A42: Características
A43: Cabines | B43: 36 | C43: 36 | D43: 24 | E43: 24 | F43: 20 | G43: 18 | H43: un | I43: PREMISSA | J43: A/B/C do briefing. B = 24 cab/48 pax (≤49 pax: regime grego de iate profissional, Lei 4926/2022)
A44: Passageiros (leitos) | B44: 72 | C44: 72 | D44: 48 | E44: 48 | F44: 40 | G44: 36 | H44: pax | I44: PREMISSA
A45: Tripulação | B45: 28 | C45: 28 | D45: 20 | E45: 20 | F45: 17 | G45: 16 | H45: pessoas | I45: ESTIMATIVA | J45: Variety Voyager: 29–32 trip. p/ 72 pax; Galileo/Harmony V: 16–18 p/ 49 pax (CONFIRMADO)
A46: Comprimento (LOA) | B46: 62 | C46: 64 | D46: 50 | E46: 47 | F46: 45 | G46: 63 | H46: m | I46: ESTIMATIVA | J46: Usados: B = anúncio #1048634 (47 m); A = anúncio #1091239 (63 m, veleiro); C = estimativa (sem anúncio de 72 pax)
A47: CAPEX
A48: Preço de compra / contrato de construção | B48: =CAPEX_Construcao!$C$9 -> 41850000 | C48: 17000000 | D48: 28000000 | E48: 7000000 | F48: 24000000 | G48: 8300000 | H48: € | I48: ver fonte | J48: C_NOVO: luxury boutique, Turquia €34–46M (ESTIMATIVA; Voyager €29M em 2012 ≈ €38–42M hoje). C_USADO: ESTIMATIVA €12–25M (nenhum anúncio de 72 pax encontrado). B_USADO: CONFIRMADO anúncio #1048634 (€7,0M, 49 pax, bandeira grega). A_USADO: CONFIRMADO anúncio #1091239 (€8,3M, 36 pax, Brodosplit 2019). B/A_NOVO: ESTIMATIVA ~€580–600k/leito (navio menor = custo/leito maior)
A49: Retrofit / upgrade para padrão QIMO | B49: 0 | C49: 3000000 | D49: 0 | E49: 2500000 | F49: 0 | G49: 1000000 | H49: € | I49: ESTIMATIVA | J49: Cabines + áreas sociais + marina + docagem de entrada; ~€60–80k por cabine + sistemas
A50: Contingência (% de construção ou retrofit) | B50: =CAPEX_Construcao!$G$27 -> 0.08 | C50: 0.2 | D50: 0.08 | E50: 0.2 | F50: 0.08 | G50: 0.2 | H50: % | I50: ESTIMATIVA | J50: Construção: 7–10%; retrofit de navio usado: 15–25%
A51: Custos do armador / pré-operacionais | B51: =CAPEX_Construcao!$C$28+CAPEX_Construcao!$C$29 -> 2511000 | C51: 800000 | D51: 1700000 | E51: 600000 | F51: 1450000 | G51: 500000 | H51: € | I51: ESTIMATIVA | J51: Novo: ~6% (supervisão, projeto de interiores, OS&E, juros pré-entrega, legal). Usado: inspeção, legal, bandeira, entrega, OS&E, lançamento, capital de giro
A52: CAPEX TOTAL até a operação | B52: =B48+B49+IF(B49>0,B49,B48)*B50+B51 -> 47709000 | C52: =C48+C49+IF(C49>0,C49,C48)*C50+C51 -> 21400000 | D52: =D48+D49+IF(D49>0,D49,D48)*D50+D51 -> 31940000 | E52: =E48+E49+IF(E49>0,E49,E48)*E50+E51 -> 10600000 | F52: =F48+F49+IF(F49>0,F49,F48)*F50+F51 -> 27370000 | G52: =G48+G49+IF(G49>0,G49,G48)*G50+G51 -> 10000000 | H52: € | I52: fórmula | J52: Soma: preço + retrofit + contingência + custos do armador
A53: Desembolso no ano -2 | B53: 0.2 | C53: 0 | D53: 0.2 | E53: 0 | F53: 0.2 | G53: 0 | H53: % | I53: ESTIMATIVA | J53: Parcelas típicas: 20% assinatura / 20% corte de aço / 60% entrega (com refund guarantee)
A54: Desembolso no ano -1 | B54: 0.2 | C54: 0 | D54: 0.2 | E54: 0 | F54: 0.2 | G54: 0 | H54: % | I54: ESTIMATIVA
A55: Desembolso no ano 0 | B55: 0.6 | C55: 1 | D55: 0.6 | E55: 1 | F55: 0.6 | G55: 1 | H55: % | I55: ESTIMATIVA
A56: OPEX fixo anual (€/ano, base 2026)
A57: Tripulação (folha + encargos) | B57: =Tripulacao!$F$31 -> 1587500 | C57: =Tripulacao!$F$31 -> 1587500 | D57: =Tripulacao!$F$55 -> 1188466 | E57: =Tripulacao!$F$55 -> 1188466 | F57: =Tripulacao!$F$76 -> 1017524 | G57: =Tripulacao!$F$76 -> 1017524 | H57: €/ano | I57: link | J57: Aba Tripulação
A58: Seguro H&M | B58: =B52*Premissas!$B$18 -> 381672 | C58: =C52*Premissas!$B$18 -> 171200 | D58: =D52*Premissas!$B$18 -> 255520 | E58: =E52*Premissas!$B$18 -> 84800 | F58: =F52*Premissas!$B$18 -> 218960 | G58: =G52*Premissas!$B$18 -> 80000 | H58: €/ano | I58: fórmula | J58: CAPEX × % H&M
A59: P&I + responsabilidade de passageiros (Atenas/Reg. UE 392/2009) + war/LoH | B59: 125000 | C59: 125000 | D59: 90000 | E59: 90000 | F59: 75000 | G59: 75000 | H59: €/ano | I59: ESTIMATIVA | J59: P&I ~US$40–80/GT p/ pequenos navios de passageiros + €15–30k demais coberturas
A60: Manutenção e reparos (exceto docagem) | B60: 450000 | C60: 700000 | D60: 320000 | E60: 450000 | F60: 270000 | G60: 300000 | H60: €/ano | I60: ESTIMATIVA | J60: 2% do valor (navio novo) a 3–5% (10–15 anos) — yatco.com; garantia reduz anos 1–2 do novo
A61: Gestão técnica / ISM / DOC (terceirizada) | B61: 280000 | C61: 280000 | D61: 230000 | E61: 230000 | F61: 220000 | G61: 220000 | H61: €/ano | I61: ESTIMATIVA | J61: Navio de passageiros com ISM/ISPS/MLC: €220–350k
A62: Hibernação de inverno (berço, energia, segurança) | B62: 80000 | C62: 80000 | D62: 60000 | E62: 60000 | F62: 50000 | G62: 50000 | H62: €/ano | I62: ESTIMATIVA | J62: €40–120k
A63: Starlink + TI de bordo | B63: 60000 | C63: 60000 | D63: 45000 | E63: 45000 | F63: 40000 | G63: 40000 | H63: €/ano | I63: CONFIRMADO (planos) | J63: Starlink Maritime US$250–2.150/mês por terminal + hardware/gestão
A64: Licenças, bandeira, classe, auditorias | B64: 80000 | C64: 80000 | D64: 65000 | E64: 65000 | F64: 55000 | G64: 55000 | H64: €/ano | I64: ESTIMATIVA | J64: Classe €30–60k + bandeira/ISM/PSC/MLC €30–60k
A65: Reposição de enxoval / FF&E | B65: 80000 | C65: 100000 | D65: 55000 | E65: 70000 | F65: 45000 | G65: 50000 | H65: €/ano | I65: ESTIMATIVA | J65: €80–150k p/ 72 pax
A66: Marketing B2B e vendas de charter (feiras, brokers, site) | B66: 120000 | C66: 120000 | D66: 90000 | E66: 90000 | F66: 80000 | G66: 80000 | H66: €/ano | I66: PREMISSA | J66: Necessário p/ vender as semanas sem QIMO
A67: G&A da SPV (contabilidade, auditoria, jurídico, diretor local) | B67: 150000 | C67: 150000 | D67: 130000 | E67: 130000 | F67: 120000 | G67: 120000 | H67: €/ano | I67: PREMISSA
A68: OPEX FIXO TOTAL | B68: =SUM(B57:B67) -> 3394172 | C68: =SUM(C57:C67) -> 3453700 | D68: =SUM(D57:D67) -> 2528986 | E68: =SUM(E57:E67) -> 2503266 | F68: =SUM(F57:F67) -> 2191484 | G68: =SUM(G57:G67) -> 2087524 | H68: €/ano | I68: fórmula
A69: OPEX variável por semana operada
A70: Consumo de combustível | B70: 25 | C70: 25 | D70: 18 | E70: 18 | F70: 16 | G70: 15 | H70: t/semana | I70: ESTIMATIVA | J70: 60–68 m: 3–4 t/dia (4–6 h navegando/dia + hotel 24h) ≈ 22–28 t/semana
A71: Alimentação hóspedes | B71: =B44*7*Premissas!$B$14*Premissas!$B$15 -> 24948 | C71: =C44*7*Premissas!$B$14*Premissas!$B$15 -> 24948 | D71: =D44*7*Premissas!$B$14*Premissas!$B$15 -> 16632 | E71: =E44*7*Premissas!$B$14*Premissas!$B$15 -> 16632 | F71: =F44*7*Premissas!$B$14*Premissas!$B$15 -> 13860 | G71: =G44*7*Premissas!$B$14*Premissas!$B$15 -> 12474 | H71: €/semana | I71: fórmula | J71: pax × 7 × ocupação × €/pax-dia
A72: Consumíveis/lavanderia | B72: =B44*7*Premissas!$B$14*Premissas!$B$16 -> 4536 | C72: =C44*7*Premissas!$B$14*Premissas!$B$16 -> 4536 | D72: =D44*7*Premissas!$B$14*Premissas!$B$16 -> 3024 | E72: =E44*7*Premissas!$B$14*Premissas!$B$16 -> 3024 | F72: =F44*7*Premissas!$B$14*Premissas!$B$16 -> 2520 | G72: =G44*7*Premissas!$B$14*Premissas!$B$16 -> 2268 | H72: €/semana | I72: fórmula
A73: Alimentação tripulação | B73: =B45*7*Premissas!$B$17 -> 2548 | C73: =C45*7*Premissas!$B$17 -> 2548 | D73: =D45*7*Premissas!$B$17 -> 1820 | E73: =E45*7*Premissas!$B$17 -> 1820 | F73: =F45*7*Premissas!$B$17 -> 1547 | G73: =G45*7*Premissas!$B$17 -> 1456 | H73: €/semana | I73: fórmula
A74: Lubrificantes, água, outros | B74: 1500 | C74: 1500 | D74: 1200 | E74: 1200 | F74: 1000 | G74: 1000 | H74: €/semana | I74: ESTIMATIVA
A75: VARIÁVEL EXCETO COMBUSTÍVEL | B75: =SUM(B71:B74) -> 33532 | C75: =SUM(C71:C74) -> 33532 | D75: =SUM(D71:D74) -> 22676 | E75: =SUM(E71:E74) -> 22676 | F75: =SUM(F71:F74) -> 18927 | G75: =SUM(G71:G74) -> 17198 | H75: €/semana | I75: fórmula | J75: Taxas portuárias, taxa de cruzeiro grega (€20 Santorini/Mykonos) e bebidas = repasse ao fretador (APA), neutros no resultado
A76: Receita
A77: Tarifa de charter de mercado (média da temporada, sem IVA/APA) | B77: 300000 | C77: 270000 | D77: 170000 | E77: 150000 | F77: 120000 | G77: 105000 | H77: €/semana | I77: CONFIRMADO (faixas) | J77: Variety Voyager €247.650–342.000/sem (broker); Galileo €92–167k; Harmony V €129–173k; Callisto (34 pax) a partir de €115k; mini-cruisers croatas de 36–38 pax €74–98k. Novo QIMO com prêmio vs. Voyager (2012)
A78: Preço por passageiro/semana (venda de cabine, líquido de taxas portuárias) | B78: 4800 | C78: 4300 | D78: 4500 | E78: 4000 | F78: 4200 | G78: 3600 | H78: €/pax | I78: CONFIRMADO (faixas) | J78: Variety Grécia US$2.702–4.655; Sea Cloud Spirit US$5.400–5.790; Emerald Azzurra US$6.984–10.821; SeaDream US$11,5–16,5k
A79: CAPEX de manutenção e docagens (€ base 2026)
A80: Docagem intermediária — ano 3 | B80: 350000 | C80: 450000 | D80: 250000 | E80: 350000 | F80: 220000 | G80: 250000 | H80: € | I80: ESTIMATIVA | J80: Navio de passageiros de 60 m: €0,3–0,6M (intermediária)
A81: Docagem especial (5 anos) — ano 5 | B81: 800000 | C81: 1000000 | D81: 600000 | E81: 750000 | F81: 500000 | G81: 550000 | H81: € | I81: ESTIMATIVA | J81: €0,6–1,2M (especial, eixos, hélices, pintura, LSA)
A82: Docagem intermediária — ano 8 | B82: 400000 | C82: 500000 | D82: 300000 | E82: 400000 | F82: 250000 | G82: 300000 | H82: € | I82: ESTIMATIVA
A83: Docagem especial — ano 10 | B83: 1000000 | C83: 1100000 | D83: 700000 | E83: 850000 | F83: 600000 | G83: 600000 | H83: € | I83: ESTIMATIVA
A84: CAPEX de manutenção recorrente (% do CAPEX/ano) | B84: 0.005 | C84: 0.01 | D84: 0.005 | E84: 0.01 | F84: 0.005 | G84: 0.01 | H84: % | I84: ESTIMATIVA
A85: Refurb de hotelaria no ano 6 (% do CAPEX) | B85: 0.04 | C85: 0.04 | D85: 0.04 | E85: 0.04 | F85: 0.04 | G85: 0.04 | H85: % | I85: PREMISSA | J85: Ciclo de renovação de produto de luxo

Sheet Tripulacao
A1: Tripulação — quadro, salários e custo anual
A2: Salários brutos mensais (€). Postos-chave pagos 12 meses × fator de rodízio; sazonais pagos por 'meses sazonais'. Fonte: UKSA Superyacht Salary Guide 2025, Quay Crew, escalas de cruzeiro (Celestyal) — ver Fontes.
A4: Configuração C — 36 cabines / 72 pax
A5: Função | B5: Qtd | C5: €/mês | D5: Posto-chave (1=sim) | E5: Meses pagos | F5: Custo anual (€)
A6: Comandante (Master) | B6: 1 | C6: 12000 | D6: 1 | E6: =IF(D6=1,12*Premissas!$B$21,Premissas!$B$22) -> 15.6 | F6: =B6*C6*E6 -> 187200
A7: Imediato (Chief Officer) | B7: 1 | C7: 7000 | D7: 1 | E7: =IF(D7=1,12*Premissas!$B$21,Premissas!$B$22) -> 15.6 | F7: =B7*C7*E7 -> 109200
A8: 2º Oficial / Navegação | B8: 1 | C8: 4500 | D8: 0 | E8: =IF(D8=1,12*Premissas!$B$21,Premissas!$B$22) -> 8 | F8: =B8*C8*E8 -> 36000
A9: Contramestre (Bosun) | B9: 1 | C9: 3500 | D9: 0 | E9: =IF(D9=1,12*Premissas!$B$21,Premissas!$B$22) -> 8 | F9: =B9*C9*E9 -> 28000
A10: Marinheiros / tender drivers | B10: 2 | C10: 2800 | D10: 0 | E10: =IF(D10=1,12*Premissas!$B$21,Premissas!$B$22) -> 8 | F10: =B10*C10*E10 -> 44800
A11: Chefe de Máquinas | B11: 1 | C11: 9000 | D11: 1 | E11: =IF(D11=1,12*Premissas!$B$21,Premissas!$B$22) -> 15.6 | F11: =B11*C11*E11 -> 140400
A12: 2º Maquinista | B12: 1 | C12: 5500 | D12: 1 | E12: =IF(D12=1,12*Premissas!$B$21,Premissas!$B$22) -> 15.6 | F12: =B12*C12*E12 -> 85800
A13: 3º Maquinista / ETO | B13: 1 | C13: 4500 | D13: 0 | E13: =IF(D13=1,12*Premissas!$B$21,Premissas!$B$22) -> 8 | F13: =B13*C13*E13 -> 36000
A14: Hotel Manager | B14: 1 | C14: 6500 | D14: 1 | E14: =IF(D14=1,12*Premissas!$B$21,Premissas!$B$22) -> 15.6 | F14: =B14*C14*E14 -> 101400
A15: Recepção / Purser | B15: 1 | C15: 3000 | D15: 0 | E15: =IF(D15=1,12*Premissas!$B$21,Premissas!$B$22) -> 8 | F15: =B15*C15*E15 -> 24000
A16: Líder de atividades / experiências | B16: 1 | C16: 4000 | D16: 0 | E16: =IF(D16=1,12*Premissas!$B$21,Premissas!$B$22) -> 8 | F16: =B16*C16*E16 -> 32000
A17: Esportes aquáticos / guia | B17: 1 | C17: 2800 | D17: 0 | E17: =IF(D17=1,12*Premissas!$B$21,Premissas!$B$22) -> 8 | F17: =B17*C17*E17 -> 22400
... A27: Lavanderia | B27: 1 | C27: 1800 | D27: 0 | E27: =IF(D27=1,12*Premissas!$B$21,Premissas!$B$22) -> 8 | F27: =B27*C27*E27 -> 14400
A28: Folha bruta | B28: =SUM(B6:B27) -> 28 | F28: =SUM(F6:F27) -> 1250000
A29: Encargos operacionais (viagens, treinamento, uniformes, recrutamento) | F29: =F28*Premissas!$B$19 -> 275000
A30: Encargos sociais da bandeira | F30: =F28*Premissas!$B$20 -> 62500
A31: CUSTO ANUAL TOTAL DA TRIPULAÇÃO | F31: =SUM(F28:F30) -> 1587500
A33: Configuração B — 24 cabines / 48 pax
A34: Função | B34: Qtd | C34: €/mês | D34: Posto-chave (1=sim) | E34: Meses pagos | F34: Custo anual (€)
A35: Comandante (Master) | B35: 1 | C35: 10000 | D35: 1 | E35: =IF(D35=1,12*Premissas!$B$21,Premissas!$B$22) -> 15.6 | F35: =B35*C35*E35 -> 156000
A36: Imediato (Chief Officer) | B36: 1 | C36: 6000 | D36: 1 | E36: =IF(D36=1,12*Premissas!$B$21,Premissas!$B$22) -> 15.6 | F36: =B36*C36*E36 -> 93600
A37: Contramestre (Bosun) | B37: 1 | C37: 3200 | D37: 0 | E37: =IF(D37=1,12*Premissas!$B$21,Premissas!$B$22) -> 8 | F37: =B37*C37*E37 -> 25600
A38: Marinheiros / tender drivers | B38: 2 | C38: 2600 | D38: 0 | E38: =IF(D38=1,12*Premissas!$B$21,Premissas!$B$22) -> 8 | F38: =B38*C38*E38 -> 41600
A39: Chefe de Máquinas | B39: 1 | C39: 8000 | D39: 1 | E39: =IF(D39=1,12*Premissas!$B$21,Premissas!$B$22) -> 15.6 | F39: =B39*C39*E39 -> 124800
A40: 2º Maquinista | B40: 1 | C40: 5000 | D40: 1 | E40: =IF(D40=1,12*Premissas!$B$21,Premissas!$B$22) -> 15.6 | F40: =B40*C40*E40 -> 78000
A41: Hotel Manager | B41: 1 | C41: 5500 | D41: 1 | E41: =IF(D41=1,12*Premissas!$B$21,Premissas!$B$22) -> 15.6 | F41: =B41*C41*E41 -> 85800
A42: Recepção / Purser | B42: 1 | C42: 2800 | D42: 0 | E42: =IF(D42=1,12*Premissas!$B$21,Premissas!$B$22) -> 8 | F42: =B42*C42*E42 -> 22400
A43: Atividades / esportes aquáticos | B43: 1 | C43: 3000 | D43: 0 | E43: =IF(D43=1,12*Premissas!$B$21,Premissas!$B$22) -> 8 | F43: =B43*C43*E43 -> 24000
A44: Chef executivo | B44: 1 | C44: 6000 | D44: 1 | E44: =IF(D44=1,12*Premissas!$B$21,Premissas!$B$22) -> 15.6 | F44: =B44*C44*E44 -> 93600
A45: Sous chef | B45: 1 | C45: 4000 | D45: 0 | E45: =IF(D45=1,12*Premissas!$B$21,Premissas!$B$22) -> 8 | F45: =B45*C45*E45 -> 32000
A46: Cozinheiro | B46: 1 | C46: 2800 | D46: 0 | E46: =IF(D46=1,12*Premissas!$B$21,Premissas!$B$22) -> 8 | F46: =B46*C46*E46 -> 22400
... A51: Camareiros | B51: 2 | C51: 2100 | D51: 0 | E51: =IF(D51=1,12*Premissas!$B$21,Premissas!$B$22) -> 8 | F51: =B51*C51*E51 -> 33600
A52: Folha bruta | B52: =SUM(B35:B51) -> 20 | F52: =SUM(F35:F51) -> 935800
A53: Encargos operacionais (viagens, treinamento, uniformes, recrutamento) | F53: =F52*Premissas!$B$19 -> 205876
A54: Encargos sociais da bandeira | F54: =F52*Premissas!$B$20 -> 46790
A55: CUSTO ANUAL TOTAL DA TRIPULAÇÃO | F55: =SUM(F52:F54) -> 1188466
A57: Configuração A — 18–20 cabines / 36–40 pax
A58: Função | B58: Qtd | C58: €/mês | D58: Posto-chave (1=sim) | E58: Meses pagos | F58: Custo anual (€)
A59: Comandante (Master) | B59: 1 | C59: 9000 | D59: 1 | E59: =IF(D59=1,12*Premissas!$B$21,Premissas!$B$22) -> 15.6 | F59: =B59*C59*E59 -> 140400
A60: Imediato (Chief Officer) | B60: 1 | C60: 5500 | D60: 1 | E60: =IF(D60=1,12*Premissas!$B$21,Premissas!$B$22) -> 15.6 | F60: =B60*C60*E60 -> 85800
A61: Marinheiros / tender drivers | B61: 2 | C61: 2600 | D61: 0 | E61: =IF(D61=1,12*Premissas!$B$21,Premissas!$B$22) -> 8 | F61: =B61*C61*E61 -> 41600
A62: Chefe de Máquinas | B62: 1 | C62: 7500 | D62: 1 | E62: =IF(D62=1,12*Premissas!$B$21,Premissas!$B$22) -> 15.6 | F62: =B62*C62*E62 -> 117000
A63: 2º Maquinista | B63: 1 | C63: 4500 | D63: 1 | E63: =IF(D63=1,12*Premissas!$B$21,Premissas!$B$22) -> 15.6 | F63: =B63*C63*E63 -> 70200
A64: Hotel Manager | B64: 1 | C64: 5000 | D64: 1 | E64: =IF(D64=1,12*Premissas!$B$21,Premissas!$B$22) -> 15.6 | F64: =B64*C64*E64 -> 78000
A65: Atividades / esportes aquáticos | B65: 1 | C65: 2800 | D65: 0 | E65: =IF(D65=1,12*Premissas!$B$21,Premissas!$B$22) -> 8 | F65: =B65*C65*E65 -> 22400
A66: Chef executivo | B66: 1 | C66: 5500 | D66: 1 | E66: =IF(D66=1,12*Premissas!$B$21,Premissas!$B$22) -> 15.6 | F66: =B66*C66*E66 -> 85800
A67: Sous chef | B67: 1 | C67: 3800 | D67: 0 | E67: =IF(D67=1,12*Premissas!$B$21,Premissas!$B$22) -> 8 | F67: =B67*C67*E67 -> 30400
A68: Cozinheiro | B68: 1 | C68: 2700 | D68: 0 | E68: =IF(D68=1,12*Premissas!$B$21,Premissas!$B$22) -> 8 | F68: =B68*C68*E68 -> 21600
A69: Maître / Head waiter | B69: 1 | C69: 2800 | D69: 0 | E69: =IF(D69=1,12*Premissas!$B$21,Premissas!$B$22) -> 8 | F69: =B69*C69*E69 -> 22400
A70: Garçons | B70: 2 | C70: 2200 | D70: 0 | E70: =IF(D70=1,12*Premissas!$B$21,Premissas!$B$22) -> 8 | F70: =B70*C70*E70 -> 35200
... A72: Camareiros | B72: 2 | C72: 2000 | D72: 0 | E72: =IF(D72=1,12*Premissas!$B$21,Premissas!$B$22) -> 8 | F72: =B72*C72*E72 -> 32000
A73: Folha bruta | B73: =SUM(B59:B72) -> 17 | F73: =SUM(F59:F72) -> 801200
A74: Encargos operacionais (viagens, treinamento, uniformes, recrutamento) | F74: =F73*Premissas!$B$19 -> 176264
A75: Encargos sociais da bandeira | F75: =F73*Premissas!$B$20 -> 40060
A76: CUSTO ANUAL TOTAL DA TRIPULAÇÃO | F76: =SUM(F73:F75) -> 1017524
A78: Nota: modelo 'superyacht-style' (tripulação europeia/internacional). Hotelaria em escalas de cruzeiro (Filipinas/Indonésia) reduz a folha de hotel em 30–40%, com risco de nível de serviço. Bandeira grega com tripulação grega: +€0,2–0,4M/ano (NAT 25–30%).

Sheet CAPEX_Construcao
A1: CAPEX de construção nova — 72 pax / ~60–65 m — três padrões
A2: Custo-base por região a partir de €/leito (pesquisa de estaleiros). Distribuição percentual = ESTIMATIVA (não há fonte pública de breakdown). Editar células azuis.
A4: 1. Custo de construção (estaleiro turco, base) por padrão
A5: Item | B5: Premium funcional | C5: Luxury boutique | D5: Ultra-luxury | F5: % PF | G5: % LB | H5: % UL
A6: Leitos | B6: =Premissas!$B$44 -> 72 | C6: =Premissas!$B$44 -> 72 | D6: =Premissas!$B$44 -> 72
A7: Custo-base por leito — referência Holanda (€) | B7: 560000 | C7: 775000 | D7: 1125000 | F7: Faixas: €520–600k / €700–850k / €1,0–1,25M por leito (ESTIMATIVA, mediana dos comparáveis ~€570k)
A8: Índice de custo da região escolhida (Turquia) | B8: 0.75 | C8: 0.75 | D8: 0.75 | F8: Turquia 0,65–0,80 vs. Holanda = 1,00 (ver tabela regional abaixo)
A9: Preço de contrato do estaleiro (antes de contingência) | B9: =B6*B7*B8 -> 30240000 | C9: =C6*C7*C8 -> 41850000 | D9: =D6*D7*D8 -> 60750000
A11: Breakdown do preço de contrato
A12: Projeto naval, engenharia e design de interiores | B12: =B$9*F12 -> 1512000 | C12: =C$9*G12 -> 2511000 | D12: =D$9*H12 -> 4252500 | F12: 0.05 | G12: 0.06 | H12: 0.07
A13: Casco e superestrutura | B13: =B$9*F13 -> 6652800 | C13: =C$9*G13 -> 7951500 | D13: =D$9*H13 -> 9720000 | F13: 0.22 | G13: 0.19 | H13: 0.16
A14: Propulsão e máquinas (motores, eixos, estabilizadores, thrusters) | B14: =B$9*F14 -> 3931200 | C14: =C$9*G14 -> 5022000 | D14: =D$9*H14 -> 6682500 | F14: 0.13 | G14: 0.12 | H14: 0.11
A15: Geradores e sistema elétrico (híbrido opcional) | B15: =B$9*F15 -> 2721600 | C15: =C$9*G15 -> 3766500 | D15: =D$9*H15 -> 5467500 | F15: 0.09 | G15: 0.09 | H15: 0.09
A16: HVAC, tubulações, água, esgoto e sistemas | B16: =B$9*F16 -> 3024000 | C16: =C$9*G16 -> 4185000 | D16: =D$9*H16 -> 5467500 | F16: 0.1 | G16: 0.1 | H16: 0.09
A17: Interiores e hotelaria (cabines, áreas sociais, marcenaria, teca) | B17: =B$9*F17 -> 6652800 | C17: =C$9*G17 -> 10462500 | D17: =D$9*H17 -> 17617500 | F17: 0.22 | G17: 0.25 | H17: 0.29
A18: Cozinha, lavanderia e equipamentos de hotel | B18: =B$9*F18 -> 907200 | C18: =C$9*G18 -> 1255500 | D18: =D$9*H18 -> 1822500 | F18: 0.03 | G18: 0.03 | H18: 0.03
A19: Navegação, comunicações, TI/AV, Starlink | B19: =B$9*F19 -> 907200 | C19: =C$9*G19 -> 1255500 | D19: =D$9*H19 -> 1822500 | F19: 0.03 | G19: 0.03 | H19: 0.03
A20: Segurança: salvatagem (LSA), combate a incêndio, MES | B20: =B$9*F20 -> 1209600 | C20: =C$9*G20 -> 1464750 | D20: =D$9*H20 -> 1822500 | F20: 0.04 | G20: 0.035 | H20: 0.03
A21: Classe, bandeira, certificações, provas de mar | B21: =B$9*F21 -> 604800 | C21: =C$9*G21 -> 837000 | D21: =D$9*H21 -> 911250 | F21: 0.02 | G21: 0.02 | H21: 0.015
A22: Tenders, Zodiacs, plataforma de marina, water toys | B22: =B$9*F22 -> 604800 | C22: =C$9*G22 -> 1046250 | D22: =D$9*H22 -> 1822500 | F22: 0.02 | G22: 0.025 | H22: 0.03
A23: Enxoval e operacional (OS&E: roupa de cama, louça, uniformes, peças) | B23: =B$9*F23 -> 604800 | C23: =C$9*G23 -> 837000 | D23: =D$9*H23 -> 1518750 | F23: 0.02 | G23: 0.02 | H23: 0.025
A24: Equipe de supervisão do armador e custos de obra | B24: =B$9*F24 -> 907200 | C24: =C$9*G24 -> 1255500 | D24: =D$9*H24 -> 1822500 | F24: 0.03 | G24: 0.03 | H24: 0.03
A25: Soma (verificação = 100%) | B25: =SUM(B12:B24) -> 30240000 | C25: =SUM(C12:C24) -> 41850000 | D25: =SUM(D12:D24) -> 60750000 | F25: =SUM(F12:F24) -> 1 | G25: =SUM(G12:G24) -> 1 | H25: =SUM(H12:H24) -> 1
A27: Contingência (% do contrato) | B27: =B9*F27 -> 2116800 | C27: =C9*G27 -> 3348000 | D27: =D9*H27 -> 6075000 | F27: 0.07 | G27: 0.08 | H27: 0.1
A28: Juros pré-entrega, legal, refund guarantee, seguros de construção (%) | B28: =B9*F28 -> 907200 | C28: =C9*G28 -> 1255500 | D28: =D9*H28 -> 1822500 | F28: 0.03 | G28: 0.03 | H28: 0.03
A29: Pré-operacional (recrutamento, treinamento, viagem inaugural, lançamento, capital de giro) (%) | B29: =B9*F29 -> 907200 | C29: =C9*G29 -> 1255500 | D29: =D9*H29 -> 1822500 | F29: 0.03 | G29: 0.03 | H29: 0.03
A30: CUSTO TOTAL ATÉ A ENTRADA EM OPERAÇÃO | B30: =B9+B27+B28+B29 -> 34171200 | C30: =C9+C27+C28+C29 -> 47709000 | D30: =D9+D27+D28+D29 -> 70470000
A31: Custo total por leito | B31: =B30/B6 -> 474600 | C31: =C30/C6 -> 662625 | D31: =D30/D6 -> 978750
A32: Prazo contrato → entrega (meses) | B32: 22–26 | C32: 24–30 | D32: 28–36
A33: Prazo decisão → 1ª temporada (meses) | B33: 30–36 | C33: 32–40 | D33: 36–44
A35: 2. Custo total por região (Luxury boutique, 72 pax)
A36: Região | B36: Índice baixo | C36: Índice alto | D36: Custo total baixo | F36: Custo total alto | G36: Observação
A37: Holanda / Noruega / Alemanha | B37: 1 | C37: 1 | D37: =$C$30/$C$8*B37 -> 63612000 | F37: =$C$30/$C$8*C37 -> 63612000 | G37: Referência (De Hoop: Silver Origin €680k/leito)
A38: Itália | B38: 0.95 | C38: 1.05 | D38: =$C$30/$C$8*B38 -> 60431400 | F38: =$C$30/$C$8*C38 -> 66792600 | G38: Mercado premium de superiates
A39: Espanha / Portugal | B39: 0.8 | C39: 0.9 | D39: =$C$30/$C$8*B39 -> 50889600 | F39: =$C$30/$C$8*C39 -> 57250800 | G39: West Sea: €357–400k/leito em navios de 176–196 pax
A40: Croácia / Grécia | B40: 0.75 | C40: 0.9 | D40: =$C$30/$C$8*B40 -> 47709000 | F40: =$C$30/$C$8*C40 -> 57250800 | G40: Brodosplit (risco financeiro); Voyager feito em Perama
A41: Turquia | B41: 0.65 | C41: 0.8 | D41: =$C$30/$C$8*B41 -> 41347800 | F41: =$C$30/$C$8*C41 -> 50889600 | G41: Mão de obra ~40% da europeia; equipamentos a preço global
A42: Vietnã / China | B42: 0.6 | C42: 0.75 | D42: =$C$30/$C$8*B42 -> 38167200 | F42: =$C$30/$C$8*C42 -> 47709000 | G42: +€0,5–1M de viagem de entrega até o Med

Sheet Charter
A1: Modelo 3 — Charter de terceiros: custo efetivo para a QIMO
A2: Tarifas CONFIRMADAS por faixas (brokers/Variety). APA, IVA e gorjetas = práticas de mercado confirmadas. Excursões = ESTIMATIVA.
A4: Navio 72 pax / 36 cab (ex.: Variety Voyager)
A5: Componente | B5: Conservador | C5: Base | D5: Premium
A6: Cabines / passageiros | B6: 36 | C6: 72
A7: Tarifa de full charter (€/semana) | B7: 247650 | C7: 280000 | D7: 342000 | F7: Broker: €247.650 (baixa) – €342.000 (alta) + despesas; Variety direto via Goolets: US$213k (jul/2025)
A8: APA — provisões, bebidas, combustível extra, taxas portuárias (% da tarifa) | B8: 0.3 | C8: 0.32 | D8: 0.35 | F8: 30–40% da tarifa (CONFIRMADO, prática de broker)
A9: IVA sobre charter (Grécia efetivo) | B9: 0.12 | C9: 0.12 | D9: 0.12 | F9: Grécia ~12% efetivo; Croácia 13%; Itália 22%
A10: Gorjetas da tripulação (% da tarifa) | B10: 0.08 | C10: 0.1 | D10: 0.12 | F10: Diretriz MYBA/brokers: 5–15%, padrão 10%
A11: Excursões/experiências em terra (€/pax/semana) | B11: 300 | C11: 450 | D11: 700 | F11: ESTIMATIVA: 5 dias × €60–140/pax
A12: Posicionamento / mínimos de consumo (€/semana) | B12: 0 | C12: 0 | D12: 15000 | F12: Normalmente zero dentro da área de operação do navio; cobrado fora dela
A13: CUSTO DO NAVIO (tarifa + APA + IVA) | B13: =B7*(1+B8+B9)+B12 -> 351663 | C13: =C7*(1+C8+C9)+C12 -> 403200 | D13: =D7*(1+D8+D9)+D12 -> 517740
A14: CUSTO TOTAL DA SEMANA (+ gorjetas + excursões) | B14: =B13+B7*B10+B11*$C$6 -> 393075 | C14: =C13+C7*C10+C11*$C$6 -> 463600 | D14: =D13+D7*D10+D11*$C$6 -> 609180
A15: …por cabine | B15: =B14/$B$6 -> 10918.75 | C15: =C14/$B$6 -> 12877.778 | D15: =D14/$B$6 -> 16921.667
A16: …por passageiro | B16: =B14/$C$6 -> 5459.375 | C16: =C14/$C$6 -> 6438.8889 | D16: =D14/$C$6 -> 8460.8333
A18: Navio ~48–49 pax / 24 cab (ex.: Galileo, Harmony V)
A19: Componente | B19: Conservador | C19: Base | D19: Premium
A20: Cabines / passageiros | B20: 24 | C20: 49
A21: Tarifa de full charter (€/semana) | B21: 92000 | C21: 135000 | D21: 172900 | F21: Galileo €92k (mar–abr) / €121,9k / €166,7k (mai–jun, set); Harmony V €129,4–172,9k
A22: APA — provisões, bebidas, combustível extra, taxas portuárias (% da tarifa) | B22: 0.3 | C22: 0.32 | D22: 0.35 | F22: 30–40% da tarifa (CONFIRMADO, prática de broker)
A23: IVA sobre charter (Grécia efetivo) | B23: 0.12 | C23: 0.12 | D23: 0.12 | F23: Grécia ~12% efetivo; Croácia 13%; Itália 22%
A24: Gorjetas da tripulação (% da tarifa) | B24: 0.08 | C24: 0.1 | D24: 0.12 | F24: Diretriz MYBA/brokers: 5–15%, padrão 10%
A25: Excursões/experiências em terra (€/pax/semana) | B25: 300 | C25: 450 | D25: 700 | F25: ESTIMATIVA: 5 dias × €60–140/pax
A26: Posicionamento / mínimos de consumo (€/semana) | B26: 0 | C26: 0 | D26: 15000 | F26: Normalmente zero dentro da área de operação do navio; cobrado fora dela
A27: CUSTO DO NAVIO (tarifa + APA + IVA) | B27: =B21*(1+B22+B23)+B26 -> 130640 | C27: =C21*(1+C22+C23)+C26 -> 194400 | D27: =D21*(1+D22+D23)+D26 -> 269163
A28: CUSTO TOTAL DA SEMANA (+ gorjetas + excursões) | B28: =B27+B21*B24+B25*$C$20 -> 152700 | C28: =C27+C21*C24+C25*$C$20 -> 229950 | D28: =D27+D21*D24+D25*$C$20 -> 324211
A29: …por cabine | B29: =B28/$B$20 -> 6362.5 | C29: =C28/$B$20 -> 9581.25 | D29: =D28/$B$20 -> 13508.792
A30: …por passageiro | B30: =B28/$C$20 -> 3116.3265 | C30: =C28/$C$20 -> 4692.8571 | D30: =D28/$C$20 -> 6616.551
A32: Navio ~36–40 pax / 18–20 cab (Croácia / Callisto)
A33: Componente | B33: Conservador | C33: Base | D33: Premium
A34: Cabines / passageiros | B34: 18 | C34: 36
A35: Tarifa de full charter (€/semana) | B35: 76000 | C35: 95000 | D35: 115000 | F35: Karizma €84–95k; Lastavica €76–87k; Callisto a partir de €115k
A36: APA — provisões, bebidas, combustível extra, taxas portuárias (% da tarifa) | B36: 0.3 | C36: 0.32 | D36: 0.35 | F36: 30–40% da tarifa (CONFIRMADO, prática de broker)
A37: IVA sobre charter (Grécia efetivo) | B37: 0.12 | C37: 0.12 | D37: 0.12 | F37: Grécia ~12% efetivo; Croácia 13%; Itália 22%
A38: Gorjetas da tripulação (% da tarifa) | B38: 0.08 | C38: 0.1 | D38: 0.12 | F38: Diretriz MYBA/brokers: 5–15%, padrão 10%
A39: Excursões/experiências em terra (€/pax/semana) | B39: 300 | C39: 450 | D39: 700 | F39: ESTIMATIVA: 5 dias × €60–140/pax
A40: Posicionamento / mínimos de consumo (€/semana) | B40: 0 | C40: 0 | D40: 15000 | F40: Normalmente zero dentro da área de operação do navio; cobrado fora dela
A41: CUSTO DO NAVIO (tarifa + APA + IVA) | B41: =B35*(1+B36+B37)+B40 -> 107920 | C41: =C35*(1+C36+C37)+C40 -> 136800 | D41: =D35*(1+D36+D37)+D40 -> 184050
A42: CUSTO TOTAL DA SEMANA (+ gorjetas + excursões) | B42: =B41+B35*B38+B39*$C$34 -> 124800 | C42: =C41+C35*C38+C39*$C$34 -> 162500 | D42: =D41+D35*D38+D39*$C$34 -> 223050
A43: …por cabine | B43: =B42/$B$34 -> 6933.3333 | C43: =C42/$B$34 -> 9027.7778 | D43: =D42/$B$34 -> 12391.667
A44: …por passageiro | B44: =B42/$C$34 -> 3466.6667 | C44: =C42/$C$34 -> 4513.8889 | D44: =D42/$C$34 -> 6195.8333
A46: Nota: nas comparações Buy × Build × Charter usa-se somente a TARIFA (sem APA/IVA/gorjetas/excursões), porque esses itens existem igualmente com navio próprio (repasse) — comparação justa entre os modelos.

Sheet Projecao
A1: Projeção de 10 anos — 6 opções × 3 cenários (desalavancado)
A2: Colunas: anos -2 e -1 = construção; 0 = entrega/compra; 1–10 = operação. Valores nominais. Todas as linhas são fórmulas ligadas às Premissas.
B4: C · 36 cab/72 pax · NOVO — cenário Conservador
B5: Ano | C5: -2 | D5: -1 | E5: 0 | F5: 1 | G5: 2 | H5: 3 | I5: 4 | J5: 5 | K5: 6 | L5: 7 | M5: 8 | N5: 9 | O5: 10
B6: Semanas operadas | C6: =IF(C$5>=1,Premissas!$B$29*IF(C$5=1,Premissas!$B$37,1),0) -> 0 | D6: =IF(D$5>=1,Premissas!$B$29*IF(D$5=1,Premissas!$B$37,1),0) -> 0 | E6: =IF(E$5>=1,Premissas!$B$29*IF(E$5=1,Premissas!$B$37,1),0) -> 0 | F6: =IF(F$5>=1,Premissas!$B$29*IF(F$5=1,Premissas!$B$37,1),0) -> 15 | G6: =IF(G$5>=1,Premissas!$B$29*IF(G$5=1,Premissas!$B$37,1),0) -> 20 | H6: =IF(H$5>=1,Premissas!$B$29*IF(H$5=1,Premissas!$B$37,1),0) -> 20 | I6: =IF(I$5>=1,Premissas!$B$29*IF(I$5=1,Premissas!$B$37,1),0) -> 20 | J6: =IF(J$5>=1,Premissas!$B$29*IF(J$5=1,Premissas!$B$37,1),0) -> 20 | ... O6: =IF(O$5>=1,Premissas!$B$29*IF(O$5=1,Premissas!$B$37,1),0) -> 20
B7: Semanas QIMO | C7: =MIN(C6,Premissas!$B$30) -> 0 | D7: =MIN(D6,Premissas!$B$30) -> 0 | E7: =MIN(E6,Premissas!$B$30) -> 0 | F7: =MIN(F6,Premissas!$B$30) -> 6 | G7: =MIN(G6,Premissas!$B$30) -> 6 | H7: =MIN(H6,Premissas!$B$30) -> 6 | I7: =MIN(I6,Premissas!$B$30) -> 6 | J7: =MIN(J6,Premissas!$B$30) -> 6 | ... O7: =MIN(O6,Premissas!$B$30) -> 6
B8: Semanas venda de cabines | C8: =MIN(C6-C7,Premissas!$B$31) -> 0 | D8: =MIN(D6-D7,Premissas!$B$31) -> 0 | E8: =MIN(E6-E7,Premissas!$B$31) -> 0 | F8: =MIN(F6-F7,Premissas!$B$31) -> 4 | G8: =MIN(G6-G7,Premissas!$B$31) -> 4 | H8: =MIN(H6-H7,Premissas!$B$31) -> 4 | I8: =MIN(I6-I7,Premissas!$B$31) -> 4 | J8: =MIN(J6-J7,Premissas!$B$31) -> 4 | ... O8: =MIN(O6-O7,Premissas!$B$31) -> 4
B9: Semanas charter terceiros | C9: =C6-C7-C8 -> 0 | D9: =D6-D7-D8 -> 0 | E9: =E6-E7-E8 -> 0 | F9: =F6-F7-F8 -> 5 | G9: =G6-G7-G8 -> 10 | H9: =H6-H7-H8 -> 10 | I9: =I6-I7-I8 -> 10 | J9: =J6-J7-J8 -> 10 | ... O9: =O6-O7-O8 -> 10
B10: Índice de tarifa | C10: =IF(C$5>=1,(1+Premissas!$B$8)^(C$5-1),0) -> 0 | D10: =IF(D$5>=1,(1+Premissas!$B$8)^(D$5-1),0) -> 0 | E10: =IF(E$5>=1,(1+Premissas!$B$8)^(E$5-1),0) -> 0 | F10: =IF(F$5>=1,(1+Premissas!$B$8)^(F$5-1),0) -> 1 | G10: =IF(G$5>=1,(1+Premissas!$B$8)^(G$5-1),0) -> 1.025 | H10: =IF(H$5>=1,(1+Premissas!$B$8)^(H$5-1),0) -> 1.050625 | I10: =IF(I$5>=1,(1+Premissas!$B$8)^(I$5-1),0) -> 1.0768906 | J10: =IF(J$5>=1,(1+Premissas!$B$8)^(J$5-1),0) -> 1.1038129 | ... O10: =IF(O$5>=1,(1+Premissas!$B$8)^(O$5-1),0) -> 1.248863
B11: Índice de custo | C11: =IF(C$5>=1,(1+Premissas!$B$9)^(C$5-1),0) -> 0 | D11: =IF(D$5>=1,(1+Premissas!$B$9)^(D$5-1),0) -> 0 | E11: =IF(E$5>=1,(1+Premissas!$B$9)^(E$5-1),0) -> 0 | F11: =IF(F$5>=1,(1+Premissas!$B$9)^(F$5-1),0) -> 1 | G11: =IF(G$5>=1,(1+Premissas!$B$9)^(G$5-1),0) -> 1.03 | H11: =IF(H$5>=1,(1+Premissas!$B$9)^(H$5-1),0) -> 1.0609 | I11: =IF(I$5>=1,(1+Premissas!$B$9)^(I$5-1),0) -> 1.092727 | J11: =IF(J$5>=1,(1+Premissas!$B$9)^(J$5-1),0) -> 1.1255088 | ... O11: =IF(O$5>=1,(1+Premissas!$B$9)^(O$5-1),0) -> 1.3047732
B12: Receita — QIMO (preço de transferência = mercado) | C12: =C7*Premissas!$B$77*Premissas!$B$32*C10 -> 0 | D12: =D7*Premissas!$B$77*Premissas!$B$32*D10 -> 0 | E12: =E7*Premissas!$B$77*Premissas!$B$32*E10 -> 0 | F12: =F7*Premissas!$B$77*Premissas!$B$32*F10 -> 1620000 | G12: =G7*Premissas!$B$77*Premissas!$B$32*G10 -> 1660500 | H12: =H7*Premissas!$B$77*Premissas!$B$32*H10 -> 1702012.5 | I12: =I7*Premissas!$B$77*Premissas!$B$32*I10 -> 1744562.8 | J12: =J7*Premissas!$B$77*Premissas!$B$32*J10 -> 1788176.9 | ... O12: =O7*Premissas!$B$77*Premissas!$B$32*O10 -> 2023158
B13: Receita — charter de terceiros (líq. comissão) | C13: =C9*Premissas!$B$77*Premissas!$B$32*(1-Premissas!$B$12)*C10 -> 0 | D13: =D9*Premissas!$B$77*Premissas!$B$32*(1-Premissas!$B$12)*D10 -> 0 | E13: =E9*Premissas!$B$77*Premissas!$B$32*(1-Premissas!$B$12)*E10 -> 0 | F13: =F9*Premissas!$B$77*Premissas!$B$32*(1-Premissas!$B$12)*F10 -> 1147500 | G13: =G9*Premissas!$B$77*Premissas!$B$32*(1-Premissas!$B$12)*G10 -> 2352375 | H13: =H9*Premissas!$B$77*Premissas!$B$32*(1-Premissas!$B$12)*H10 -> 2411184.4 | I13: =I9*Premissas!$B$77*Premissas!$B$32*(1-Premissas!$B$12)*I10 -> 2471464 | J13: =J9*Premissas!$B$77*Premissas!$B$32*(1-Premissas!$B$12)*J10 -> 2533250.6 | ... O13: =O9*Premissas!$B$77*Premissas!$B$32*(1-Premissas!$B$12)*O10 -> 2866140.5
B14: Receita — venda de cabines (líq. comissão) | C14: =C8*Premissas!$B$44*Premissas!$B$38*Premissas!$B$78*Premissas!$B$32*(1-Premissas!$B$12)*C10 -> 0 | D14: =D8*Premissas!$B$44*Premissas!$B$38*Premissas!$B$78*Premissas!$B$32*(1-Premissas!$B$12)*D10 -> 0 | E14: =E8*Premissas!$B$44*Premissas!$B$38*Premissas!$B$78*Premissas!$B$32*(1-Premissas!$B$12)*E10 -> 0 | F14: =F8*Premissas!$B$44*Premissas!$B$38*Premissas!$B$78*Premissas!$B$32*(1-Premissas!$B$12)*F10 -> 687398.4 | G14: =G8*Premissas!$B$44*Premissas!$B$38*Premissas!$B$78*Premissas!$B$32*(1-Premissas!$B$12)*G10 -> 704583.36 | H14: =H8*Premissas!$B$44*Premissas!$B$38*Premissas!$B$78*Premissas!$B$32*(1-Premissas!$B$12)*H10 -> 722197.94 | I14: =I8*Premissas!$B$44*Premissas!$B$38*Premissas!$B$78*Premissas!$B$32*(1-Premissas!$B$12)*I10 -> 740252.89 | J14: =J8*Premissas!$B$44*Premissas!$B$38*Premissas!$B$78*Premissas!$B$32*(1-Premissas!$B$12)*J10 -> 758759.21 | ... O14: =O8*Premissas!$B$44*Premissas!$B$38*Premissas!$B$78*Premissas!$B$32*(1-Premissas!$B$12)*O10 -> 858466.41
B15: Receita líquida a bordo | C15: =C6*Premissas!$B$44*Premissas!$B$14*Premissas!$B$13*C10 -> 0 | D15: =D6*Premissas!$B$44*Premissas!$B$14*Premissas!$B$13*D10 -> 0 | E15: =E6*Premissas!$B$44*Premissas!$B$14*Premissas!$B$13*E10 -> 0 | F15: =F6*Premissas!$B$44*Premissas!$B$14*Premissas!$B$13*F10 -> 145800 | G15: =G6*Premissas!$B$44*Premissas!$B$14*Premissas!$B$13*G10 -> 199260 | H15: =H6*Premissas!$B$44*Premissas!$B$14*Premissas!$B$13*H10 -> 204241.5 | I15: =I6*Premissas!$B$44*Premissas!$B$14*Premissas!$B$13*I10 -> 209347.54 | J15: =J6*Premissas!$B$44*Premissas!$B$14*Premissas!$B$13*J10 -> 214581.23 | ... O15: =O6*Premissas!$B$44*Premissas!$B$14*Premissas!$B$13*O10 -> 242778.96
B16: RECEITA TOTAL | C16: =SUM(C12:C15) -> 0 | D16: =SUM(D12:D15) -> 0 | E16: =SUM(E12:E15) -> 0 | F16: =SUM(F12:F15) -> 3600698.4 | G16: =SUM(G12:G15) -> 4916718.4 | H16: =SUM(H12:H15) -> 5039636.3 | I16: =SUM(I12:I15) -> 5165627.2 | J16: =SUM(J12:J15) -> 5294767.9 | ... O16: =SUM(O12:O15) -> 5990543.9
B17: Custos variáveis (combustível, alimentação, consumíveis) | C17: =-C6*(Premissas!$B$70*Premissas!$B$34/Premissas!$B$6+Premissas!$B$75)*Premissas!$B$33*C11 -> 0 | D17: =-D6*(Premissas!$B$70*Premissas!$B$34/Premissas!$B$6+Premissas!$B$75)*Premissas!$B$33*D11 -> 0 | E17: =-E6*(Premissas!$B$70*Premissas!$B$34/Premissas!$B$6+Premissas!$B$75)*Premissas!$B$33*E11 -> 0 | F17: =-F6*(Premissas!$B$70*Premissas!$B$34/Premissas!$B$6+Premissas!$B$75)*Premissas!$B$33*F11 -> -1055451.9 | G17: =-G6*(Premissas!$B$70*Premissas!$B$34/Premissas!$B$6+Premissas!$B$75)*Premissas!$B$33*G11 -> -1449487.3 | H17: =-H6*(Premissas!$B$70*Premissas!$B$34/Premissas!$B$6+Premissas!$B$75)*Premissas!$B$33*H11 -> -1492971.9 | I17: =-I6*(Premissas!$B$70*Premissas!$B$34/Premissas!$B$6+Premissas!$B$75)*Premissas!$B$33*I11 -> -1537761.1 | J17: =-J6*(Premissas!$B$70*Premissas!$B$34/Premissas!$B$6+Premissas!$B$75)*Premissas!$B$33*J11 -> -1583893.9 | ... O17: =-O6*(Premissas!$B$70*Premissas!$B$34/Premissas!$B$6+Premissas!$B$75)*Premissas!$B$33*O11 -> -1836167.1
B18: Custos fixos (tripulação, seguros, manutenção, gestão…) | C18: =-IF(C$5>=1,Premissas!$B$68*Premissas!$B$33*C11,0) -> 0 | D18: =-IF(D$5>=1,Premissas!$B$68*Premissas!$B$33*D11,0) -> 0 | E18: =-IF(E$5>=1,Premissas!$B$68*Premissas!$B$33*E11,0) -> 0 | F18: =-IF(F$5>=1,Premissas!$B$68*Premissas!$B$33*F11,0) -> -3733589.2 | G18: =-IF(G$5>=1,Premissas!$B$68*Premissas!$B$33*G11,0) -> -3845596.9 | H18: =-IF(H$5>=1,Premissas!$B$68*Premissas!$B$33*H11,0) -> -3960964.8 | I18: =-IF(I$5>=1,Premissas!$B$68*Premissas!$B$33*I11,0) -> -4079793.7 | J18: =-IF(J$5>=1,Premissas!$B$68*Premissas!$B$33*J11,0) -> -4202187.5 | ... O18: =-IF(O$5>=1,Premissas!$B$68*Premissas!$B$33*O11,0) -> -4871487.1
B19: EBITDA | C19: =C16+C17+C18 -> 0 | D19: =D16+D17+D18 -> 0 | E19: =E16+E17+E18 -> 0 | F19: =F16+F17+F18 -> -1188342.7 | G19: =G16+G17+G18 -> -378365.81 | H19: =H16+H17+H18 -> -414300.38 | I19: =I16+I17+I18 -> -451927.57 | J19: =J16+J17+J18 -> -491313.53 | ... O19: =O16+O17+O18 -> -717110.31
B20: Margem EBITDA | C20: =IF(C16=0,0,C19/C16) -> 0 | D20: =IF(D16=0,0,D19/D16) -> 0 | E20: =IF(E16=0,0,E19/E16) -> 0 | F20: =IF(F16=0,0,F19/F16) -> -0.33003117 | G20: =IF(G16=0,0,G19/G16) -> -0.076954949 | H20: =IF(H16=0,0,H19/H16) -> -0.082208388 | I20: =IF(I16=0,0,I19/I16) -> -0.087487453 | J20: =IF(J16=0,0,J19/J16) -> -0.09279227 | ... O20: =IF(O16=0,0,O19/O16) -> -0.11970705
B21: Depreciação (até o valor residual) | C21: =-IF(C$5>=1,Premissas!$B$52*(1-Premissas!$B$35)/10,0) -> 0 | D21: =-IF(D$5>=1,Premissas!$B$52*(1-Premissas!$B$35)/10,0) -> 0 | E21: =-IF(E$5>=1,Premissas!$B$52*(1-Premissas!$B$35)/10,0) -> 0 | F21: =-IF(F$5>=1,Premissas!$B$52*(1-Premissas!$B$35)/10,0) -> -2623995 | G21: =-IF(G$5>=1,Premissas!$B$52*(1-Premissas!$B$35)/10,0) -> -2623995 | H21: =-IF(H$5>=1,Premissas!$B$52*(1-Premissas!$B$35)/10,0) -> -2623995 | I21: =-IF(I$5>=1,Premissas!$B$52*(1-Premissas!$B$35)/10,0) -> -2623995 | J21: =-IF(J$5>=1,Premissas!$B$52*(1-Premissas!$B$35)/10,0) -> -2623995 | ... O21: =-IF(O$5>=1,Premissas!$B$52*(1-Premissas!$B$35)/10,0) -> -2623995
B22: EBIT | C22: =C19+C21 -> 0 | D22: =D19+D21 -> 0 | E22: =E19+E21 -> 0 | F22: =F19+F21 -> -3812337.7 | G22: =G19+G21 -> -3002360.8 | H22: =H19+H21 -> -3038295.4 | I22: =I19+I21 -> -3075922.6 | J22: =J19+J21 -> -3115308.5 | ... O22: =O19+O21 -> -3341105.3
B23: Impostos (CFC Brasil, sobre EBIT positivo) | C23: =-MAX(0,C22)*Premissas!$B$11 -> 0 | D23: =-MAX(0,D22)*Premissas!$B$11 -> 0 | E23: =-MAX(0,E22)*Premissas!$B$11 -> 0 | F23: =-MAX(0,F22)*Premissas!$B$11 -> 0 | G23: =-MAX(0,G22)*Premissas!$B$11 -> 0 | H23: =-MAX(0,H22)*Premissas!$B$11 -> 0 | I23: =-MAX(0,I22)*Premissas!$B$11 -> 0 | J23: =-MAX(0,J22)*Premissas!$B$11 -> 0 | ... O23: =-MAX(0,O22)*Premissas!$B$11 -> 0
B24: Docagens (dry dock) | C24: =-(IF(C$5=3,Premissas!$B$80,0)+IF(C$5=5,Premissas!$B$81,0)+IF(C$5=8,Premissas!$B$82,0)+IF(C$5=10,Premissas!$B$83,0))*C11 -> 0 | D24: =-(IF(D$5=3,Premissas!$B$80,0)+IF(D$5=5,Premissas!$B$81,0)+IF(D$5=8,Premissas!$B$82,0)+IF(D$5=10,Premissas!$B$83,0))*D11 -> 0 | E24: =-(IF(E$5=3,Premissas!$B$80,0)+IF(E$5=5,Premissas!$B$81,0)+IF(E$5=8,Premissas!$B$82,0)+IF(E$5=10,Premissas!$B$83,0))*E11 -> 0 | F24: =-(IF(F$5=3,Premissas!$B$80,0)+IF(F$5=5,Premissas!$B$81,0)+IF(F$5=8,Premissas!$B$82,0)+IF(F$5=10,Premissas!$B$83,0))*F11 -> 0 | G24: =-(IF(G$5=3,Premissas!$B$80,0)+IF(G$5=5,Premissas!$B$81,0)+IF(G$5=8,Premissas!$B$82,0)+IF(G$5=10,Premissas!$B$83,0))*G11 -> 0 | H24: =-(IF(H$5=3,Premissas!$B$80,0)+IF(H$5=5,Premissas!$B$81,0)+IF(H$5=8,Premissas!$B$82,0)+IF(H$5=10,Premissas!$B$83,0))*H11 -> -371315 | I24: =-(IF(I$5=3,Premissas!$B$80,0)+IF(I$5=5,Premissas!$B$81,0)+IF(I$5=8,Premissas!$B$82,0)+IF(I$5=10,Premissas!$B$83,0))*I11 -> 0 | J24: =-(IF(J$5=3,Premissas!$B$80,0)+IF(J$5=5,Premissas!$B$81,0)+IF(J$5=8,Premissas!$B$82,0)+IF(J$5=10,Premissas!$B$83,0))*J11 -> -900407.05 | ... O24: =-(IF(O$5=3,Premissas!$B$80,0)+IF(O$5=5,Premissas!$B$81,0)+IF(O$5=8,Premissas!$B$82,0)+IF(O$5=10,Premissas!$B$83,0))*O11 -> -1304773.2
B25: CAPEX de manutenção + refurb | C25: =-IF(C$5>=1,Premissas!$B$52*(Premissas!$B$84+IF(C$5=6,Premissas!$B$85,0))*C11,0) -> 0 | D25: =-IF(D$5>=1,Premissas!$B$52*(Premissas!$B$84+IF(D$5=6,Premissas!$B$85,0))*D11,0) -> 0 | E25: =-IF(E$5>=1,Premissas!$B$52*(Premissas!$B$84+IF(E$5=6,Premissas!$B$85,0))*E11,0) -> 0 | F25: =-IF(F$5>=1,Premissas!$B$52*(Premissas!$B$84+IF(F$5=6,Premissas!$B$85,0))*F11,0) -> -238545 | G25: =-IF(G$5>=1,Premissas!$B$52*(Premissas!$B$84+IF(G$5=6,Premissas!$B$85,0))*G11,0) -> -245701.35 | H25: =-IF(H$5>=1,Premissas!$B$52*(Premissas!$B$84+IF(H$5=6,Premissas!$B$85,0))*H11,0) -> -253072.39 | I25: =-IF(I$5>=1,Premissas!$B$52*(Premissas!$B$84+IF(I$5=6,Premissas!$B$85,0))*I11,0) -> -260664.56 | J25: =-IF(J$5>=1,Premissas!$B$52*(Premissas!$B$84+IF(J$5=6,Premissas!$B$85,0))*J11,0) -> -268484.5 | ... O25: =-IF(O$5>=1,Premissas!$B$52*(Premissas!$B$84+IF(O$5=6,Premissas!$B$85,0))*O11,0) -> -311247.12
B26: CAPEX inicial | C26: =-Premissas!$B$52*Premissas!$B$53 -> -9541800 | D26: =-Premissas!$B$52*Premissas!$B$54 -> -9541800 | E26: =-Premissas!$B$52*Premissas!$B$55 -> -28625400 | F26: 0 | G26: 0 | H26: 0 | I26: 0 | J26: 0 | K26: 0 | L26: 0 | M26: 0 | N26: 0 | O26: 0
B27: Valor residual (venda no ano 10) | C27: =IF(C$5=10,Premissas!$B$52*Premissas!$B$35,0) -> 0 | D27: =IF(D$5=10,Premissas!$B$52*Premissas!$B$35,0) -> 0 | E27: =IF(E$5=10,Premissas!$B$52*Premissas!$B$35,0) -> 0 | F27: =IF(F$5=10,Premissas!$B$52*Premissas!$B$35,0) -> 0 | G27: =IF(G$5=10,Premissas!$B$52*Premissas!$B$35,0) -> 0 | H27: =IF(H$5=10,Premissas!$B$52*Premissas!$B$35,0) -> 0 | I27: =IF(I$5=10,Premissas!$B$52*Premissas!$B$35,0) -> 0 | J27: =IF(J$5=10,Premissas!$B$52*Premissas!$B$35,0) -> 0 | ... O27: =IF(O$5=10,Premissas!$B$52*Premissas!$B$35,0) -> 21469050
B28: FLUXO DE CAIXA LIVRE (desalavancado) | C28: =C19+C23+C24+C25+C26+C27 -> -9541800 | D28: =D19+D23+D24+D25+D26+D27 -> -9541800 | E28: =E19+E23+E24+E25+E26+E27 -> -28625400 | F28: =F19+F23+F24+F25+F26+F27 -> -1426887.7 | G28: =G19+G23+G24+G25+G26+G27 -> -624067.16 | H28: =H19+H23+H24+H25+H26+H27 -> -1038687.8 | I28: =I19+I23+I24+I25+I26+I27 -> -712592.13 | J28: =J19+J23+J24+J25+J26+J27 -> -1660205.1 | ... O28: =O19+O23+O24+O25+O26+O27 -> 19135919
B29: FCL acumulado sem valor residual | C29: =C28-C27 -> -9541800 | D29: =C29+D28-D27 -> -19083600 | E29: =D29+E28-E27 -> -47709000 | F29: =E29+F28-F27 -> -49135888 | G29: =F29+G28-G27 -> -49759955 | H29: =G29+H28-H27 -> -50798643 | I29: =H29+I28-I27 -> -51511235 | J29: =I29+J28-J27 -> -53171440 | K29: =J29+K28-K27 -> -56192818 | ... O29: =N29+O28-O27 -> -61762508
B30: aux. payback | C30: 0 | D30: 0 | E30: 0 | F30: =IF(AND(E29<0,F29>=0),F$5-1+(-E29)/(F28-F27),0) -> 0 | G30: =IF(AND(F29<0,G29>=0),G$5-1+(-F29)/(G28-G27),0) -> 0 | H30: =IF(AND(G29<0,H29>=0),H$5-1+(-G29)/(H28-H27),0) -> 0 | I30: =IF(AND(H29<0,I29>=0),I$5-1+(-H29)/(I28-I27),0) -> 0 | J30: =IF(AND(I29<0,J29>=0),J$5-1+(-I29)/(J28-J27),0) -> 0 | K30: =IF(AND(J29<0,K29>=0),K$5-1+(-J29)/(K28-K27),0) -> 0 | L30: =IF(AND(K29<0,L29>=0),L$5-1+(-K29)/(L28-L27),0) -> 0 | M30: =IF(AND(L29<0,M29>=0),M$5-1+(-L29)/(M28-M27),0) -> 0 | ... O30: =IF(AND(N29<0,O29>=0),O$5-1+(-N29)/(O28-O27),0) -> 0
B31: TIR do projeto (10 anos, desalavancada) | C31: =IFERROR(IRR(C28:O28,0.05),IFERROR(IRR(C28:O28,-0.05),IF(SUM(C28:O28)<0,"negativa","n/d"))) -> -0.11933694
B32: VPL @ hurdle (data de entrega, ano 0) | C32: =C28*(1+Premissas!$B$10)^2+D28*(1+Premissas!$B$10)+E28+NPV(Premissas!$B$10,F28:O28) -> -50614480
B33: Payback (anos após entrega, sem residual) | C33: =IF(SUM(F30:O30)=0,"> 10",SUM(F30:O30)) -> > 10
B34: ROI em 10 anos (ganho líquido / investimento) | C34: =SUM(C28:O28)/-SUM(C26:E26) -> -0.84456722
B35: ROIC médio (NOPAT médio / capital investido) | C35: =AVERAGE(F22:O22)*(1-Premissas!$B$11)/-SUM(C26:E26) -> -0.044653027
B36: EBITDA ano 3 (regime) | C36: =H19 -> -414300.38
B37: Receita ano 3 | C37: =H16 -> 5039636.3
B38: Margem EBITDA ano 3 | C38: =H20 -> -0.082208388
B39: OPEX total ano 3 | C39: =-(H17+H18) -> 5453936.7
B40: Break-even EBITDA (semanas/ano, ano 3) | C40: =IFERROR(-H18/((H16+H17)/H6),"n/d") -> 22.336282
B41: CAPEX total | C41: =-SUM(C26:E26) -> 47709000
B42: Valor residual estimado no ano 10 | C42: =O27 -> 21469050
B45: C · 36 cab/72 pax · NOVO — cenário Base
B46: Ano | C46: -2 | D46: -1 | E46: 0 | F46: 1 | G46: 2 | H46: 3 | I46: 4 | J46: 5 | K46: 6 | L46: 7 | M46: 8 | N46: 9 | O46: 10
B47: Semanas operadas | C47: =IF(C$46>=1,Premissas!$C$29*IF(C$46=1,Premissas!$C$37,1),0) -> 0 | D47: =IF(D$46>=1,Premissas!$C$29*IF(D$46=1,Premissas!$C$37,1),0) -> 0 | E47: =IF(E$46>=1,Premissas!$C$29*IF(E$46=1,Premissas!$C$37,1),0) -> 0 | F47: =IF(F$46>=1,Premissas!$C$29*IF(F$46=1,Premissas!$C$37,1),0) -> 22.1 | G47: =IF(G$46>=1,Premissas!$C$29*IF(G$46=1,Premissas!$C$37,1),0) -> 26 | H47: =IF(H$46>=1,Premissas!$C$29*IF(H$46=1,Premissas!$C$37,1),0) -> 26 | I47: =IF(I$46>=1,Premissas!$C$29*IF(I$46=1,Premissas!$C$37,1),0) -> 26 | J47: =IF(J$46>=1,Premissas!$C$29*IF(J$46=1,Premissas!$C$37,1),0) -> 26 | ... O47: =IF(O$46>=1,Premissas!$C$29*IF(O$46=1,Premissas!$C$37,1),0) -> 26
B48: Semanas QIMO | C48: =MIN(C47,Premissas!$C$30) -> 0 | D48: =MIN(D47,Premissas!$C$30) -> 0 | E48: =MIN(E47,Premissas!$C$30) -> 0 | F48: =MIN(F47,Premissas!$C$30) -> 8 | G48: =MIN(G47,Premissas!$C$30) -> 8 | H48: =MIN(H47,Premissas!$C$30) -> 8 | I48: =MIN(I47,Premissas!$C$30) -> 8 | J48: =MIN(J47,Premissas!$C$30) -> 8 | ... O48: =MIN(O47,Premissas!$C$30) -> 8
B49: Semanas venda de cabines | C49: =MIN(C47-C48,Premissas!$C$31) -> 0 | D49: =MIN(D47-D48,Premissas!$C$31) -> 0 | E49: =MIN(E47-E48,Premissas!$C$31) -> 0 | F49: =MIN(F47-F48,Premissas!$C$31) -> 4 | G49: =MIN(G47-G48,Premissas!$C$31) -> 4 | H49: =MIN(H47-H48,Premissas!$C$31) -> 4 | I49: =MIN(I47-I48,Premissas!$C$31) -> 4 | J49: =MIN(J47-J48,Premissas!$C$31) -> 4 | ... O49: =MIN(O47-O48,Premissas!$C$31) -> 4
B50: Semanas charter terceiros | C50: =C47-C48-C49 -> 0 | D50: =D47-D48-D49 -> 0 | E50: =E47-E48-E49 -> 0 | F50: =F47-F48-F49 -> 10.1 | G50: =G47-G48-G49 -> 14 | H50: =H47-H48-H49 -> 14 | I50: =I47-I48-I49 -> 14 | J50: =J47-J48-J49 -> 14 | ... O50: =O47-O48-O49 -> 14
B51: Índice de tarifa | C51: =IF(C$46>=1,(1+Premissas!$B$8)^(C$46-1),0) -> 0 | D51: =IF(D$46>=1,(1+Premissas!$B$8)^(D$46-1),0) -> 0 | E51: =IF(E$46>=1,(1+Premissas!$B$8)^(E$46-1),0) -> 0 | F51: =IF(F$46>=1,(1+Premissas!$B$8)^(F$46-1),0) -> 1 | G51: =IF(G$46>=1,(1+Premissas!$B$8)^(G$46-1),0) -> 1.025 | H51: =IF(H$46>=1,(1+Premissas!$B$8)^(H$46-1),0) -> 1.050625 | I51: =IF(I$46>=1,(1+Premissas!$B$8)^(I$46-1),0) -> 1.0768906 | J51: =IF(J$46>=1,(1+Premissas!$B$8)^(J$46-1),0) -> 1.1038129 | ... O51: =IF(O$46>=1,(1+Premissas!$B$8)^(O$46-1),0) -> 1.248863
B52: Índice de custo | C52: =IF(C$46>=1,(1+Premissas!$B$9)^(C$46-1),0) -> 0 | D52: =IF(D$46>=1,(1+Premissas!$B$9)^(D$46-1),0) -> 0 | E52: =IF(E$46>=1,(1+Premissas!$B$9)^(E$46-1),0) -> 0 | F52: =IF(F$46>=1,(1+Premissas!$B$9)^(F$46-1),0) -> 1 | G52: =IF(G$46>=1,(1+Premissas!$B$9)^(G$46-1),0) -> 1.03 | H52: =IF(H$46>=1,(1+Premissas!$B$9)^(H$46-1),0) -> 1.0609 | I52: =IF(I$46>=1,(1+Premissas!$B$9)^(I$46-1),0) -> 1.092727 | J52: =IF(J$46>=1,(1+Premissas!$B$9)^(J$46-1),0) -> 1.1255088 | ... O52: =IF(O$46>=1,(1+Premissas!$B$9)^(O$46-1),0) -> 1.3047732
B53: Receita — QIMO (preço de transferência = mercado) | C53: =C48*Premissas!$B$77*Premissas!$C$32*C51 -> 0 | D53: =D48*Premissas!$B$77*Premissas!$C$32*D51 -> 0 | E53: =E48*Premissas!$B$77*Premissas!$C$32*E51 -> 0 | F53: =F48*Premissas!$B$77*Premissas!$C$32*F51 -> 2400000 | G53: =G48*Premissas!$B$77*Premissas!$C$32*G51 -> 2460000 | H53: =H48*Premissas!$B$77*Premissas!$C$32*H51 -> 2521500 | I53: =I48*Premissas!$B$77*Premissas!$C$32*I51 -> 2584537.5 | J53: =J48*Premissas!$B$77*Premissas!$C$32*J51 -> 2649150.9 | ... O53: =O48*Premissas!$B$77*Premissas!$C$32*O51 -> 2997271.1
B54: Receita — charter de terceiros (líq. comissão) | C54: =C50*Premissas!$B$77*Premissas!$C$32*(1-Premissas!$B$12)*C51 -> 0 | D54: =D50*Premissas!$B$77*Premissas!$C$32*(1-Premissas!$B$12)*D51 -> 0 | E54: =E50*Premissas!$B$77*Premissas!$C$32*(1-Premissas!$B$12)*E51 -> 0 | F54: =F50*Premissas!$B$77*Premissas!$C$32*(1-Premissas!$B$12)*F51 -> 2575500 | G54: =G50*Premissas!$B$77*Premissas!$C$32*(1-Premissas!$B$12)*G51 -> 3659250 | H54: =H50*Premissas!$B$77*Premissas!$C$32*(1-Premissas!$B$12)*H51 -> 3750731.2 | I54: =I50*Premissas!$B$77*Premissas!$C$32*(1-Premissas!$B$12)*I51 -> 3844499.5 | J54: =J50*Premissas!$B$77*Premissas!$C$32*(1-Premissas!$B$12)*J51 -> 3940612 | ... O54: =O50*Premissas!$B$77*Premissas!$C$32*(1-Premissas!$B$12)*O51 -> 4458440.8
B55: Receita — venda de cabines (líq. comissão) | C55: =C49*Premissas!$B$44*Premissas!$C$38*Premissas!$B$78*Premissas!$C$32*(1-Premissas!$B$12)*C51 -> 0 | D55: =D49*Premissas!$B$44*Premissas!$C$38*Premissas!$B$78*Premissas!$C$32*(1-Premissas!$B$12)*D51 -> 0 | E55: =E49*Premissas!$B$44*Premissas!$C$38*Premissas!$B$78*Premissas!$C$32*(1-Premissas!$B$12)*E51 -> 0 | F55: =F49*Premissas!$B$44*Premissas!$C$38*Premissas!$B$78*Premissas!$C$32*(1-Premissas!$B$12)*F51 -> 881280 | G55: =G49*Premissas!$B$44*Premissas!$C$38*Premissas!$B$78*Premissas!$C$32*(1-Premissas!$B$12)*G51 -> 903312 | H55: =H49*Premissas!$B$44*Premissas!$C$38*Premissas!$B$78*Premissas!$C$32*(1-Premissas!$B$12)*H51 -> 925894.8 | I55: =I49*Premissas!$B$44*Premissas!$C$38*Premissas!$B$78*Premissas!$C$32*(1-Premissas!$B$12)*I51 -> 949042.17 | J55: =J49*Premissas!$B$44*Premissas!$C$38*Premissas!$B$78*Premissas!$C$32*(1-Premissas!$B$12)*J51 -> 972768.22 | ... O55: =O49*Premissas!$B$44*Premissas!$C$38*Premissas!$B$78*Premissas!$C$32*(1-Premissas!$B$12)*O51 -> 1100598
B56: Receita líquida a bordo | C56: =C47*Premissas!$B$44*Premissas!$B$14*Premissas!$B$13*C51 -> 0 | D56: =D47*Premissas!$B$44*Premissas!$B$14*Premissas!$B$13*D51 -> 0 | E56: =E47*Premissas!$B$44*Premissas!$B$14*Premissas!$B$13*E51 -> 0 | F56: =F47*Premissas!$B$44*Premissas!$B$14*Premissas!$B$13*F51 -> 214812 | G56: =G47*Premissas!$B$44*Premissas!$B$14*Premissas!$B$13*G51 -> 259038 | H56: =H47*Premissas!$B$44*Premissas!$B$14*Premissas!$B$13*H51 -> 265513.95 | I56: =I47*Premissas!$B$44*Premissas!$B$14*Premissas!$B$13*I51 -> 272151.8 | J56: =J47*Premissas!$B$44*Premissas!$B$14*Premissas!$B$13*J51 -> 278955.59 | ... O56: =O47*Premissas!$B$44*Premissas!$B$14*Premissas!$B$13*O51 -> 315612.65
B57: RECEITA TOTAL | C57: =SUM(C53:C56) -> 0 | D57: =SUM(D53:D56) -> 0 | E57: =SUM(E53:E56) -> 0 | F57: =SUM(F53:F56) -> 6071592 | G57: =SUM(G53:G56) -> 7281600 | H57: =SUM(H53:H56) -> 7463640 | I57: =SUM(I53:I56) -> 7650231 | J57: =SUM(J53:J56) -> 7841486.8 | ... O57: =SUM(O53:O56) -> 8871922.5
B58: Custos variáveis (combustível, alimentação, consumíveis) | C58: =-C47*(Premissas!$B$70*Premissas!$C$34/Premissas!$B$6+Premissas!$B$75)*Premissas!$C$33*C52 -> 0 | D58: =-D47*(Premissas!$B$70*Premissas!$C$34/Premissas!$B$6+Premissas!$B$75)*Premissas!$C$33*D52 -> 0 | E58: =-E47*(Premissas!$B$70*Premissas!$C$34/Premissas!$B$6+Premissas!$B$75)*Premissas!$C$33*E52 -> 0 | F58: =-F47*(Premissas!$B$70*Premissas!$C$34/Premissas!$B$6+Premissas!$B$75)*Premissas!$C$33*F52 -> -1221492 | G58: =-G47*(Premissas!$B$70*Premissas!$C$34/Premissas!$B$6+Premissas!$B$75)*Premissas!$C$33*G52 -> -1480160.9 | H58: =-H47*(Premissas!$B$70*Premissas!$C$34/Premissas!$B$6+Premissas!$B$75)*Premissas!$C$33*H52 -> -1524565.7 | I58: =-I47*(Premissas!$B$70*Premissas!$C$34/Premissas!$B$6+Premissas!$B$75)*Premissas!$C$33*I52 -> -1570302.7 | J58: =-J47*(Premissas!$B$70*Premissas!$C$34/Premissas!$B$6+Premissas!$B$75)*Premissas!$C$33*J52 -> -1617411.8 | ... O58: =-O47*(Premissas!$B$70*Premissas!$C$34/Premissas!$B$6+Premissas!$B$75)*Premissas!$C$33*O52 -> -1875023.5
B59: Custos fixos (tripulação, seguros, manutenção, gestão…) | C59: =-IF(C$46>=1,Premissas!$B$68*Premissas!$C$33*C52,0) -> 0 | D59: =-IF(D$46>=1,Premissas!$B$68*Premissas!$C$33*D52,0) -> 0 | E59: =-IF(E$46>=1,Premissas!$B$68*Premissas!$C$33*E52,0) -> 0 | F59: =-IF(F$46>=1,Premissas!$B$68*Premissas!$C$33*F52,0) -> -3394172 | G59: =-IF(G$46>=1,Premissas!$B$68*Premissas!$C$33*G52,0) -> -3495997.2 | H59: =-IF(H$46>=1,Premissas!$B$68*Premissas!$C$33*H52,0) -> -3600877.1 | I59: =-IF(I$46>=1,Premissas!$B$68*Premissas!$C$33*I52,0) -> -3708903.4 | J59: =-IF(J$46>=1,Premissas!$B$68*Premissas!$C$33*J52,0) -> -3820170.5 | ... O59: =-IF(O$46>=1,Premissas!$B$68*Premissas!$C$33*O52,0) -> -4428624.6
B60: EBITDA | C60: =C57+C58+C59 -> 0 | D60: =D57+D58+D59 -> 0 | E60: =E57+E58+E59 -> 0 | F60: =F57+F58+F59 -> 1455928 | G60: =G57+G58+G59 -> 2305442 | H60: =H57+H58+H59 -> 2338197.2 | I60: =I57+I58+I59 -> 2371024.9 | J60: =J57+J58+J59 -> 2403904.5 | ... O60: =O57+O58+O59 -> 2568274.4
B61: Margem EBITDA | C61: =IF(C57=0,0,C60/C57) -> 0 | D61: =IF(D57=0,0,D60/D57) -> 0 | E61: =IF(E57=0,0,E60/E57) -> 0 | F61: =IF(F57=0,0,F60/F57) -> 0.23979345 | G61: =IF(G57=0,0,G60/G57) -> 0.316612 | H61: =IF(H57=0,0,H60/H57) -> 0.3132784 | I61: =IF(I57=0,0,I60/I57) -> 0.30992854 | J61: =IF(J57=0,0,J60/J57) -> 0.30656234 | ... O61: =IF(O57=0,0,O60/O57) -> 0.28948341
B62: Depreciação (até o valor residual) | C62: =-IF(C$46>=1,Premissas!$B$52*(1-Premissas!$C$35)/10,0) -> 0 | D62: =-IF(D$46>=1,Premissas!$B$52*(1-Premissas!$C$35)/10,0) -> 0 | E62: =-IF(E$46>=1,Premissas!$B$52*(1-Premissas!$C$35)/10,0) -> 0 | F62: =-IF(F$46>=1,Premissas!$B$52*(1-Premissas!$C$35)/10,0) -> -2146905 | G62: =-IF(G$46>=1,Premissas!$B$52*(1-Premissas!$C$35)/10,0) -> -2146905 | H62: =-IF(H$46>=1,Premissas!$B$52*(1-Premissas!$C$35)/10,0) -> -2146905 | I62: =-IF(I$46>=1,Premissas!$B$52*(1-Premissas!$C$35)/10,0) -> -2146905 | J62: =-IF(J$46>=1,Premissas!$B$52*(1-Premissas!$C$35)/10,0) -> -2146905 | ... O62: =-IF(O$46>=1,Premissas!$B$52*(1-Premissas!$C$35)/10,0) -> -2146905
B63: EBIT | C63: =C60+C62 -> 0 | D63: =D60+D62 -> 0 | E63: =E60+E62 -> 0 | F63: =F60+F62 -> -690976.98 | G63: =G60+G62 -> 158536.97 | H63: =H60+H62 -> 191292.23 | I63: =I60+I62 -> 224119.94 | J63: =J60+J62 -> 256999.54 | ... O63: =O60+O62 -> 421369.42
B64: Impostos (CFC Brasil, sobre EBIT positivo) | C64: =-MAX(0,C63)*Premissas!$B$11 -> 0 | D64: =-MAX(0,D63)*Premissas!$B$11 -> 0 | E64: =-MAX(0,E63)*Premissas!$B$11 -> 0 | F64: =-MAX(0,F63)*Premissas!$B$11 -> 0 | G64: =-MAX(0,G63)*Premissas!$B$11 -> -53902.569 | H64: =-MAX(0,H63)*Premissas!$B$11 -> -65039.357 | I64: =-MAX(0,I63)*Premissas!$B$11 -> -76200.781 | J64: =-MAX(0,J63)*Premissas!$B$11 -> -87379.842 | ... O64: =-MAX(0,O63)*Premissas!$B$11 -> -143265.6
B65: Docagens (dry dock) | C65: =-(IF(C$46=3,Premissas!$B$80,0)+IF(C$46=5,Premissas!$B$81,0)+IF(C$46=8,Premissas!$B$82,0)+IF(C$46=10,Premissas!$B$83,0))*C52 -> 0 | D65: =-(IF(D$46=3,Premissas!$B$80,0)+IF(D$46=5,Premissas!$B$81,0)+IF(D$46=8,Premissas!$B$82,0)+IF(D$46=10,Premissas!$B$83,0))*D52 -> 0 | E65: =-(IF(E$46=3,Premissas!$B$80,0)+IF(E$46=5,Premissas!$B$81,0)+IF(E$46=8,Premissas!$B$82,0)+IF(E$46=10,Premissas!$B$83,0))*E52 -> 0 | F65: =-(IF(F$46=3,Premissas!$B$80,0)+IF(F$46=5,Premissas!$B$81,0)+IF(F$46=8,Premissas!$B$82,0)+IF(F$46=10,Premissas!$B$83,0))*F52 -> 0 | G65: =-(IF(G$46=3,Premissas!$B$80,0)+IF(G$46=5,Premissas!$B$81,0)+IF(G$46=8,Premissas!$B$82,0)+IF(G$46=10,Premissas!$B$83,0))*G52 -> 0 | H65: =-(IF(H$46=3,Premissas!$B$80,0)+IF(H$46=5,Premissas!$B$81,0)+IF(H$46=8,Premissas!$B$82,0)+IF(H$46=10,Premissas!$B$83,0))*H52 -> -371315 | I65: =-(IF(I$46=3,Premissas!$B$80,0)+IF(I$46=5,Premissas!$B$81,0)+IF(I$46=8,Premissas!$B$82,0)+IF(I$46=10,Premissas!$B$83,0))*I52 -> 0 | J65: =-(IF(J$46=3,Premissas!$B$80,0)+IF(J$46=5,Premissas!$B$81,0)+IF(J$46=8,Premissas!$B$82,0)+IF(J$46=10,Premissas!$B$83,0))*J52 -> -900407.05 | ... O65: =-(IF(O$46=3,Premissas!$B$80,0)+IF(O$46=5,Premissas!$B$81,0)+IF(O$46=8,Premissas!$B$82,0)+IF(O$46=10,Premissas!$B$83,0))*O52 -> -1304773.2
B66: CAPEX de manutenção + refurb | C66: =-IF(C$46>=1,Premissas!$B$52*(Premissas!$B$84+IF(C$46=6,Premissas!$B$85,0))*C52,0) -> 0 | D66: =-IF(D$46>=1,Premissas!$B$52*(Premissas!$B$84+IF(D$46=6,Premissas!$B$85,0))*D52,0) -> 0 | E66: =-IF(E$46>=1,Premissas!$B$52*(Premissas!$B$84+IF(E$46=6,Premissas!$B$85,0))*E52,0) -> 0 | F66: =-IF(F$46>=1,Premissas!$B$52*(Premissas!$B$84+IF(F$46=6,Premissas!$B$85,0))*F52,0) -> -238545 | G66: =-IF(G$46>=1,Premissas!$B$52*(Premissas!$B$84+IF(G$46=6,Premissas!$B$85,0))*G52,0) -> -245701.35 | H66: =-IF(H$46>=1,Premissas!$B$52*(Premissas!$B$84+IF(H$46=6,Premissas!$B$85,0))*H52,0) -> -253072.39 | I66: =-IF(I$46>=1,Premissas!$B$52*(Premissas!$B$84+IF(I$46=6,Premissas!$B$85,0))*I52,0) -> -260664.56 | J66: =-IF(J$46>=1,Premissas!$B$52*(Premissas!$B$84+IF(J$46=6,Premissas!$B$85,0))*J52,0) -> -268484.5 | ... O66: =-IF(O$46>=1,Premissas!$B$52*(Premissas!$B$84+IF(O$46=6,Premissas!$B$85,0))*O52,0) -> -311247.12
B67: CAPEX inicial | C67: =-Premissas!$B$52*Premissas!$B$53 -> -9541800 | D67: =-Premissas!$B$52*Premissas!$B$54 -> -9541800 | E67: =-Premissas!$B$52*Premissas!$B$55 -> -28625400 | F67: 0 | G67: 0 | H67: 0 | I67: 0 | J67: 0 | K67: 0 | L67: 0 | M67: 0 | N67: 0 | O67: 0
B68: Valor residual (venda no ano 10) | C68: =IF(C$46=10,Premissas!$B$52*Premissas!$C$35,0) -> 0 | D68: =IF(D$46=10,Premissas!$B$52*Premissas!$C$35,0) -> 0 | E68: =IF(E$46=10,Premissas!$B$52*Premissas!$C$35,0) -> 0 | F68: =IF(F$46=10,Premissas!$B$52*Premissas!$C$35,0) -> 0 | G68: =IF(G$46=10,Premissas!$B$52*Premissas!$C$35,0) -> 0 | H68: =IF(H$46=10,Premissas!$B$52*Premissas!$C$35,0) -> 0 | I68: =IF(I$46=10,Premissas!$B$52*Premissas!$C$35,0) -> 0 | J68: =IF(J$46=10,Premissas!$B$52*Premissas!$C$35,0) -> 0 | ... O68: =IF(O$46=10,Premissas!$B$52*Premissas!$C$35,0) -> 26239950
B69: FLUXO DE CAIXA LIVRE (desalavancado) | C69: =C60+C64+C65+C66+C67+C68 -> -9541800 | D69: =D60+D64+D65+D66+D67+D68 -> -9541800 | E69: =E60+E64+E65+E66+E67+E68 -> -28625400 | F69: =F60+F64+F65+F66+F67+F68 -> 1217383 | G69: =G60+G64+G65+G66+G67+G68 -> 2005838 | H69: =H60+H64+H65+H66+H67+H68 -> 1648770.5 | I69: =I60+I64+I65+I66+I67+I68 -> 2034159.6 | J69: =J60+J64+J65+J66+J67+J68 -> 1147633.1 | ... O69: =O60+O64+O65+O66+O67+O68 -> 27048939
B70: FCL acumulado sem valor residual | C70: =C69-C68 -> -9541800 | D70: =C70+D69-D68 -> -19083600 | E70: =D70+E69-E68 -> -47709000 | F70: =E70+F69-F68 -> -46491617 | G70: =F70+G69-G68 -> -44485779 | H70: =G70+H69-H68 -> -42837008 | I70: =H70+I69-I68 -> -40802849 | J70: =I70+J69-J68 -> -39655216 | K70: =J70+K69-K68 -> -39805822 | ... O70: =N70+O69-O68 -> -33224157
B71: aux. payback | C71: 0 | D71: 0 | E71: 0 | F71: =IF(AND(E70<0,F70>=0),F$46-1+(-E70)/(F69-F68),0) -> 0 | G71: =IF(AND(F70<0,G70>=0),G$46-1+(-F70)/(G69-G68),0) -> 0 | H71: =IF(AND(G70<0,H70>=0),H$46-1+(-G70)/(H69-H68),0) -> 0 | I71: =IF(AND(H70<0,I70>=0),I$46-1+(-H70)/(I69-I68),0) -> 0 | J71: =IF(AND(I70<0,J70>=0),J$46-1+(-I70)/(J69-J68),0) -> 0 | K71: =IF(AND(J70<0,K70>=0),K$46-1+(-J70)/(K69-K68),0) -> 0 | L71: =IF(AND(K70<0,L70>=0),L$46-1+(-K70)/(L69-L68),0) -> 0 | M71: =IF(AND(L70<0,M70>=0),M$46-1+(-L70)/(M69-M68),0) -> 0 | ... O71: =IF(AND(N70<0,O70>=0),O$46-1+(-N70)/(O69-O68),0) -> 0
B72: TIR do projeto (10 anos, desalavancada) | C72: =IFERROR(IRR(C69:O69,0.05),IFERROR(IRR(C69:O69,-0.05),IF(SUM(C69:O69)<0,"negativa","n/d"))) -> -0.017419323
B73: VPL @ hurdle (data de entrega, ano 0) | C73: =C69*(1+Premissas!$B$10)^2+D69*(1+Premissas!$B$10)+E69+NPV(Premissas!$B$10,F69:O69) -> -31517619
B74: Payback (anos após entrega, sem residual) | C74: =IF(SUM(F71:O71)=0,"> 10",SUM(F71:O71)) -> > 10
B75: ROI em 10 anos (ganho líquido / investimento) | C75: =SUM(C69:O69)/-SUM(C67:E67) -> -0.1463918
B76: ROIC médio (NOPAT médio / capital investido) | C76: =AVERAGE(F63:O63)*(1-Premissas!$B$11)/-SUM(C67:E67) -> 0.0026538678
B77: EBITDA ano 3 (regime) | C77: =H60 -> 2338197.2
B78: Receita ano 3 | C78: =H57 -> 7463640
B79: Margem EBITDA ano 3 | C79: =H61 -> 0.3132784
B80: OPEX total ano 3 | C80: =-(H58+H59) -> 5125442.8
B81: Break-even EBITDA (semanas/ano, ano 3) | C81: =IFERROR(-H59/((H57+H58)/H47),"n/d") -> 15.763871
B82: CAPEX total | C82: =-SUM(C67:E67) -> 47709000
B83: Valor residual estimado no ano 10 | C83: =O68 -> 26239950
B86: C · 36 cab/72 pax · NOVO — cenário Otimista
B87: Ano | C87: -2 | D87: -1 | E87: 0 | F87: 1 | G87: 2 | H87: 3 | I87: 4 | J87: 5 | K87: 6 | L87: 7 | M87: 8 | N87: 9 | O87: 10
B88: Semanas operadas | C88: =IF(C$87>=1,Premissas!$D$29*IF(C$87=1,Premissas!$D$37,1),0) -> 0 | D88: =IF(D$87>=1,Premissas!$D$29*IF(D$87=1,Premissas!$D$37,1),0) -> 0 | E88: =IF(E$87>=1,Premissas!$D$29*IF(E$87=1,Premissas!$D$37,1),0) -> 0 | F88: =IF(F$87>=1,Premissas!$D$29*IF(F$87=1,Premissas!$D$37,1),0) -> 28.5 | G88: =IF(G$87>=1,Premissas!$D$29*IF(G$87=1,Premissas!$D$37,1),0) -> 30 | H88: =IF(H$87>=1,Premissas!$D$29*IF(H$87=1,Premissas!$D$37,1),0) -> 30 | I88: =IF(I$87>=1,Premissas!$D$29*IF(I$87=1,Premissas!$D$37,1),0) -> 30 | J88: =IF(J$87>=1,Premissas!$D$29*IF(J$87=1,Premissas!$D$37,1),0) -> 30 | ... O88: =IF(O$87>=1,Premissas!$D$29*IF(O$87=1,Premissas!$D$37,1),0) -> 30
B89: Semanas QIMO | C89: =MIN(C88,Premissas!$D$30) -> 0 | D89: =MIN(D88,Premissas!$D$30) -> 0 | E89: =MIN(E88,Premissas!$D$30) -> 0 | F89: =MIN(F88,Premissas!$D$30) -> 12 | G89: =MIN(G88,Premissas!$D$30) -> 12 | H89: =MIN(H88,Premissas!$D$30) -> 12 | I89: =MIN(I88,Premissas!$D$30) -> 12 | J89: =MIN(J88,Premissas!$D$30) -> 12 | ... O89: =MIN(O88,Premissas!$D$30) -> 12
B90: Semanas venda de cabines | C90: =MIN(C88-C89,Premissas!$D$31) -> 0 | D90: =MIN(D88-D89,Premissas!$D$31) -> 0 | E90: =MIN(E88-E89,Premissas!$D$31) -> 0 | F90: =MIN(F88-F89,Premissas!$D$31) -> 4 | G90: =MIN(G88-G89,Premissas!$D$31) -> 4 | H90: =MIN(H88-H89,Premissas!$D$31) -> 4 | I90: =MIN(I88-I89,Premissas!$D$31) -> 4 | J90: =MIN(J88-J89,Premissas!$D$31) -> 4 | ... O90: =MIN(O88-O89,Premissas!$D$31) -> 4
B91: Semanas charter terceiros | C91: =C88-C89-C90 -> 0 | D91: =D88-D89-D90 -> 0 | E91: =E88-E89-E90 -> 0 | F91: =F88-F89-F90 -> 12.5 | G91: =G88-G89-G90 -> 14 | H91: =H88-H89-H90 -> 14 | I91: =I88-I89-I90 -> 14 | J91: =J88-J89-J90 -> 14 | ... O91: =O88-O89-O90 -> 14
B92: Índice de tarifa | C92: =IF(C$87>=1,(1+Premissas!$B$8)^(C$87-1),0) -> 0 | D92: =IF(D$87>=1,(1+Premissas!$B$8)^(D$87-1),0) -> 0 | E92: =IF(E$87>=1,(1+Premissas!$B$8)^(E$87-1),0) -> 0 | F92: =IF(F$87>=1,(1+Premissas!$B$8)^(F$87-1),0) -> 1 | G92: =IF(G$87>=1,(1+Premissas!$B$8)^(G$87-1),0) -> 1.025 | H92: =IF(H$87>=1,(1+Premissas!$B$8)^(H$87-1),0) -> 1.050625 | I92: =IF(I$87>=1,(1+Premissas!$B$8)^(I$87-1),0) -> 1.0768906 | J92: =IF(J$87>=1,(1+Premissas!$B$8)^(J$87-1),0) -> 1.1038129 | ... O92: =IF(O$87>=1,(1+Premissas!$B$8)^(O$87-1),0) -> 1.248863
B93: Índice de custo | C93: =IF(C$87>=1,(1+Premissas!$B$9)^(C$87-1),0) -> 0 | D93: =IF(D$87>=1,(1+Premissas!$B$9)^(D$87-1),0) -> 0 | E93: =IF(E$87>=1,(1+Premissas!$B$9)^(E$87-1),0) -> 0 | F93: =IF(F$87>=1,(1+Premissas!$B$9)^(F$87-1),0) -> 1 | G93: =IF(G$87>=1,(1+Premissas!$B$9)^(G$87-1),0) -> 1.03 | H93: =IF(H$87>=1,(1+Premissas!$B$9)^(H$87-1),0) -> 1.0609 | I93: =IF(I$87>=1,(1+Premissas!$B$9)^(I$87-1),0) -> 1.092727 | J93: =IF(J$87>=1,(1+Premissas!$B$9)^(J$87-1),0) -> 1.1255088 | ... O93: =IF(O$87>=1,(1+Premissas!$B$9)^(O$87-1),0) -> 1.3047732
B94: Receita — QIMO (preço de transferência = mercado) | C94: =C89*Premissas!$B$77*Premissas!$D$32*C92 -> 0 | D94: =D89*Premissas!$B$77*Premissas!$D$32*D92 -> 0 | E94: =E89*Premissas!$B$77*Premissas!$D$32*E92 -> 0 | F94: =F89*Premissas!$B$77*Premissas!$D$32*F92 -> 3960000 | G94: =G89*Premissas!$B$77*Premissas!$D$32*G92 -> 4059000 | H94: =H89*Premissas!$B$77*Premissas!$D$32*H92 -> 4160475 | I94: =I89*Premissas!$B$77*Premissas!$D$32*I92 -> 4264486.9 | J94: =J89*Premissas!$B$77*Premissas!$D$32*J92 -> 4371099 | ... O94: =O89*Premissas!$B$77*Premissas!$D$32*O92 -> 4945497.4
B95: Receita — charter de terceiros (líq. comissão) | C95: =C91*Premissas!$B$77*Premissas!$D$32*(1-Premissas!$B$12)*C92 -> 0 | D95: =D91*Premissas!$B$77*Premissas!$D$32*(1-Premissas!$B$12)*D92 -> 0 | E95: =E91*Premissas!$B$77*Premissas!$D$32*(1-Premissas!$B$12)*E92 -> 0 | F95: =F91*Premissas!$B$77*Premissas!$D$32*(1-Premissas!$B$12)*F92 -> 3506250 | G95: =G91*Premissas!$B$77*Premissas!$D$32*(1-Premissas!$B$12)*G92 -> 4025175 | H95: =H91*Premissas!$B$77*Premissas!$D$32*(1-Premissas!$B$12)*H92 -> 4125804.4 | I95: =I91*Premissas!$B$77*Premissas!$D$32*(1-Premissas!$B$12)*I92 -> 4228949.5 | J95: =J91*Premissas!$B$77*Premissas!$D$32*(1-Premissas!$B$12)*J92 -> 4334673.2 | ... O95: =O91*Premissas!$B$77*Premissas!$D$32*(1-Premissas!$B$12)*O92 -> 4904284.9
B96: Receita — venda de cabines (líq. comissão) | C96: =C90*Premissas!$B$44*Premissas!$D$38*Premissas!$B$78*Premissas!$D$32*(1-Premissas!$B$12)*C92 -> 0 | D96: =D90*Premissas!$B$44*Premissas!$D$38*Premissas!$B$78*Premissas!$D$32*(1-Premissas!$B$12)*D92 -> 0 | E96: =E90*Premissas!$B$44*Premissas!$D$38*Premissas!$B$78*Premissas!$D$32*(1-Premissas!$B$12)*E92 -> 0 | F96: =F90*Premissas!$B$44*Premissas!$D$38*Premissas!$B$78*Premissas!$D$32*(1-Premissas!$B$12)*F92 -> 1098662.4 | G96: =G90*Premissas!$B$44*Premissas!$D$38*Premissas!$B$78*Premissas!$D$32*(1-Premissas!$B$12)*G92 -> 1126129 | H96: =H90*Premissas!$B$44*Premissas!$D$38*Premissas!$B$78*Premissas!$D$32*(1-Premissas!$B$12)*H92 -> 1154282.2 | I96: =I90*Premissas!$B$44*Premissas!$D$38*Premissas!$B$78*Premissas!$D$32*(1-Premissas!$B$12)*I92 -> 1183139.2 | J96: =J90*Premissas!$B$44*Premissas!$D$38*Premissas!$B$78*Premissas!$D$32*(1-Premissas!$B$12)*J92 -> 1212717.7 | ... O96: =O90*Premissas!$B$44*Premissas!$D$38*Premissas!$B$78*Premissas!$D$32*(1-Premissas!$B$12)*O92 -> 1372078.8
B97: Receita líquida a bordo | C97: =C88*Premissas!$B$44*Premissas!$B$14*Premissas!$B$13*C92 -> 0 | D97: =D88*Premissas!$B$44*Premissas!$B$14*Premissas!$B$13*D92 -> 0 | E97: =E88*Premissas!$B$44*Premissas!$B$14*Premissas!$B$13*E92 -> 0 | F97: =F88*Premissas!$B$44*Premissas!$B$14*Premissas!$B$13*F92 -> 277020 | G97: =G88*Premissas!$B$44*Premissas!$B$14*Premissas!$B$13*G92 -> 298890 | H97: =H88*Premissas!$B$44*Premissas!$B$14*Premissas!$B$13*H92 -> 306362.25 | I97: =I88*Premissas!$B$44*Premissas!$B$14*Premissas!$B$13*I92 -> 314021.31 | J97: =J88*Premissas!$B$44*Premissas!$B$14*Premissas!$B$13*J92 -> 321871.84 | ... O97: =O88*Premissas!$B$44*Premissas!$B$14*Premissas!$B$13*O92 -> 364168.44
B98: RECEITA TOTAL | C98: =SUM(C94:C97) -> 0 | D98: =SUM(D94:D97) -> 0 | E98: =SUM(E94:E97) -> 0 | F98: =SUM(F94:F97) -> 8841932.4 | G98: =SUM(G94:G97) -> 9509194 | H98: =SUM(H94:H97) -> 9746923.8 | I98: =SUM(I94:I97) -> 9990596.9 | J98: =SUM(J94:J97) -> 10240362 | ... O98: =SUM(O94:O97) -> 11586029
B99: Custos variáveis (combustível, alimentação, consumíveis) | C99: =-C88*(Premissas!$B$70*Premissas!$D$34/Premissas!$B$6+Premissas!$B$75)*Premissas!$D$33*C93 -> 0 | D99: =-D88*(Premissas!$B$70*Premissas!$D$34/Premissas!$B$6+Premissas!$B$75)*Premissas!$D$33*D93 -> 0 | E99: =-E88*(Premissas!$B$70*Premissas!$D$34/Premissas!$B$6+Premissas!$B$75)*Premissas!$D$33*E93 -> 0 | F99: =-F88*(Premissas!$B$70*Premissas!$D$34/Premissas!$B$6+Premissas!$B$75)*Premissas!$D$33*F93 -> -1349319.1 | G99: =-G88*(Premissas!$B$70*Premissas!$D$34/Premissas!$B$6+Premissas!$B$75)*Premissas!$D$33*G93 -> -1462946 | H99: =-H88*(Premissas!$B$70*Premissas!$D$34/Premissas!$B$6+Premissas!$B$75)*Premissas!$D$33*H93 -> -1506834.4 | I99: =-I88*(Premissas!$B$70*Premissas!$D$34/Premissas!$B$6+Premissas!$B$75)*Premissas!$D$33*I93 -> -1552039.4 | J99: =-J88*(Premissas!$B$70*Premissas!$D$34/Premissas!$B$6+Premissas!$B$75)*Premissas!$D$33*J93 -> -1598600.6 | ... O99: =-O88*(Premissas!$B$70*Premissas!$D$34/Premissas!$B$6+Premissas!$B$75)*Premissas!$D$33*O93 -> -1853216.2
B100: Custos fixos (tripulação, seguros, manutenção, gestão…) | C100: =-IF(C$87>=1,Premissas!$B$68*Premissas!$D$33*C93,0) -> 0 | D100: =-IF(D$87>=1,Premissas!$B$68*Premissas!$D$33*D93,0) -> 0 | E100: =-IF(E$87>=1,Premissas!$B$68*Premissas!$D$33*E93,0) -> 0 | F100: =-IF(F$87>=1,Premissas!$B$68*Premissas!$D$33*F93,0) -> -3224463.4 | G100: =-IF(G$87>=1,Premissas!$B$68*Premissas!$D$33*G93,0) -> -3321197.3 | H100: =-IF(H$87>=1,Premissas!$B$68*Premissas!$D$33*H93,0) -> -3420833.2 | I100: =-IF(I$87>=1,Premissas!$B$68*Premissas!$D$33*I93,0) -> -3523458.2 | J100: =-IF(J$87>=1,Premissas!$B$68*Premissas!$D$33*J93,0) -> -3629162 | ... O100: =-IF(O$87>=1,Premissas!$B$68*Premissas!$D$33*O93,0) -> -4207193.4
B101: EBITDA | C101: =C98+C99+C100 -> 0 | D101: =D98+D99+D100 -> 0 | E101: =E98+E99+E100 -> 0 | F101: =F98+F99+F100 -> 4268149.9 | G101: =G98+G99+G100 -> 4725050.7 | H101: =H98+H99+H100 -> 4819256.2 | I101: =I98+I99+I100 -> 4915099.3 | J101: =J98+J99+J100 -> 5012599.3 | ... O101: =O98+O99+O100 -> 5525619.9
B102: Margem EBITDA | C102: =IF(C98=0,0,C101/C98) -> 0 | D102: =IF(D98=0,0,D101/D98) -> 0 | E102: =IF(E98=0,0,E101/E98) -> 0 | F102: =IF(F98=0,0,F101/F98) -> 0.48271686 | G102: =IF(G98=0,0,G101/G98) -> 0.49689287 | H102: =IF(H98=0,0,H101/H98) -> 0.49443869 | I102: =IF(I98=0,0,I101/I98) -> 0.49197254 | J102: =IF(J98=0,0,J101/J98) -> 0.48949435 | ... O102: =IF(O98=0,0,O101/O98) -> 0.47692092
B103: Depreciação (até o valor residual) | C103: =-IF(C$87>=1,Premissas!$B$52*(1-Premissas!$D$35)/10,0) -> 0 | D103: =-IF(D$87>=1,Premissas!$B$52*(1-Premissas!$D$35)/10,0) -> 0 | E103: =-IF(E$87>=1,Premissas!$B$52*(1-Premissas!$D$35)/10,0) -> 0 | F103: =-IF(F$87>=1,Premissas!$B$52*(1-Premissas!$D$35)/10,0) -> -1669815 | G103: =-IF(G$87>=1,Premissas!$B$52*(1-Premissas!$D$35)/10,0) -> -1669815 | H103: =-IF(H$87>=1,Premissas!$B$52*(1-Premissas!$D$35)/10,0) -> -1669815 | I103: =-IF(I$87>=1,Premissas!$B$52*(1-Premissas!$D$35)/10,0) -> -1669815 | J103: =-IF(J$87>=1,Premissas!$B$52*(1-Premissas!$D$35)/10,0) -> -1669815 | ... O103: =-IF(O$87>=1,Premissas!$B$52*(1-Premissas!$D$35)/10,0) -> -1669815
B104: EBIT | C104: =C101+C103 -> 0 | D104: =D101+D103 -> 0 | E104: =E101+E103 -> 0 | F104: =F101+F103 -> 2598334.9 | G104: =G101+G103 -> 3055235.7 | H104: =H101+H103 -> 3149441.2 | I104: =I101+I103 -> 3245284.3 | J104: =J101+J103 -> 3342784.3 | ... O104: =O101+O103 -> 3855804.9
B105: Impostos (CFC Brasil, sobre EBIT positivo) | C105: =-MAX(0,C104)*Premissas!$B$11 -> 0 | D105: =-MAX(0,D104)*Premissas!$B$11 -> 0 | E105: =-MAX(0,E104)*Premissas!$B$11 -> 0 | F105: =-MAX(0,F104)*Premissas!$B$11 -> -883433.86 | G105: =-MAX(0,G104)*Premissas!$B$11 -> -1038780.1 | H105: =-MAX(0,H104)*Premissas!$B$11 -> -1070810 | I105: =-MAX(0,I104)*Premissas!$B$11 -> -1103396.7 | J105: =-MAX(0,J104)*Premissas!$B$11 -> -1136546.7 | ... O105: =-MAX(0,O104)*Premissas!$B$11 -> -1310973.7
...

Sheet Sensib_Semanas
A1: Sensibilidade à utilização — 10 a 35 semanas/ano (cenário Base, ano de regime, € de 2026)
A2: TIR aproximada via RATE (fluxo constante + residual) — para análise rápida; a projeção completa está na aba Projecao.
A4: C · 36 cab/72 pax · NOVO
A5: Semanas/ano | B5: Semanas | C5: Receita | D5: OPEX | E5: EBITDA | F5: Margem | G5: FCL anual | H5: TIR ~10a | I5: Custo próprio/sem. | J5: Tarifa charter/sem.
A6: 10 semanas | B6: 10 | C6: =MIN(B6,Premissas!$C$30)*Premissas!$B$77*Premissas!$C$32+(B6-MIN(B6,Premissas!$C$30)-MIN(B6-MIN(B6,Premissas!$C$30),Premissas!$C$31))*Premissas!$B$77*Premissas!$C$32*(1-Premissas!$B$12)+MIN(B6-MIN(B6,Premissas!$C$30),Premissas!$C$31)*Premissas!$B$44*Premissas!$C$38*Premissas!$B$78*Premissas!$C$32*(1-Premissas!$B$12)+B6*Premissas!$B$44*Premissas!$B$14*Premissas!$B$13 -> 2937840 | D6: =B6*(Premissas!$B$70*Premissas!$C$34/Premissas!$B$6+Premissas!$B$75)*Premissas!$C$33+Premissas!$B$68*Premissas!$C$33 -> 3946883.3 | E6: =C6-D6 -> -1009043.3 | F6: =IF(C6=0,0,E6/C6) -> -0.34346435 | G6: =E6-MAX(0,E6-Premissas!$B$52*(1-Premissas!$C$35)/10)*Premissas!$B$11-(Premissas!$B$52*(Premissas!$B$84+Premissas!$B$85/10)+(Premissas!$B$80+Premissas!$B$81+Premissas!$B$82+Premissas!$B$83)/10) -> -1693424.3 | H6: =IFERROR(RATE(10,G6,-Premissas!$B$52,Premissas!$B$52*Premissas!$C$35),"< -10%") -> -0.1063898 | I6: =(D6+((Premissas!$B$52-Premissas!$B$52*Premissas!$C$35/(1+Premissas!$B$10)^10)*(Premissas!$B$10/(1-(1+Premissas!$B$10)^-10))+(Premissas!$B$52*(Premissas!$B$84+Premissas!$B$85/10)+(Premissas!$B$80+Premissas!$B$81+Premissas!$B$82+Premissas!$B$83)/10)))/B6 -> 1074924.8 | J6: =Premissas!$B$77*Premissas!$C$32 -> 300000
A7: 15 semanas | B7: 15 | C7: =MIN(B7,Premissas!$C$30)*Premissas!$B$77*Premissas!$C$32+(B7-MIN(B7,Premissas!$C$30)-MIN(B7-MIN(B7,Premissas!$C$30),Premissas!$C$31))*Premissas!$B$77*Premissas!$C$32*(1-Premissas!$B$12)+MIN(B7-MIN(B7,Premissas!$C$30),Premissas!$C$31)*Premissas!$B$44*Premissas!$C$38*Premissas!$B$78*Premissas!$C$32*(1-Premissas!$B$12)+B7*Premissas!$B$44*Premissas!$B$14*Premissas!$B$13 -> 4192080 | D7: =B7*(Premissas!$B$70*Premissas!$C$34/Premissas!$B$6+Premissas!$B$75)*Premissas!$C$33+Premissas!$B$68*Premissas!$C$33 -> 4223239 | E7: =C7-D7 -> -31158.957 | F7: =IF(C7=0,0,E7/C7) -> -0.0074328153 | G7: =E7-MAX(0,E7-Premissas!$B$52*(1-Premissas!$C$35)/10)*Premissas!$B$11-(Premissas!$B$52*(Premissas!$B$84+Premissas!$B$85/10)+(Premissas!$B$80+Premissas!$B$81+Premissas!$B$82+Premissas!$B$83)/10) -> -715539.96 | H7: =IFERROR(RATE(10,G7,-Premissas!$B$52,Premissas!$B$52*Premissas!$C$35),"< -10%") -> -0.07816134 | I7: =(D7+((Premissas!$B$52-Premissas!$B$52*Premissas!$C$35/(1+Premissas!$B$10)^10)*(Premissas!$B$10/(1-(1+Premissas!$B$10)^-10))+(Premissas!$B$52*(Premissas!$B$84+Premissas!$B$85/10)+(Premissas!$B$80+Premissas!$B$81+Premissas!$B$82+Premissas!$B$83)/10)))/B7 -> 735040.27 | J7: =Premissas!$B$77*Premissas!$C$32 -> 300000
A8: 20 semanas | B8: 20 | C8: =MIN(B8,Premissas!$C$30)*Premissas!$B$77*Premissas!$C$32+(B8-MIN(B8,Premissas!$C$30)-MIN(B8-MIN(B8,Premissas!$C$30),Premissas!$C$31))*Premissas!$B$77*Premissas!$C$32*(1-Premissas!$B$12)+MIN(B8-MIN(B8,Premissas!$C$30),Premissas!$C$31)*Premissas!$B$44*Premissas!$C$38*Premissas!$B$78*Premissas!$C$32*(1-Premissas!$B$12)+B8*Premissas!$B$44*Premissas!$B$14*Premissas!$B$13 -> 5515680 | D8: =B8*(Premissas!$B$70*Premissas!$C$34/Premissas!$B$6+Premissas!$B$75)*Premissas!$C$33+Premissas!$B$68*Premissas!$C$33 -> 4499594.6 | E8: =C8-D8 -> 1016085.4 | F8: =IF(C8=0,0,E8/C8) -> 0.18421761 | G8: =E8-MAX(0,E8-Premissas!$B$52*(1-Premissas!$C$35)/10)*Premissas!$B$11-(Premissas!$B$52*(Premissas!$B$84+Premissas!$B$85/10)+(Premissas!$B$80+Premissas!$B$81+Premissas!$B$82+Premissas!$B$83)/10) -> 331704.39 | H8: =IFERROR(RATE(10,G8,-Premissas!$B$52,Premissas!$B$52*Premissas!$C$35),"< -10%") -> -0.048842036 | I8: =(D8+((Premissas!$B$52-Premissas!$B$52*Premissas!$C$35/(1+Premissas!$B$10)^10)*(Premissas!$B$10/(1-(1+Premissas!$B$10)^-10))+(Premissas!$B$52*(Premissas!$B$84+Premissas!$B$85/10)+(Premissas!$B$80+Premissas!$B$81+Premissas!$B$82+Premissas!$B$83)/10)))/B8 -> 565097.98 | J8: =Premissas!$B$77*Premissas!$C$32 -> 300000
A9: 25 semanas | B9: 25 | C9: =MIN(B9,Premissas!$C$30)*Premissas!$B$77*Premissas!$C$32+(B9-MIN(B9,Premissas!$C$30)-MIN(B9-MIN(B9,Premissas!$C$30),Premissas!$C$31))*Premissas!$B$77*Premissas!$C$32*(1-Premissas!$B$12)+MIN(B9-MIN(B9,Premissas!$C$30),Premissas!$C$31)*Premissas!$B$44*Premissas!$C$38*Premissas!$B$78*Premissas!$C$32*(1-Premissas!$B$12)+B9*Premissas!$B$44*Premissas!$B$14*Premissas!$B$13 -> 6839280 | D9: =B9*(Premissas!$B$70*Premissas!$C$34/Premissas!$B$6+Premissas!$B$75)*Premissas!$C$33+Premissas!$B$68*Premissas!$C$33 -> 4775950.3 | E9: =C9-D9 -> 2063329.7 | F9: =IF(C9=0,0,E9/C9) -> 0.30168815 | G9: =E9-MAX(0,E9-Premissas!$B$52*(1-Premissas!$C$35)/10)*Premissas!$B$11-(Premissas!$B$52*(Premissas!$B$84+Premissas!$B$85/10)+(Premissas!$B$80+Premissas!$B$81+Premissas!$B$82+Premissas!$B$83)/10) -> 1378948.7 | H9: =IFERROR(RATE(10,G9,-Premissas!$B$52,Premissas!$B$52*Premissas!$C$35),"< -10%") -> -0.020379109 | I9: =(D9+((Premissas!$B$52-Premissas!$B$52*Premissas!$C$35/(1+Premissas!$B$10)^10)*(Premissas!$B$10/(1-(1+Premissas!$B$10)^-10))+(Premissas!$B$52*(Premissas!$B$84+Premissas!$B$85/10)+(Premissas!$B$80+Premissas!$B$81+Premissas!$B$82+Premissas!$B$83)/10)))/B9 -> 463132.61 | J9: =Premissas!$B$77*Premissas!$C$32 -> 300000
A10: 30 semanas | B10: 30 | C10: =MIN(B10,Premissas!$C$30)*Premissas!$B$77*Premissas!$C$32+(B10-MIN(B10,Premissas!$C$30)-MIN(B10-MIN(B10,Premissas!$C$30),Premissas!$C$31))*Premissas!$B$77*Premissas!$C$32*(1-Premissas!$B$12)+MIN(B10-MIN(B10,Premissas!$C$30),Premissas!$C$31)*Premissas!$B$44*Premissas!$C$38*Premissas!$B$78*Premissas!$C$32*(1-Premissas!$B$12)+B10*Premissas!$B$44*Premissas!$B$14*Premissas!$B$13 -> 8162880 | D10: =B10*(Premissas!$B$70*Premissas!$C$34/Premissas!$B$6+Premissas!$B$75)*Premissas!$C$33+Premissas!$B$68*Premissas!$C$33 -> 5052305.9 | E10: =C10-D10 -> 3110574.1 | F10: =IF(C10=0,0,E10/C10) -> 0.38106331 | G10: =E10-MAX(0,E10-Premissas!$B$52*(1-Premissas!$C$35)/10)*Premissas!$B$11-(Premissas!$B$52*(Premissas!$B$84+Premissas!$B$85/10)+(Premissas!$B$80+Premissas!$B$81+Premissas!$B$82+Premissas!$B$83)/10) -> 2098545.6 | H10: =IFERROR(RATE(10,G10,-Premissas!$B$52,Premissas!$B$52*Premissas!$C$35),"< -10%") -> -0.0012717662 | I10: =(D10+((Premissas!$B$52-Premissas!$B$52*Premissas!$C$35/(1+Premissas!$B$10)^10)*(Premissas!$B$10/(1-(1+Premissas!$B$10)^-10))+(Premissas!$B$52*(Premissas!$B$84+Premissas!$B$85/10)+(Premissas!$B$80+Premissas!$B$81+Premissas!$B$82+Premissas!$B$83)/10)))/B10 -> 395155.7 | J10: =Premissas!$B$77*Premissas!$C$32 -> 300000
A11: 35 semanas | B11: 35 | C11: =MIN(B11,Premissas!$C$30)*Premissas!$B$77*Premissas!$C$32+(B11-MIN(B11,Premissas!$C$30)-MIN(B11-MIN(B11,Premissas!$C$30),Premissas!$C$31))*Premissas!$B$77*Premissas!$C$32*(1-Premissas!$B$12)+MIN(B11-MIN(B11,Premissas!$C$30),Premissas!$C$31)*Premissas!$B$44*Premissas!$C$38*Premissas!$B$78*Premissas!$C$32*(1-Premissas!$B$12)+B11*Premissas!$B$44*Premissas!$B$14*Premissas!$B$13 -> 9486480 | D11: =B11*(Premissas!$B$70*Premissas!$C$34/Premissas!$B$6+Premissas!$B$75)*Premissas!$C$33+Premissas!$B$68*Premissas!$C$33 -> 5328661.6 | E11: =C11-D11 -> 4157818.4 | F11: =IF(C11=0,0,E11/C11) -> 0.43828885 | G11: =E11-MAX(0,E11-Premissas!$B$52*(1-Premissas!$C$35)/10)*Premissas!$B$11-(Premissas!$B$52*(Premissas!$B$84+Premissas!$B$85/10)+(Premissas!$B$80+Premissas!$B$81+Premissas!$B$82+Premissas!$B$83)/10) -> 2789726.9 | H11: =IFERROR(RATE(10,G11,-Premissas!$B$52,Premissas!$B$52*Premissas!$C$35),"< -10%") -> 0.016765355 | I11: =(D11+((Premissas!$B$52-Premissas!$B$52*Premissas!$C$35/(1+Premissas!$B$10)^10)*(Premissas!$B$10/(1-(1+Premissas!$B$10)^-10))+(Premissas!$B$52*(Premissas!$B$84+Premissas!$B$85/10)+(Premissas!$B$80+Premissas!$B$81+Premissas!$B$82+Premissas!$B$83)/10)))/B11 -> 346600.76 | J11: =Premissas!$B$77*Premissas!$C$32 -> 300000
A13: C · 36 cab/72 pax · USADO
A14: Semanas/ano | B14: Semanas | C14: Receita | D14: OPEX | E14: EBITDA | F14: Margem | G14: FCL anual | H14: TIR ~10a | I14: Custo próprio/sem. | J14: Tarifa charter/sem.
A15: 10 semanas | B15: 10 | C15: =MIN(B15,Premissas!$C$30)*Premissas!$C$77*Premissas!$C$32+(B15-MIN(B15,Premissas!$C$30)-MIN(B15-MIN(B15,Premissas!$C$30),Premissas!$C$31))*Premissas!$C$77*Premissas!$C$32*(1-Premissas!$B$12)+MIN(B15-MIN(B15,Premissas!$C$30),Premissas!$C$31)*Premissas!$C$44*Premissas!$C$38*Premissas!$C$78*Premissas!$C$32*(1-Premissas!$B$12)+B15*Premissas!$C$44*Premissas!$B$14*Premissas!$B$13 -> 2651940 | D15: =B15*(Premissas!$C$70*Premissas!$C$34/Premissas!$B$6+Premissas!$C$75)*Premissas!$C$33+Premissas!$C$68*Premissas!$C$33 -> 4006411.3 | E15: =C15-D15 -> -1354471.3 | F15: =IF(C15=0,0,E15/C15) -> -0.51074734 | G15: =E15-MAX(0,E15-Premissas!$C$52*(1-Premissas!$C$36)/10)*Premissas!$B$11-(Premissas!$C$52*(Premissas!$C$84+Premissas!$C$85/10)+(Premissas!$C$80+Premissas!$C$81+Premissas!$C$82+Premissas!$C$83)/10) -> -1959071.3 | H15: =IFERROR(RATE(10,G15,-Premissas!$C$52,Premissas!$C$52*Premissas!$C$36),"< -10%") -> -0.20589639 | I15: =(D15+((Premissas!$C$52-Premissas!$C$52*Premissas!$C$36/(1+Premissas!$B$10)^10)*(Premissas!$B$10/(1-(1+Premissas!$B$10)^-10))+(Premissas!$C$52*(Premissas!$C$84+Premissas!$C$85/10)+(Premissas!$C$80+Premissas!$C$81+Premissas!$C$82+Premissas!$C$83)/10)))/B15 -> 742238.7 | J15: =Premissas!$C$77*Premissas!$C$32 -> 270000
A16: 15 semanas | B16: 15 | C16: =MIN(B16,Premissas!$C$30)*Premissas!$C$77*Premissas!$C$32+(B16-MIN(B16,Premissas!$C$30)-MIN(B16-MIN(B16,Premissas!$C$30),Premissas!$C$31))*Premissas!$C$77*Premissas!$C$32*(1-Premissas!$B$12)+MIN(B16-MIN(B16,Premissas!$C$30),Premissas!$C$31)*Premissas!$C$44*Premissas!$C$38*Premissas!$C$78*Premissas!$C$32*(1-Premissas!$B$12)+B16*Premissas!$C$44*Premissas!$B$14*Premissas!$B$13 -> 3783780 | D16: =B16*(Premissas!$C$70*Premissas!$C$34/Premissas!$B$6+Premissas!$C$75)*Premissas!$C$33+Premissas!$C$68*Premissas!$C$33 -> 4282767 | E16: =C16-D16 -> -498986.96 | F16: =IF(C16=0,0,E16/C16) -> -0.13187526 | G16: =E16-MAX(0,E16-Premissas!$C$52*(1-Premissas!$C$36)/10)*Premissas!$B$11-(Premissas!$C$52*(Premissas!$C$84+Premissas!$C$85/10)+(Premissas!$C$80+Premissas!$C$81+Premissas!$C$82+Premissas!$C$83)/10) -> -1103587 | H16: =IFERROR(RATE(10,G16,-Premissas!$C$52,Premissas!$C$52*Premissas!$C$36),"< -10%") -> -0.14223699 | I16: =(D16+((Premissas!$C$52-Premissas!$C$52*Premissas!$C$36/(1+Premissas!$B$10)^10)*(Premissas!$B$10/(1-(1+Premissas!$B$10)^-10))+(Premissas!$C$52*(Premissas!$C$84+Premissas!$C$85/10)+(Premissas!$C$80+Premissas!$C$81+Premissas!$C$82+Premissas!$C$83)/10)))/B16 -> 513249.51 | J16: =Premissas!$C$77*Premissas!$C$32 -> 270000
A17: 20 semanas | B17: 20 | C17: =MIN(B17,Premissas!$C$30)*Premissas!$C$77*Premissas!$C$32+(B17-MIN(B17,Premissas!$C$30)-MIN(B17-MIN(B17,Premissas!$C$30),Premissas!$C$31))*Premissas!$C$77*Premissas!$C$32*(1-Premissas!$B$12)+MIN(B17-MIN(B17,Premissas!$C$30),Premissas!$C$31)*Premissas!$C$44*Premissas!$C$38*Premissas!$C$78*Premissas!$C$32*(1-Premissas!$B$12)+B17*Premissas!$C$44*Premissas!$B$14*Premissas!$B$13 -> 4979880 | D17: =B17*(Premissas!$C$70*Premissas!$C$34/Premissas!$B$6+Premissas!$C$75)*Premissas!$C$33+Premissas!$C$68*Premissas!$C$33 -> 4559122.6 | E17: =C17-D17 -> 420757.39 | F17: =IF(C17=0,0,E17/C17) -> 0.084491472 | G17: =E17-MAX(0,E17-Premissas!$C$52*(1-Premissas!$C$36)/10)*Premissas!$B$11-(Premissas!$C$52*(Premissas!$C$84+Premissas!$C$85/10)+(Premissas!$C$80+Premissas!$C$81+Premissas!$C$82+Premissas!$C$83)/10) -> -183842.61 | H17: =IFERROR(RATE(10,G17,-Premissas!$C$52,Premissas!$C$52*Premissas!$C$36),"< -10%") -> -0.079024722 | I17: =(D17+((Premissas!$C$52-Premissas!$C$52*Premissas!$C$36/(1+Premissas!$B$10)^10)*(Premissas!$B$10/(1-(1+Premissas!$B$10)^-10))+(Premissas!$C$52*(Premissas!$C$84+Premissas!$C$85/10)+(Premissas!$C$80+Premissas!$C$81+Premissas!$C$82+Premissas!$C$83)/10)))/B17 -> 398754.92 | J17: =Premissas!$C$77*Premissas!$C$32 -> 270000
A18: 25 semanas | B18: 25 | C18: =MIN(B18,Premissas!$C$30)*Premissas!$C$77*Premissas!$C$32+(B18-MIN(B18,Premissas!$C$30)-MIN(B18-MIN(B18,Premissas!$C$30),Premissas!$C$31))*Premissas!$C$77*Premissas!$C$32*(1-Premissas!$B$12)+MIN(B18-MIN(B18,Premissas!$C$30),Premissas!$C$31)*Premissas!$C$44*Premissas!$C$38*Premissas!$C$78*Premissas!$C$32*(1-Premissas!$B$12)+B18*Premissas!$C$44*Premissas!$B$14*Premissas!$B$13 -> 6175980 | D18: =B18*(Premissas!$C$70*Premissas!$C$34/Premissas!$B$6+Premissas!$C$75)*Premissas!$C$33+Premissas!$C$68*Premissas!$C$33 -> 4835478.3 | E18: =C18-D18 -> 1340501.7 | F18: =IF(C18=0,0,E18/C18) -> 0.21705085 | G18: =E18-MAX(0,E18-Premissas!$C$52*(1-Premissas!$C$36)/10)*Premissas!$B$11-(Premissas!$C$52*(Premissas!$C$84+Premissas!$C$85/10)+(Premissas!$C$80+Premissas!$C$81+Premissas!$C$82+Premissas!$C$83)/10) -> 643931.15 | H18: =IFERROR(RATE(10,G18,-Premissas!$C$52,Premissas!$C$52*Premissas!$C$36),"< -10%") -> -0.026055725 | I18: =(D18+((Premissas!$C$52-Premissas!$C$52*Premissas!$C$36/(1+Premissas!$B$10)^10)*(Premissas!$B$10/(1-(1+Premissas!$B$10)^-10))+(Premissas!$C$52*(Premissas!$C$84+Premissas!$C$85/10)+(Premissas!$C$80+Premissas!$C$81+Premissas!$C$82+Premissas!$C$83)/10)))/B18 -> 330058.16 | J18: =Premissas!$C$77*Premissas!$C$32 -> 270000
A19: 30 semanas | B19: 30 | C19: =MIN(B19,Premissas!$C$30)*Premissas!$C$77*Premissas!$C$32+(B19-MIN(B19,Premissas!$C$30)-MIN(B19-MIN(B19,Premissas!$C$30),Premissas!$C$31))*Premissas!$C$77*Premissas!$C$32*(1-Premissas!$B$12)+MIN(B19-MIN(B19,Premissas!$C$30),Premissas!$C$31)*Premissas!$C$44*Premissas!$C$38*Premissas!$C$78*Premissas!$C$32*(1-Premissas!$B$12)+B19*Premissas!$C$44*Premissas!$B$14*Premissas!$B$13 -> 7372080 | D19: =B19*(Premissas!$C$70*Premissas!$C$34/Premissas!$B$6+Premissas!$C$75)*Premissas!$C$33+Premissas!$C$68*Premissas!$C$33 -> 5111833.9 | E19: =C19-D19 -> 2260246.1 | F19: =IF(C19=0,0,E19/C19) -> 0.30659544 | G19: =E19-MAX(0,E19-Premissas!$C$52*(1-Premissas!$C$36)/10)*Premissas!$B$11-(Premissas!$C$52*(Premissas!$C$84+Premissas!$C$85/10)+(Premissas!$C$80+Premissas!$C$81+Premissas!$C$82+Premissas!$C$83)/10) -> 1250962.4 | H19: =IFERROR(RATE(10,G19,-Premissas!$C$52,Premissas!$C$52*Premissas!$C$36),"< -10%") -> 0.010848913 | I19: =(D19+((Premissas!$C$52-Premissas!$C$52*Premissas!$C$36/(1+Premissas!$B$10)^10)*(Premissas!$B$10/(1-(1+Premissas!$B$10)^-10))+(Premissas!$C$52*(Premissas!$C$84+Premissas!$C$85/10)+(Premissas!$C$80+Premissas!$C$81+Premissas!$C$82+Premissas!$C$83)/10)))/B19 -> 284260.32 | J19: =Premissas!$C$77*Premissas!$C$32 -> 270000
A20: 35 semanas | B20: 35 | C20: =MIN(B20,Premissas!$C$30)*Premissas!$C$77*Premissas!$C$32+(B20-MIN(B20,Premissas!$C$30)-MIN(B20-MIN(B20,Premissas!$C$30),Premissas!$C$31))*Premissas!$C$77*Premissas!$C$32*(1-Premissas!$B$12)+MIN(B20-MIN(B20,Premissas!$C$30),Premissas!$C$31)*Premissas!$C$44*Premissas!$C$38*Premissas!$C$78*Premissas!$C$32*(1-Premissas!$B$12)+B20*Premissas!$C$44*Premissas!$B$14*Premissas!$B$13 -> 8568180 | D20: =B20*(Premissas!$C$70*Premissas!$C$34/Premissas!$B$6+Premissas!$C$75)*Premissas!$C$33+Premissas!$C$68*Premissas!$C$33 -> 5388189.6 | E20: =C20-D20 -> 3179990.4 | F20: =IF(C20=0,0,E20/C20) -> 0.37113955 | G20: =E20-MAX(0,E20-Premissas!$C$52*(1-Premissas!$C$36)/10)*Premissas!$B$11-(Premissas!$C$52*(Premissas!$C$84+Premissas!$C$85/10)+(Premissas!$C$80+Premissas!$C$81+Premissas!$C$82+Premissas!$C$83)/10) -> 1857993.7 | H20: =IFERROR(RATE(10,G20,-Premissas!$C$52,Premissas!$C$52*Premissas!$C$36),"< -10%") -> 0.046396327 | I20: =(D20+((Premissas!$C$52-Premissas!$C$52*Premissas!$C$36/(1+Premissas!$B$10)^10)*(Premissas!$B$10/(1-(1+Premissas!$B$10)^-10))+(Premissas!$C$52*(Premissas!$C$84+Premissas!$C$85/10)+(Premissas!$C$80+Premissas!$C$81+Premissas!$C$82+Premissas!$C$83)/10)))/B20 -> 251547.58 | J20: =Premissas!$C$77*Premissas!$C$32 -> 270000
A22: B · 24 cab/48 pax · NOVO
A23: Semanas/ano | B23: Semanas | C23: Receita | D23: OPEX | E23: EBITDA | F23: Margem | G23: FCL anual | H23: TIR ~10a | I23: Custo próprio/sem. | J23: Tarifa charter/sem.
A24: 10 semanas | B24: 10 | C24: =MIN(B24,Premissas!$C$30)*Premissas!$D$77*Premissas!$C$32+(B24-MIN(B24,Premissas!$C$30)-MIN(B24-MIN(B24,Premissas!$C$30),Premissas!$C$31))*Premissas!$D$77*Premissas!$C$32*(1-Premissas!$B$12)+MIN(B24-MIN(B24,Premissas!$C$30),Premissas!$C$31)*Premissas!$D$44*Premissas!$C$38*Premissas!$D$78*Premissas!$C$32*(1-Premissas!$B$12)+B24*Premissas!$D$44*Premissas!$B$14*Premissas!$B$13 -> 1700200 | D24: =B24*(Premissas!$D$70*Premissas!$C$34/Premissas!$B$6+Premissas!$D$75)*Premissas!$C$33+Premissas!$D$68*Premissas!$C$33 -> 2912267.7 | E24: =C24-D24 -> -1212067.7 | F24: =IF(C24=0,0,E24/C24) -> -0.71289715 | G24: =E24-MAX(0,E24-Premissas!$D$52*(1-Premissas!$C$35)/10)*Premissas!$B$11-(Premissas!$D$52*(Premissas!$D$84+Premissas!$D$85/10)+(Premissas!$D$80+Premissas!$D$81+Premissas!$D$82+Premissas!$D$83)/10) -> -1684527.7 | H24: =IFERROR(RATE(10,G24,-Premissas!$D$52,Premissas!$D$52*Premissas!$C$35),"< -10%") -> -0.13082788 | I24: =(D24+((Premissas!$D$52-Premissas!$D$52*Premissas!$C$35/(1+Premissas!$B$10)^10)*(Premissas!$B$10/(1-(1+Premissas!$B$10)^-10))+(Premissas!$D$52*(Premissas!$D$84+Premissas!$D$85/10)+(Premissas!$D$80+Premissas!$D$81+Premissas!$D$82+Premissas!$D$83)/10)))/B24 -> 748056.73 | J24: =Premissas!$D$77*Premissas!$C$32 -> 170000
A25: 15 semanas | B25: 15 | C25: =MIN(B25,Premissas!$C$30)*Premissas!$D$77*Premissas!$C$32+(B25-MIN(B25,Premissas!$C$30)-MIN(B25-MIN(B25,Premissas!$C$30),Premissas!$C$31))*Premissas!$D$77*Premissas!$C$32*(1-Premissas!$B$12)+MIN(B25-MIN(B25,Premissas!$C$30),Premissas!$C$31)*Premissas!$D$44*Premissas!$C$38*Premissas!$D$78*Premissas!$C$32*(1-Premissas!$B$12)+B25*Premissas!$D$44*Premissas!$B$14*Premissas!$B$13 -> 2441500 | D25: =B25*(Premissas!$D$70*Premissas!$C$34/Premissas!$B$6+Premissas!$D$75)*Premissas!$C$33+Premissas!$D$68*Premissas!$C$33 -> 3103908.6 | E25: =C25-D25 -> -662408.61 | F25: =IF(C25=0,0,E25/C25) -> -0.27131215 | G25: =E25-MAX(0,E25-Premissas!$D$52*(1-Premissas!$C$35)/10)*Premissas!$B$11-(Premissas!$D$52*(Premissas!$D$84+Premissas!$D$85/10)+(Premissas!$D$80+Premissas!$D$81+Premissas!$D$82+Premissas!$D$83)/10) -> -1134868.6 | H25: =IFERROR(RATE(10,G25,-Premissas!$D$52,Premissas!$D$52*Premissas!$C$35),"< -10%") -> -0.10644071 | I25: =(D25+((Premissas!$D$52-Premissas!$D$52*Premissas!$C$35/(1+Premissas!$B$10)^10)*(Premissas!$B$10/(1-(1+Premissas!$B$10)^-10))+(Premissas!$D$52*(Premissas!$D$84+Premissas!$D$85/10)+(Premissas!$D$80+Premissas!$D$81+Premissas!$D$82+Premissas!$D$83)/10)))/B25 -> 511480.54 | J25: =Premissas!$D$77*Premissas!$C$32 -> 170000
A26: 20 semanas | B26: 20 | C26: =MIN(B26,Premissas!$C$30)*Premissas!$D$77*Premissas!$C$32+(B26-MIN(B26,Premissas!$C$30)-MIN(B26-MIN(B26,Premissas!$C$30),Premissas!$C$31))*Premissas!$D$77*Premissas!$C$32*(1-Premissas!$B$12)+MIN(B26-MIN(B26,Premissas!$C$30),Premissas!$C$31)*Premissas!$D$44*Premissas!$C$38*Premissas!$D$78*Premissas!$C$32*(1-Premissas!$B$12)+B26*Premissas!$D$44*Premissas!$B$14*Premissas!$B$13 -> 3196400 | D26: =B26*(Premissas!$D$70*Premissas!$C$34/Premissas!$B$6+Premissas!$D$75)*Premissas!$C$33+Premissas!$D$68*Premissas!$C$33 -> 3295549.5 | E26: =C26-D26 -> -99149.478 | F26: =IF(C26=0,0,E26/C26) -> -0.031019108 | G26: =E26-MAX(0,E26-Premissas!$D$52*(1-Premissas!$C$35)/10)*Premissas!$B$11-(Premissas!$D$52*(Premissas!$D$84+Premissas!$D$85/10)+(Premissas!$D$80+Premissas!$D$81+Premissas!$D$82+Premissas!$D$83)/10) -> -571609.48 | H26: =IFERROR(RATE(10,G26,-Premissas!$D$52,Premissas!$D$52*Premissas!$C$35),"< -10%") -> -0.082101351 | I26: =(D26+((Premissas!$D$52-Premissas!$D$52*Premissas!$C$35/(1+Premissas!$B$10)^10)*(Premissas!$B$10/(1-(1+Premissas!$B$10)^-10))+(Premissas!$D$52*(Premissas!$D$84+Premissas!$D$85/10)+(Premissas!$D$80+Premissas!$D$81+Premissas!$D$82+Premissas!$D$83)/10)))/B26 -> 393192.45 | J26: =Premissas!$D$77*Premissas!$C$32 -> 170000
A27: 25 semanas | B27: 25 | C27: =MIN(B27,Premissas!$C$30)*Premissas!$D$77*Premissas!$C$32+(B27-MIN(B27,Premissas!$C$30)-MIN(B27-MIN(B27,Premissas!$C$30),Premissas!$C$31))*Premissas!$D$77*Premissas!$C$32*(1-Premissas!$B$12)+MIN(B27-MIN(B27,Premissas!$C$30),Premissas!$C$31)*Premissas!$D$44*Premissas!$C$38*Premissas!$D$78*Premissas!$C$32*(1-Premissas!$B$12)+B27*Premissas!$D$44*Premissas!$B$14*Premissas!$B$13 -> 3951300 | D27: =B27*(Premissas!$D$70*Premissas!$C$34/Premissas!$B$6+Premissas!$D$75)*Premissas!$C$33+Premissas!$D$68*Premissas!$C$33 -> 3487190.3 | E27: =C27-D27 -> 464109.65 | F27: =IF(C27=0,0,E27/C27) -> 0.11745746 | G27: =E27-MAX(0,E27-Premissas!$D$52*(1-Premissas!$C$35)/10)*Premissas!$B$11-(Premissas!$D$52*(Premissas!$D$84+Premissas!$D$85/10)+(Premissas!$D$80+Premissas!$D$81+Premissas!$D$82+Premissas!$D$83)/10) -> -8350.3478 | H27: =IFERROR(RATE(10,G27,-Premissas!$D$52,Premissas!$D$52*Premissas!$C$35),"< -10%") -> -0.058379012 | I27: =(D27+((Premissas!$D$52-Premissas!$D$52*Premissas!$C$35/(1+Premissas!$B$10)^10)*(Premissas!$B$10/(1-(1+Premissas!$B$10)^-10))+(Premissas!$D$52*(Premissas!$D$84+Premissas!$D$85/10)+(Premissas!$D$80+Premissas!$D$81+Premissas!$D$82+Premissas!$D$83)/10)))/B27 -> 322219.6 | J27: =Premissas!$D$77*Premissas!$C$32 -> 170000
A28: 30 semanas | B28: 30 | C28: =MIN(B28,Premissas!$C$30)*Premissas!$D$77*Premissas!$C$32+(B28-MIN(B28,Premissas!$C$30)-MIN(B28-MIN(B28,Premissas!$C$30),Premissas!$C$31))*Premissas!$D$77*Premissas!$C$32*(1-Premissas!$B$12)+MIN(B28-MIN(B28,Premissas!$C$30),Premissas!$C$31)*Premissas!$D$44*Premissas!$C$38*Premissas!$D$78*Premissas!$C$32*(1-Premissas!$B$12)+B28*Premissas!$D$44*Premissas!$B$14*Premissas!$B$13 -> 4706200 | D28: =B28*(Premissas!$D$70*Premissas!$C$34/Premissas!$B$6+Premissas!$D$75)*Premissas!$C$33+Premissas!$D$68*Premissas!$C$33 -> 3678831.2 | E28: =C28-D28 -> 1027368.8 | F28: =IF(C28=0,0,E28/C28) -> 0.21830113 | G28: =E28-MAX(0,E28-Premissas!$D$52*(1-Premissas!$C$35)/10)*Premissas!$B$11-(Premissas!$D$52*(Premissas!$D$84+Premissas!$D$85/10)+(Premissas!$D$80+Premissas!$D$81+Premissas!$D$82+Premissas!$D$83)/10) -> 554908.78 | H28: =IFERROR(RATE(10,G28,-Premissas!$D$52,Premissas!$D$52*Premissas!$C$35),"< -10%") -> -0.035228285 | I28: =(D28+((Premissas!$D$52-Premissas!$D$52*Premissas!$C$35/(1+Premissas!$B$10)^10)*(Premissas!$B$10/(1-(1+Premissas!$B$10)^-10))+(Premissas!$D$52*(Premissas!$D$84+Premissas!$D$85/10)+(Premissas!$D$80+Premissas!$D$81+Premissas!$D$82+Premissas!$D$83)/10)))/B28 -> 274904.36 | J28: =Premissas!$D$77*Premissas!$C$32 -> 170000
A29: 35 semanas | B29: 35 | C29: =MIN(B29,Premissas!$C$30)*Premissas!$D$77*Premissas!$C$32+(B29-MIN(B29,Premissas!$C$30)-MIN(B29-MIN(B29,Premissas!$C$30),Premissas!$C$31))*Premissas!$D$77*Premissas!$C$32*(1-Premissas!$B$12)+MIN(B29-MIN(B29,Premissas!$C$30),Premissas!$C$31)*Premissas!$D$44*Premissas!$C$38*Premissas!$D$78*Premissas!$C$32*(1-Premissas!$B$12)+B29*Premissas!$D$44*Premissas!$B$14*Premissas!$B$13 -> 5461100 | D29: =B29*(Premissas!$D$70*Premissas!$C$34/Premissas!$B$6+Premissas!$D$75)*Premissas!$C$33+Premissas!$D$68*Premissas!$C$33 -> 3870472.1 | E29: =C29-D29 -> 1590627.9 | F29: =IF(C29=0,0,E29/C29) -> 0.29126511 | G29: =E29-MAX(0,E29-Premissas!$D$52*(1-Premissas!$C$35)/10)*Premissas!$B$11-(Premissas!$D$52*(Premissas!$D$84+Premissas!$D$85/10)+(Premissas!$D$80+Premissas!$D$81+Premissas!$D$82+Premissas!$D$83)/10) -> 1066036.4 | H29: =IFERROR(RATE(10,G29,-Premissas!$D$52,Premissas!$D$52*Premissas!$C$35),"< -10%") -> -0.014676249 | I29: =(D29+((Premissas!$D$52-Premissas!$D$52*Premissas!$C$35/(1+Premissas!$B$10)^10)*(Premissas!$B$10/(1-(1+Premissas!$B$10)^-10))+(Premissas!$D$52*(Premissas!$D$84+Premissas!$D$85/10)+(Premissas!$D$80+Premissas!$D$81+Premissas!$D$82+Premissas!$D$83)/10)))/B29 -> 241107.76 | J29: =Premissas!$D$77*Premissas!$C$32 -> 170000
A31: B · 24 cab/48 pax · USADO
A32: Semanas/ano | B32: Semanas | C32: Receita | D32: OPEX | E32: EBITDA | F32: Margem | G32: FCL anual | H32: TIR ~10a | I32: Custo próprio/sem. | J32: Tarifa charter/sem.
A33: 10 semanas | B33: 10 | C33: =MIN(B33,Premissas!$C$30)*Premissas!$E$77*Premissas!$C$32+(B33-MIN(B33,Premissas!$C$30)-MIN(B33-MIN(B33,Premissas!$C$30),Premissas!$C$31))*Premissas!$E$77*Premissas!$C$32*(1-Premissas!$B$12)+MIN(B33-MIN(B33,Premissas!$C$30),Premissas!$C$31)*Premissas!$E$44*Premissas!$C$38*Premissas!$E$78*Premissas!$C$32*(1-Premissas!$B$12)+B33*Premissas!$E$44*Premissas!$B$14*Premissas!$B$13 -> 1509600 | D33: =B33*(Premissas!$E$70*Premissas!$C$34/Premissas!$B$6+Premissas!$E$75)*Premissas!$C$33+Premissas!$E$68*Premissas!$C$33 -> 2886547.7 | E33: =C33-D33 -> -1376947.7 | F33: =IF(C33=0,0,E33/C33) -> -0.91212754 | G33: =E33-MAX(0,E33-Premissas!$E$52*(1-Premissas!$C$36)/10)*Premissas!$B$11-(Premissas!$E$52*(Premissas!$E$84+Premissas!$E$85/10)+(Premissas!$E$80+Premissas!$E$81+Premissas!$E$82+Premissas!$E$83)/10) -> -1760347.7 | H33: =IFERROR(RATE(10,G33,-Premissas!$E$52,Premissas!$E$52*Premissas!$C$36),"< -10%") -> -0.33771437 | I33: =(D33+((Premissas!$E$52-Premissas!$E$52*Premissas!$C$36/(1+Premissas!$B$10)^10)*(Premissas!$B$10/(1-(1+Premissas!$B$10)^-10))+(Premissas!$E$52*(Premissas!$E$84+Premissas!$E$85/10)+(Premissas!$E$80+Premissas!$E$81+Premissas!$E$82+Premissas!$E$83)/10)))/B33 -> 466249.83 | J33: =Premissas!$E$77*Premissas!$C$32 -> 150000
A34: 15 semanas | B34: 15 | C34: =MIN(B34,Premissas!$C$30)*Premissas!$E$77*Premissas!$C$32+(B34-MIN(B34,Premissas!$C$30)-MIN(B34-MIN(B34,Premissas!$C$30),Premissas!$C$31))*Premissas!$E$77*Premissas!$C$32*(1-Premissas!$B$12)+MIN(B34-MIN(B34,Premissas!$C$30),Premissas!$C$31)*Premissas!$E$44*Premissas!$C$38*Premissas!$E$78*Premissas!$C$32*(1-Premissas!$B$12)+B34*Premissas!$E$44*Premissas!$B$14*Premissas!$B$13 -> 2169300 | D34: =B34*(Premissas!$E$70*Premissas!$C$34/Premissas!$B$6+Premissas!$E$75)*Premissas!$C$33+Premissas!$E$68*Premissas!$C$33 -> 3078188.6 | E34: =C34-D34 -> -908888.61 | F34: =IF(C34=0,0,E34/C34) -> -0.41897783 | G34: =E34-MAX(0,E34-Premissas!$E$52*(1-Premissas!$C$36)/10)*Premissas!$B$11-(Premissas!$E$52*(Premissas!$E$84+Premissas!$E$85/10)+(Premissas!$E$80+Premissas!$E$81+Premissas!$E$82+Premissas!$E$83)/10) -> -1292288.6 | H34: =IFERROR(RATE(10,G34,-Premissas!$E$52,Premissas!$E$52*Premissas!$C$36),"< -10%") -> -0.25762778 | I34: =(D34+((Premissas!$E$52-Premissas!$E$52*Premissas!$C$36/(1+Premissas!$B$10)^10)*(Premissas!$B$10/(1-(1+Premissas!$B$10)^-10))+(Premissas!$E$52*(Premissas!$E$84+Premissas!$E$85/10)+(Premissas!$E$80+Premissas!$E$81+Premissas!$E$82+Premissas!$E$83)/10)))/B34 -> 323609.28 | J34: =Premissas!$E$77*Premissas!$C$32 -> 150000
A35: 20 semanas | B35: 20 | C35: =MIN(B35,Premissas!$C$30)*Premissas!$E$77*Premissas!$C$32+(B35-MIN(B35,Premissas!$C$30)-MIN(B35-MIN(B35,Premissas!$C$30),Premissas!$C$31))*Premissas!$E$77*Premissas!$C$32*(1-Premissas!$B$12)+MIN(B35-MIN(B35,Premissas!$C$30),Premissas!$C$31)*Premissas!$E$44*Premissas!$C$38*Premissas!$E$78*Premissas!$C$32*(1-Premissas!$B$12)+B35*Premissas!$E$44*Premissas!$B$14*Premissas!$B$13 -> 2839200 | D35: =B35*(Premissas!$E$70*Premissas!$C$34/Premissas!$B$6+Premissas!$E$75)*Premissas!$C$33+Premissas!$E$68*Premissas!$C$33 -> 3269829.5 | E35: =C35-D35 -> -430629.48 | F35: =IF(C35=0,0,E35/C35) -> -0.15167282 | G35: =E35-MAX(0,E35-Premissas!$E$52*(1-Premissas!$C$36)/10)*Premissas!$B$11-(Premissas!$E$52*(Premissas!$E$84+Premissas!$E$85/10)+(Premissas!$E$80+Premissas!$E$81+Premissas!$E$82+Premissas!$E$83)/10) -> -814029.48 | H35: =IFERROR(RATE(10,G35,-Premissas!$E$52,Premissas!$E$52*Premissas!$C$36),"< -10%") -> -0.18182644 | I35: =(D35+((Premissas!$E$52-Premissas!$E$52*Premissas!$C$36/(1+Premissas!$B$10)^10)*(Premissas!$B$10/(1-(1+Premissas!$B$10)^-10))+(Premissas!$E$52*(Premissas!$E$84+Premissas!$E$85/10)+(Premissas!$E$80+Premissas!$E$81+Premissas!$E$82+Premissas!$E$83)/10)))/B35 -> 252289 | J35: =Premissas!$E$77*Premissas!$C$32 -> 150000
A36: 25 semanas | B36: 25 | C36: =MIN(B36,Premissas!$C$30)*Premissas!$E$77*Premissas!$C$32+(B36-MIN(B36,Premissas!$C$30)-MIN(B36-MIN(B36,Premissas!$C$30),Premissas!$C$31))*Premissas!$E$77*Premissas!$C$32*(1-Premissas!$B$12)+MIN(B36-MIN(B36,Premissas!$C$30),Premissas!$C$31)*Premissas!$E$44*Premissas!$C$38*Premissas!$E$78*Premissas!$C$32*(1-Premissas!$B$12)+B36*Premissas!$E$44*Premissas!$B$14*Premissas!$B$13 -> 3509100 | D36: =B36*(Premissas!$E$70*Premissas!$C$34/Premissas!$B$6+Premissas!$E$75)*Premissas!$C$33+Premissas!$E$68*Premissas!$C$33 -> 3461470.3 | E36: =C36-D36 -> 47629.652 | F36: =IF(C36=0,0,E36/C36) -> 0.013573182 | G36: =E36-MAX(0,E36-Premissas!$E$52*(1-Premissas!$C$36)/10)*Premissas!$B$11-(Premissas!$E$52*(Premissas!$E$84+Premissas!$E$85/10)+(Premissas!$E$80+Premissas!$E$81+Premissas!$E$82+Premissas!$E$83)/10) -> -335770.35 | H36: =IFERROR(RATE(10,G36,-Premissas!$E$52,Premissas!$E$52*Premissas!$C$36),"< -10%") -> -0.112351 | I36: =(D36+((Premissas!$E$52-Premissas!$E$52*Premissas!$C$36/(1+Premissas!$B$10)^10)*(Premissas!$B$10/(1-(1+Premissas!$B$10)^-10))+(Premissas!$E$52*(Premissas!$E$84+Premissas!$E$85/10)+(Premissas!$E$80+Premissas!$E$81+Premissas!$E$82+Premissas!$E$83)/10)))/B36 -> 209496.84 | J36: =Premissas!$E$77*Premissas!$C$32 -> 150000
A37: 30 semanas | B37: 30 | C37: =MIN(B37,Premissas!$C$30)*Premissas!$E$77*Premissas!$C$32+(B37-MIN(B37,Premissas!$C$30)-MIN(B37-MIN(B37,Premissas!$C$30),Premissas!$C$31))*Premissas!$E$77*Premissas!$C$32*(1-Premissas!$B$12)+MIN(B37-MIN(B37,Premissas!$C$30),Premissas!$C$31)*Premissas!$E$44*Premissas!$C$38*Premissas!$E$78*Premissas!$C$32*(1-Premissas!$B$12)+B37*Premissas!$E$44*Premissas!$B$14*Premissas!$B$13 -> 4179000 | D37: =B37*(Premissas!$E$70*Premissas!$C$34/Premissas!$B$6+Premissas!$E$75)*Premissas!$C$33+Premissas!$E$68*Premissas!$C$33 -> 3653111.2 | E37: =C37-D37 -> 525888.78 | F37: =IF(C37=0,0,E37/C37) -> 0.12584082 | G37: =E37-MAX(0,E37-Premissas!$E$52*(1-Premissas!$C$36)/10)*Premissas!$B$11-(Premissas!$E$52*(Premissas!$E$84+Premissas!$E$85/10)+(Premissas!$E$80+Premissas!$E$81+Premissas!$E$82+Premissas!$E$83)/10) -> 142488.78 | H37: =IFERROR(RATE(10,G37,-Premissas!$E$52,Premissas!$E$52*Premissas!$C$36),"< -10%") -> -0.048446406 | I37: =(D37+((Premissas!$E$52-Premissas!$E$52*Premissas!$C$36/(1+Premissas!$B$10)^10)*(Premissas!$B$10/(1-(1+Premissas!$B$10)^-10))+(Premissas!$E$52*(Premissas!$E$84+Premissas!$E$85/10)+(Premissas!$E$80+Premissas!$E$81+Premissas!$E$82+Premissas!$E$83)/10)))/B37 -> 180968.73 | J37: =Premissas!$E$77*Premissas!$C$32 -> 150000
A38: 35 semanas | B38: 35 | C38: =MIN(B38,Premissas!$C$30)*Premissas!$E$77*Premissas!$C$32+(B38-MIN(B38,Premissas!$C$30)-MIN(B38-MIN(B38,Premissas!$C$30),Premissas!$C$31))*Premissas!$E$77*Premissas!$C$32*(1-Premissas!$B$12)+MIN(B38-MIN(B38,Premissas!$C$30),Premissas!$C$31)*Premissas!$E$44*Premissas!$C$38*Premissas!$E$78*Premissas!$C$32*(1-Premissas!$B$12)+B38*Premissas!$E$44*Premissas!$B$14*Premissas!$B$13 -> 4848900 | D38: =B38*(Premissas!$E$70*Premissas!$C$34/Premissas!$B$6+Premissas!$E$75)*Premissas!$C$33+Premissas!$E$68*Premissas!$C$33 -> 3844752.1 | E38: =C38-D38 -> 1004147.9 | F38: =IF(C38=0,0,E38/C38) -> 0.20708778 | G38: =E38-MAX(0,E38-Premissas!$E$52*(1-Premissas!$C$36)/10)*Premissas!$B$11-(Premissas!$E$52*(Premissas!$E$84+Premissas!$E$85/10)+(Premissas!$E$80+Premissas!$E$81+Premissas!$E$82+Premissas!$E$83)/10) -> 459537.62 | H38: =IFERROR(RATE(10,G38,-Premissas!$E$52,Premissas!$E$52*Premissas!$C$36),"< -10%") -> -0.0086169703 | I38: =(D38+((Premissas!$E$52-Premissas!$E$52*Premissas!$C$36/(1+Premissas!$B$10)^10)*(Premissas!$B$10/(1-(1+Premissas!$B$10)^-10))+(Premissas!$E$52*(Premissas!$E$84+Premissas!$E$85/10)+(Premissas!$E$80+Premissas!$E$81+Premissas!$E$82+Premissas!$E$83)/10)))/B38 -> 160591.51 | J38: =Premissas!$E$77*Premissas!$C$32 -> 150000
A40: A · 20 cab/40 pax · NOVO
A41: Semanas/ano | B41: Semanas | C41: Receita | D41: OPEX | E41: EBITDA | F41: Margem | G41: FCL anual | H41: TIR ~10a | I41: Custo próprio/sem. | J41: Tarifa charter/sem.
A42: 10 semanas | B42: 10 | C42: =MIN(B42,Premissas!$C$30)*Premissas!$F$77*Premissas!$C$32+(B42-MIN(B42,Premissas!$C$30)-MIN(B42-MIN(B42,Premissas!$C$30),Premissas!$C$31))*Premissas!$F$77*Premissas!$C$32*(1-Premissas!$B$12)+MIN(B42-MIN(B42,Premissas!$C$30),Premissas!$C$31)*Premissas!$F$44*Premissas!$C$38*Premissas!$F$78*Premissas!$C$32*(1-Premissas!$B$12)+B42*Premissas!$F$44*Premissas!$B$14*Premissas!$B$13 -> 1228200 | D42: =B42*(Premissas!$F$70*Premissas!$C$34/Premissas!$B$6+Premissas!$F$75)*Premissas!$C$33+Premissas!$F$68*Premissas!$C$33 -> 2519884.4 | E42: =C42-D42 -> -1291684.4 | F42: =IF(C42=0,0,E42/C42) -> -1.051689 | G42: =E42-MAX(0,E42-Premissas!$F$52*(1-Premissas!$C$35)/10)*Premissas!$B$11-(Premissas!$F$52*(Premissas!$F$84+Premissas!$F$85/10)+(Premissas!$F$80+Premissas!$F$81+Premissas!$F$82+Premissas!$F$83)/10) -> -1695014.4 | H42: =IFERROR(RATE(10,G42,-Premissas!$F$52,Premissas!$F$52*Premissas!$C$35),"< -10%") -> -0.1441194 | I42: =(D42+((Premissas!$F$52-Premissas!$F$52*Premissas!$C$35/(1+Premissas!$B$10)^10)*(Premissas!$B$10/(1-(1+Premissas!$B$10)^-10))+(Premissas!$F$52*(Premissas!$F$84+Premissas!$F$85/10)+(Premissas!$F$80+Premissas!$F$81+Premissas!$F$82+Premissas!$F$83)/10)))/B42 -> 643301.81 | J42: =Premissas!$F$77*Premissas!$C$32 -> 120000
A43: 15 semanas | B43: 15 | C43: =MIN(B43,Premissas!$C$30)*Premissas!$F$77*Premissas!$C$32+(B43-MIN(B43,Premissas!$C$30)-MIN(B43-MIN(B43,Premissas!$C$30),Premissas!$C$31))*Premissas!$F$77*Premissas!$C$32*(1-Premissas!$B$12)+MIN(B43-MIN(B43,Premissas!$C$30),Premissas!$C$31)*Premissas!$F$44*Premissas!$C$38*Premissas!$F$78*Premissas!$C$32*(1-Premissas!$B$12)+B43*Premissas!$F$44*Premissas!$B$14*Premissas!$B$13 -> 1775400 | D43: =B43*(Premissas!$F$70*Premissas!$C$34/Premissas!$B$6+Premissas!$F$75)*Premissas!$C$33+Premissas!$F$68*Premissas!$C$33 -> 2684084.7 | E43: =C43-D43 -> -908684.65 | F43: =IF(C43=0,0,E43/C43) -> -0.51181968 | G43: =E43-MAX(0,E43-Premissas!$F$52*(1-Premissas!$C$35)/10)*Premissas!$B$11-(Premissas!$F$52*(Premissas!$F$84+Premissas!$F$85/10)+(Premissas!$F$80+Premissas!$F$81+Premissas!$F$82+Premissas!$F$83)/10) -> -1312014.7 | H43: =IFERROR(RATE(10,G43,-Premissas!$F$52,Premissas!$F$52*Premissas!$C$35),"< -10%") -> -0.1239546 | I43: =(D43+((Premissas!$F$52-Premissas!$F$52*Premissas!$C$35/(1+Premissas!$B$10)^10)*(Premissas!$B$10/(1-(1+Premissas!$B$10)^-10))+(Premissas!$F$52*(Premissas!$F$84+Premissas!$F$85/10)+(Premissas!$F$80+Premissas!$F$81+Premissas!$F$82+Premissas!$F$83)/10)))/B43 -> 439814.55 | J43: =Premissas!$F$77*Premissas!$C$32 -> 120000
A44: 20 semanas | B44: 20 | C44: =MIN(B44,Premissas!$C$30)*Premissas!$F$77*Premissas!$C$32+(B44-MIN(B44,Premissas!$C$30)-MIN(B44-MIN(B44,Premissas!$C$30),Premissas!$C$31))*Premissas!$F$77*Premissas!$C$32*(1-Premissas!$B$12)+MIN(B44-MIN(B44,Premissas!$C$30),Premissas!$C$31)*Premissas!$F$44*Premissas!$C$38*Premissas!$F$78*Premissas!$C$32*(1-Premissas!$B$12)+B44*Premissas!$F$44*Premissas!$B$14*Premissas!$B$13 -> 2312400 | D44: =B44*(Premissas!$F$70*Premissas!$C$34/Premissas!$B$6+Premissas!$F$75)*Premissas!$C$33+Premissas!$F$68*Premissas!$C$33 -> 2848284.9 | E44: =C44-D44 -> -535884.87 | F44: =IF(C44=0,0,E44/C44) -> -0.23174402 | G44: =E44-MAX(0,E44-Premissas!$F$52*(1-Premissas!$C$35)/10)*Premissas!$B$11-(Premissas!$F$52*(Premissas!$F$84+Premissas!$F$85/10)+(Premissas!$F$80+Premissas!$F$81+Premissas!$F$82+Premissas!$F$83)/10) -> -939214.87 | H44: =IFERROR(RATE(10,G44,-Premissas!$F$52,Premissas!$F$52*Premissas!$C$35),"< -10%") -> -0.10474201 | I44: =(D44+((Premissas!$F$52-Premissas!$F$52*Premissas!$C$35/(1+Premissas!$B$10)^10)*(Premissas!$B$10/(1-(1+Premissas!$B$10)^-10))+(Premissas!$F$52*(Premissas!$F$84+Premissas!$F$85/10)+(Premissas!$F$80+Premissas!$F$81+Premissas!$F$82+Premissas!$F$83)/10)))/B44 -> 338070.93 | J44: =Premissas!$F$77*Premissas!$C$32 -> 120000
A45: 25 semanas | B45: 25 | C45: =MIN(B45,Premissas!$C$30)*Premissas!$F$77*Premissas!$C$32+(B45-MIN(B45,Premissas!$C$30)-MIN(B45-MIN(B45,Premissas!$C$30),Premissas!$C$31))*Premissas!$F$77*Premissas!$C$32*(1-Premissas!$B$12)+MIN(B45-MIN(B45,Premissas!$C$30),Premissas!$C$31)*Premissas!$F$44*Premissas!$C$38*Premissas!$F$78*Premissas!$C$32*(1-Premissas!$B$12)+B45*Premissas!$F$44*Premissas!$B$14*Premissas!$B$13 -> 2849400 | D45: =B45*(Premissas!$F$70*Premissas!$C$34/Premissas!$B$6+Premissas!$F$75)*Premissas!$C$33+Premissas!$F$68*Premissas!$C$33 -> 3012485.1 | E45: =C45-D45 -> -163085.09 | F45: =IF(C45=0,0,E45/C45) -> -0.057234887 | G45: =E45-MAX(0,E45-Premissas!$F$52*(1-Premissas!$C$35)/10)*Premissas!$B$11-(Premissas!$F$52*(Premissas!$F$84+Premissas!$F$85/10)+(Premissas!$F$80+Premissas!$F$81+Premissas!$F$82+Premissas!$F$83)/10) -> -566415.09 | H45: =IFERROR(RATE(10,G45,-Premissas!$F$52,Premissas!$F$52*Premissas!$C$35),"< -10%") -> -0.085921303 | I45: =(D45+((Premissas!$F$52-Premissas!$F$52*Premissas!$C$35/(1+Premissas!$B$10)^10)*(Premissas!$B$10/(1-(1+Premissas!$B$10)^-10))+(Premissas!$F$52*(Premissas!$F$84+Premissas!$F$85/10)+(Premissas!$F$80+Premissas!$F$81+Premissas!$F$82+Premissas!$F$83)/10)))/B45 -> 277024.75 | J45: =Premissas!$F$77*Premissas!$C$32 -> 120000
A46: 30 semanas | B46: 30 | C46: =MIN(B46,Premissas!$C$30)*Premissas!$F$77*Premissas!$C$32+(B46-MIN(B46,Premissas!$C$30)-MIN(B46-MIN(B46,Premissas!$C$30),Premissas!$C$31))*Premissas!$F$77*Premissas!$C$32*(1-Premissas!$B$12)+MIN(B46-MIN(B46,Premissas!$C$30),Premissas!$C$31)*Premissas!$F$44*Premissas!$C$38*Premissas!$F$78*Premissas!$C$32*(1-Premissas!$B$12)+B46*Premissas!$F$44*Premissas!$B$14*Premissas!$B$13 -> 3386400 | D46: =B46*(Premissas!$F$70*Premissas!$C$34/Premissas!$B$6+Premissas!$F$75)*Premissas!$C$33+Premissas!$F$68*Premissas!$C$33 -> 3176685.3 | E46: =C46-D46 -> 209714.7 | F46: =IF(C46=0,0,E46/C46) -> 0.061928507 | G46: =E46-MAX(0,E46-Premissas!$F$52*(1-Premissas!$C$35)/10)*Premissas!$B$11-(Premissas!$F$52*(Premissas!$F$84+Premissas!$F$85/10)+(Premissas!$F$80+Premissas!$F$81+Premissas!$F$82+Premissas!$F$83)/10) -> -193615.3 | H46: =IFERROR(RATE(10,G46,-Premissas!$F$52,Premissas!$F$52*Premissas!$C$35),"< -10%") -> -0.067472929 | I46: =(D46+((Premissas!$F$52-Premissas!$F$52*Premissas!$C$35/(1+Premissas!$B$10)^10)*(Premissas!$B$10/(1-(1+Premissas!$B$10)^-10))+(Premissas!$F$52*(Premissas!$F$84+Premissas!$F$85/10)+(Premissas!$F$80+Premissas!$F$81+Premissas!$F$82+Premissas!$F$83)/10)))/B46 -> 236327.3 | J46: =Premissas!$F$77*Premissas!$C$32 -> 120000
A47: 35 semanas | B47: 35 | C47: =MIN(B47,Premissas!$C$30)*Premissas!$F$77*Premissas!$C$32+(B47-MIN(B47,Premissas!$C$30)-MIN(B47-MIN(B47,Premissas!$C$30),Premissas!$C$31))*Premissas!$F$77*Premissas!$C$32*(1-Premissas!$B$12)+MIN(B47-MIN(B47,Premissas!$C$30),Premissas!$C$31)*Premissas!$F$44*Premissas!$C$38*Premissas!$F$78*Premissas!$C$32*(1-Premissas!$B$12)+B47*Premissas!$F$44*Premissas!$B$14*Premissas!$B$13 -> 3923400 | D47: =B47*(Premissas!$F$70*Premissas!$C$34/Premissas!$B$6+Premissas!$F$75)*Premissas!$C$33+Premissas!$F$68*Premissas!$C$33 -> 3340885.5 | E47: =C47-D47 -> 582514.48 | F47: =IF(C47=0,0,E47/C47) -> 0.14847186 | G47: =E47-MAX(0,E47-Premissas!$F$52*(1-Premissas!$C$35)/10)*Premissas!$B$11-(Premissas!$F$52*(Premissas!$F$84+Premissas!$F$85/10)+(Premissas!$F$80+Premissas!$F$81+Premissas!$F$82+Premissas!$F$83)/10) -> 179184.48 | H47: =IFERROR(RATE(10,G47,-Premissas!$F$52,Premissas!$F$52*Premissas!$C$35),"< -10%") -> -0.049376162 | I47: =(D47+((Premissas!$F$52-Premissas!$F$52*Premissas!$C$35/(1+Premissas!$B$10)^10)*(Premissas!$B$10/(1-(1+Premissas!$B$10)^-10))+(Premissas!$F$52*(Premissas!$F$84+Premissas!$F$85/10)+(Premissas!$F$80+Premissas!$F$81+Premissas!$F$82+Premissas!$F$83)/10)))/B47 -> 207257.69 | J47: =Premissas!$F$77*Premissas!$C$32 -> 120000
A49: A · 18 cab/36 pax · USADO
A50: Semanas/ano | B50: Semanas | C50: Receita | D50: OPEX | E50: EBITDA | F50: Margem | G50: FCL anual | H50: TIR ~10a | I50: Custo próprio/sem. | J50: Tarifa charter/sem.
A51: 10 semanas | B51: 10 | C51: =MIN(B51,Premissas!$C$30)*Premissas!$G$77*Premissas!$C$32+(B51-MIN(B51,Premissas!$C$30)-MIN(B51-MIN(B51,Premissas!$C$30),Premissas!$C$31))*Premissas!$G$77*Premissas!$C$32*(1-Premissas!$B$12)+MIN(B51-MIN(B51,Premissas!$C$30),Premissas!$C$31)*Premissas!$G$44*Premissas!$C$38*Premissas!$G$78*Premissas!$C$32*(1-Premissas!$B$12)+B51*Premissas!$G$44*Premissas!$B$14*Premissas!$B$13 -> 1053840 | D51: =B51*(Premissas!$G$70*Premissas!$C$34/Premissas!$B$6+Premissas!$G$75)*Premissas!$C$33+Premissas!$G$68*Premissas!$C$33 -> 2389938.8 | E51: =C51-D51 -> -1336098.8 | F51: =IF(C51=0,0,E51/C51) -> -1.2678384 | G51: =E51-MAX(0,E51-Premissas!$G$52*(1-Premissas!$C$36)/10)*Premissas!$B$11-(Premissas!$G$52*(Premissas!$G$84+Premissas!$G$85/10)+(Premissas!$G$80+Premissas!$G$81+Premissas!$G$82+Premissas!$G$83)/10) -> -1646098.8 | H51: =IFERROR(RATE(10,G51,-Premissas!$G$52,Premissas!$G$52*Premissas!$C$36),"< -10%") -> -0.33498415 | I51: =(D51+((Premissas!$G$52-Premissas!$G$52*Premissas!$C$36/(1+Premissas!$B$10)^10)*(Premissas!$B$10/(1-(1+Premissas!$B$10)^-10))+(Premissas!$G$52*(Premissas!$G$84+Premissas!$G$85/10)+(Premissas!$G$80+Premissas!$G$81+Premissas!$G$82+Premissas!$G$83)/10)))/B51 -> 401366.58 | J51: =Premissas!$G$77*Premissas!$C$32 -> 105000
A52: 15 semanas | B52: 15 | C52: =MIN(B52,Premissas!$C$30)*Premissas!$G$77*Premissas!$C$32+(B52-MIN(B52,Premissas!$C$30)-MIN(B52-MIN(B52,Premissas!$C$30),Premissas!$C$31))*Premissas!$G$77*Premissas!$C$32*(1-Premissas!$B$12)+MIN(B52-MIN(B52,Premissas!$C$30),Premissas!$C$31)*Premissas!$G$44*Premissas!$C$38*Premissas!$G$78*Premissas!$C$32*(1-Premissas!$B$12)+B52*Premissas!$G$44*Premissas!$B$14*Premissas!$B$13 -> 1511130 | D52: =B52*(Premissas!$G$70*Premissas!$C$34/Premissas!$B$6+Premissas!$G$75)*Premissas!$C$33+Premissas!$G$68*Premissas!$C$33 -> 2541146.2 | E52: =C52-D52 -> -1030016.2 | F52: =IF(C52=0,0,E52/C52) -> -0.68161983 | G52: =E52-MAX(0,E52-Premissas!$G$52*(1-Premissas!$C$36)/10)*Premissas!$B$11-(Premissas!$G$52*(Premissas!$G$84+Premissas!$G$85/10)+(Premissas!$G$80+Premissas!$G$81+Premissas!$G$82+Premissas!$G$83)/10) -> -1340016.2 | H52: =IFERROR(RATE(10,G52,-Premissas!$G$52,Premissas!$G$52*Premissas!$C$36),"< -10%") -> -0.27901131 | I52: =(D52+((Premissas!$G$52-Premissas!$G$52*Premissas!$C$36/(1+Premissas!$B$10)^10)*(Premissas!$B$10/(1-(1+Premissas!$B$10)^-10))+(Premissas!$G$52*(Premissas!$G$84+Premissas!$G$85/10)+(Premissas!$G$80+Premissas!$G$81+Premissas!$G$82+Premissas!$G$83)/10)))/B52 -> 277658.21 | J52: =Premissas!$G$77*Premissas!$C$32 -> 105000
A53: 20 semanas | B53: 20 | C53: =MIN(B53,Premissas!$C$30)*Premissas!$G$77*Premissas!$C$32+(B53-MIN(B53,Premissas!$C$30)-MIN(B53-MIN(B53,Premissas!$C$30),Premissas!$C$31))*Premissas!$G$77*Premissas!$C$32*(1-Premissas!$B$12)+MIN(B53-MIN(B53,Premissas!$C$30),Premissas!$C$31)*Premissas!$G$44*Premissas!$C$38*Premissas!$G$78*Premissas!$C$32*(1-Premissas!$B$12)+B53*Premissas!$G$44*Premissas!$B$14*Premissas!$B$13 -> 1981680 | D53: =B53*(Premissas!$G$70*Premissas!$C$34/Premissas!$B$6+Premissas!$G$75)*Premissas!$C$33+Premissas!$G$68*Premissas!$C$33 -> 2692353.6 | E53: =C53-D53 -> -710673.57 | F53: =IF(C53=0,0,E53/C53) -> -0.35862176 | G53: =E53-MAX(0,E53-Premissas!$G$52*(1-Premissas!$C$36)/10)*Premissas!$B$11-(Premissas!$G$52*(Premissas!$G$84+Premissas!$G$85/10)+(Premissas!$G$80+Premissas!$G$81+Premissas!$G$82+Premissas!$G$83)/10) -> -1020673.6 | H53: =IFERROR(RATE(10,G53,-Premissas!$G$52,Premissas!$G$52*Premissas!$C$36),"< -10%") -> -0.22349002 | I53: =(D53+((Premissas!$G$52-Premissas!$G$52*Premissas!$C$36/(1+Premissas!$B$10)^10)*(Premissas!$B$10/(1-(1+Premissas!$B$10)^-10))+(Premissas!$G$52*(Premissas!$G$84+Premissas!$G$85/10)+(Premissas!$G$80+Premissas!$G$81+Premissas!$G$82+Premissas!$G$83)/10)))/B53 -> 215804.03 | J53: =Premissas!$G$77*Premissas!$C$32 -> 105000
A54: 25 semanas | B54: 25 | C54: =MIN(B54,Premissas!$C$30)*Premissas!$G$77*Premissas!$C$32+(B54-MIN(B54,Premissas!$C$30)-MIN(B54-MIN(B54,Premissas!$C$30),Premissas!$C$31))*Premissas!$G$77*Premissas!$C$32*(1-Premissas!$B$12)+MIN(B54-MIN(B54,Premissas!$C$30),Premissas!$C$31)*Premissas!$G$44*Premissas!$C$38*Premissas!$G$78*Premissas!$C$32*(1-Premissas!$B$12)+B54*Premissas!$G$44*Premissas!$B$14*Premissas!$B$13 -> 2452230 | D54: =B54*(Premissas!$G$70*Premissas!$C$34/Premissas!$B$6+Premissas!$G$75)*Premissas!$C$33+Premissas!$G$68*Premissas!$C$33 -> 2843561 | E54: =C54-D54 -> -391330.96 | F54: =IF(C54=0,0,E54/C54) -> -0.15958167 | G54: =E54-MAX(0,E54-Premissas!$G$52*(1-Premissas!$C$36)/10)*Premissas!$B$11-(Premissas!$G$52*(Premissas!$G$84+Premissas!$G$85/10)+(Premissas!$G$80+Premissas!$G$81+Premissas!$G$82+Premissas!$G$83)/10) -> -701330.96 | H54: =IFERROR(RATE(10,G54,-Premissas!$G$52,Premissas!$G$52*Premissas!$C$36),"< -10%") -> -0.17118018 | I54: =(D54+((Premissas!$G$52-Premissas!$G$52*Premissas!$C$36/(1+Premissas!$B$10)^10)*(Premissas!$B$10/(1-(1+Premissas!$B$10)^-10))+(Premissas!$G$52*(Premissas!$G$84+Premissas!$G$85/10)+(Premissas!$G$80+Premissas!$G$81+Premissas!$G$82+Premissas!$G$83)/10)))/B54 -> 178691.52 | J54: =Premissas!$G$77*Premissas!$C$32 -> 105000
A55: 30 semanas | B55: 30 | C55: =MIN(B55,Premissas!$C$30)*Premissas!$G$77*Premissas!$C$32+(B55-MIN(B55,Premissas!$C$30)-MIN(B55-MIN(B55,Premissas!$C$30),Premissas!$C$31))*Premissas!$G$77*Premissas!$C$32*(1-Premissas!$B$12)+MIN(B55-MIN(B55,Premissas!$C$30),Premissas!$C$31)*Premissas!$G$44*Premissas!$C$38*Premissas!$G$78*Premissas!$C$32*(1-Premissas!$B$12)+B55*Premissas!$G$44*Premissas!$B$14*Premissas!$B$13 -> 2922780 | D55: =B55*(Premissas!$G$70*Premissas!$C$34/Premissas!$B$6+Premissas!$G$75)*Premissas!$C$33+Premissas!$G$68*Premissas!$C$33 -> 2994768.3 | E55: =C55-D55 -> -71988.348 | F55: =IF(C55=0,0,E55/C55) -> -0.024630095 | G55: =E55-MAX(0,E55-Premissas!$G$52*(1-Premissas!$C$36)/10)*Premissas!$B$11-(Premissas!$G$52*(Premissas!$G$84+Premissas!$G$85/10)+(Premissas!$G$80+Premissas!$G$81+Premissas!$G$82+Premissas!$G$83)/10) -> -381988.35 | H55: =IFERROR(RATE(10,G55,-Premissas!$G$52,Premissas!$G$52*Premissas!$C$36),"< -10%") -> -0.12202565 | I55: =(D55+((Premissas!$G$52-Premissas!$G$52*Premissas!$C$36/(1+Premissas!$B$10)^10)*(Premissas!$B$10/(1-(1+Premissas!$B$10)^-10))+(Premissas!$G$52*(Premissas!$G$84+Premissas!$G$85/10)+(Premissas!$G$80+Premissas!$G$81+Premissas!$G$82+Premissas!$G$83)/10)))/B55 -> 153949.84 | J55: =Premissas!$G$77*Premissas!$C$32 -> 105000
A56: 35 semanas | B56: 35 | C56: =MIN(B56,Premissas!$C$30)*Premissas!$G$77*Premissas!$C$32+(B56-MIN(B56,Premissas!$C$30)-MIN(B56-MIN(B56,Premissas!$C$30),Premissas!$C$31))*Premissas!$G$77*Premissas!$C$32*(1-Premissas!$B$12)+MIN(B56-MIN(B56,Premissas!$C$30),Premissas!$C$31)*Premissas!$G$44*Premissas!$C$38*Premissas!$G$78*Premissas!$C$32*(1-Premissas!$B$12)+B56*Premissas!$G$44*Premissas!$B$14*Premissas!$B$13 -> 3393330 | D56: =B56*(Premissas!$G$70*Premissas!$C$34/Premissas!$B$6+Premissas!$G$75)*Premissas!$C$33+Premissas!$G$68*Premissas!$C$33 -> 3145975.7 | E56: =C56-D56 -> 247354.26 | F56: =IF(C56=0,0,E56/C56) -> 0.072894255 | G56: =E56-MAX(0,E56-Premissas!$G$52*(1-Premissas!$C$36)/10)*Premissas!$B$11-(Premissas!$G$52*(Premissas!$G$84+Premissas!$G$85/10)+(Premissas!$G$80+Premissas!$G$81+Premissas!$G$82+Premissas!$G$83)/10) -> -62645.739 | H56: =IFERROR(RATE(10,G56,-Premissas!$G$52,Premissas!$G$52*Premissas!$C$36),"< -10%") -> -0.075742097 | I56: =(D56+((Premissas!$G$52-Premissas!$G$52*Premissas!$C$36/(1+Premissas!$B$10)^10)*(Premissas!$B$10/(1-(1+Premissas!$B$10)^-10))+(Premissas!$G$52*(Premissas!$G$84+Premissas!$G$85/10)+(Premissas!$G$80+Premissas!$G$81+Premissas!$G$82+Premissas!$G$83)/10)))/B56 -> 136277.22 | J56: =Premissas!$G$77*Premissas!$C$32 -> 105000
A58: Custo próprio/semana = (OPEX + custo de capital anual: anuidade do CAPEX líquido do residual descontado @ hurdle + CAPEX de manutenção médio) ÷ semanas. Se > tarifa de charter, fretar é mais barato.

Sheet Buy_Build_Charter
A1: Buy × Build × Charter — ponto de equilíbrio entre possuir e fretar
A2: Semanas a partir das quais possuir fica mais barato que fretar: w* = (OPEX fixo + custo anual de capital) ÷ (tarifa de charter − custo variável por semana). Cenário Base.
A4: 1. Crossover por opção (cenário Base)
A5: Métrica | B5: C · 36 cab/72 pax · NOVO | C5: C · 36 cab/72 pax · USADO | D5: B · 24 cab/48 pax · NOVO | E5: B · 24 cab/48 pax · USADO | F5: A · 20 cab/40 pax · NOVO | G5: A · 18 cab/36 pax · USADO
A6: CAPEX total | B6: =Premissas!$B$52 -> 47709000 | C6: =Premissas!$C$52 -> 21400000 | D6: =Premissas!$D$52 -> 31940000 | E6: =Premissas!$E$52 -> 10600000 | F6: =Premissas!$F$52 -> 27370000 | G6: =Premissas!$G$52 -> 10000000
A7: Valor residual ano 10 (% CAPEX) | B7: =Premissas!$C$35 -> 0.55 | C7: =Premissas!$C$36 -> 0.5 | D7: =Premissas!$C$35 -> 0.55 | E7: =Premissas!$C$36 -> 0.5 | F7: =Premissas!$C$35 -> 0.55 | G7: =Premissas!$C$36 -> 0.5
A8: Fator de recuperação de capital (hurdle, 10 anos) | B8: =Premissas!$B$10/(1-(1+Premissas!$B$10)^-10) -> 0.16274539 | C8: =Premissas!$B$10/(1-(1+Premissas!$B$10)^-10) -> 0.16274539 | D8: =Premissas!$B$10/(1-(1+Premissas!$B$10)^-10) -> 0.16274539 | E8: =Premissas!$B$10/(1-(1+Premissas!$B$10)^-10) -> 0.16274539 | F8: =Premissas!$B$10/(1-(1+Premissas!$B$10)^-10) -> 0.16274539 | G8: =Premissas!$B$10/(1-(1+Premissas!$B$10)^-10) -> 0.16274539
A9: CAPEX de manutenção + docagens médios/ano | B9: =Premissas!$B$52*(Premissas!$B$84+Premissas!$B$85/10)+(Premissas!$B$80+Premissas!$B$81+Premissas!$B$82+Premissas!$B$83)/10 -> 684381 | C9: =Premissas!$C$52*(Premissas!$C$84+Premissas!$C$85/10)+(Premissas!$C$80+Premissas!$C$81+Premissas!$C$82+Premissas!$C$83)/10 -> 604600 | D9: =Premissas!$D$52*(Premissas!$D$84+Premissas!$D$85/10)+(Premissas!$D$80+Premissas!$D$81+Premissas!$D$82+Premissas!$D$83)/10 -> 472460 | E9: =Premissas!$E$52*(Premissas!$E$84+Premissas!$E$85/10)+(Premissas!$E$80+Premissas!$E$81+Premissas!$E$82+Premissas!$E$83)/10 -> 383400 | F9: =Premissas!$F$52*(Premissas!$F$84+Premissas!$F$85/10)+(Premissas!$F$80+Premissas!$F$81+Premissas!$F$82+Premissas!$F$83)/10 -> 403330 | G9: =Premissas!$G$52*(Premissas!$G$84+Premissas!$G$85/10)+(Premissas!$G$80+Premissas!$G$81+Premissas!$G$82+Premissas!$G$83)/10 -> 310000
A10: Custo anual de capital (anuidade + manutenção) | B10: =(B6-B6*B7/(1+Premissas!$B$10)^10)*B8+B9 -> 6802365 | C10: =(C6-C6*C7/(1+Premissas!$B$10)^10)*C8+C9 -> 3415975.7 | D10: =(D6-D6*D7/(1+Premissas!$B$10)^10)*D8+D9 -> 4568299.6 | E10: =(E6-E6*E7/(1+Premissas!$B$10)^10)*E8+E9 -> 1775950.6 | F10: =(F6-F6*F7/(1+Premissas!$B$10)^10)*F8+F9 -> 3913133.7 | G10: =(G6-G6*G7/(1+Premissas!$B$10)^10)*G8+G9 -> 1623727
A11: OPEX fixo anual | B11: =Premissas!$B$68*Premissas!$C$33 -> 3394172 | C11: =Premissas!$C$68*Premissas!$C$33 -> 3453700 | D11: =Premissas!$D$68*Premissas!$C$33 -> 2528986 | E11: =Premissas!$E$68*Premissas!$C$33 -> 2503266 | F11: =Premissas!$F$68*Premissas!$C$33 -> 2191484 | G11: =Premissas!$G$68*Premissas!$C$33 -> 2087524
A12: Custo variável por semana | B12: =(Premissas!$B$70*Premissas!$C$34/Premissas!$B$6+Premissas!$B$75)*Premissas!$C$33 -> 55271.13 | C12: =(Premissas!$C$70*Premissas!$C$34/Premissas!$B$6+Premissas!$C$75)*Premissas!$C$33 -> 55271.13 | D12: =(Premissas!$D$70*Premissas!$C$34/Premissas!$B$6+Premissas!$D$75)*Premissas!$C$33 -> 38328.174 | E12: =(Premissas!$E$70*Premissas!$C$34/Premissas!$B$6+Premissas!$E$75)*Premissas!$C$33 -> 38328.174 | F12: =(Premissas!$F$70*Premissas!$C$34/Premissas!$B$6+Premissas!$F$75)*Premissas!$C$33 -> 32840.043 | G12: =(Premissas!$G$70*Premissas!$C$34/Premissas!$B$6+Premissas!$G$75)*Premissas!$C$33 -> 30241.478
A13: Tarifa de charter de mercado equivalente (€/semana) | B13: =Premissas!$B$77*Premissas!$C$32 -> 300000 | C13: =Premissas!$C$77*Premissas!$C$32 -> 270000 | D13: =Premissas!$D$77*Premissas!$C$32 -> 170000 | E13: =Premissas!$E$77*Premissas!$C$32 -> 150000 | F13: =Premissas!$F$77*Premissas!$C$32 -> 120000 | G13: =Premissas!$G$77*Premissas!$C$32 -> 105000
A14: SEMANAS PARA POSSUIR = FRETAR (w*) | B14: =(B11+B10)/(B13-B12) -> 41.664627 | C14: =(C11+C10)/(C13-C12) -> 31.992325 | D14: =(D11+D10)/(D13-D12) -> 53.901322 | E14: =(E11+E10)/(E13-E12) -> 38.319572 | F14: =(F11+F10)/(F13-F12) -> 70.039246 | G14: =(G11+G10)/(G13-G12) -> 49.643183
A15: Semanas p/ break-even de EBITDA (sem custo de capital) | B15: =B11/(B13-B12) -> 13.869112 | C15: =C11/(C13-C12) -> 16.084004 | D15: =D11/(D13-D12) -> 19.206736 | E15: =E11/(E13-E12) -> 22.416272 | F15: =F11/(F13-F12) -> 25.143243 | G15: =G11/(G13-G12) -> 27.923559
A16: Custo próprio por semana @ 26 semanas | B16: =(B11+B10)/26+B12 -> 447445.63 | C16: =(C11+C10)/26+C12 -> 319489.43 | D16: =(D11+D10)/26+D12 -> 311300.7 | E16: =(E11+E10)/26+E12 -> 202913.43 | F16: =(F11+F10)/26+F12 -> 267633.03 | G16: =(G11+G10)/26+G12 -> 172981.9
A17: Custo próprio vs. tarifa @ 26 semanas | B17: =B16/B13-1 -> 0.49148544 | C17: =C16/C13-1 -> 0.18329418 | D17: =D16/D13-1 -> 0.83118056 | E17: =E16/E13-1 -> 0.35275618 | F17: =F16/F13-1 -> 1.2302753 | G17: =G16/G13-1 -> 0.64744667
A18: Custo próprio por semana @ 30 semanas (máx. temporada Med) | B18: =(B11+B10)/30+B12 -> 395155.7 | C18: =(C11+C10)/30+C12 -> 284260.32 | D18: =(D11+D10)/30+D12 -> 274904.36 | E18: =(E11+E10)/30+E12 -> 180968.73 | F18: =(F11+F10)/30+F12 -> 236327.3 | G18: =(G11+G10)/30+G12 -> 153949.84
A19: Custo próprio vs. tarifa @ 30 semanas | B19: =B18/B13-1 -> 0.31718566 | C19: =C18/C13-1 -> 0.052816005 | D19: =D18/D13-1 -> 0.61708447 | E19: =E18/E13-1 -> 0.20645818 | F19: =F18/F13-1 -> 0.96939416 | G19: =G18/G13-1 -> 0.46618899
A20: Fator de anuidade (10 anos @ hurdle) | B20: =(1-(1+Premissas!$B$10)^-10)/Premissas!$B$10 -> 6.1445671 | C20: =(1-(1+Premissas!$B$10)^-10)/Premissas!$B$10 -> 6.1445671 | D20: =(1-(1+Premissas!$B$10)^-10)/Premissas!$B$10 -> 6.1445671 | E20: =(1-(1+Premissas!$B$10)^-10)/Premissas!$B$10 -> 6.1445671 | F20: =(1-(1+Premissas!$B$10)^-10)/Premissas!$B$10 -> 6.1445671 | G20: =(1-(1+Premissas!$B$10)^-10)/Premissas!$B$10 -> 6.1445671
A21: CAPEX máximo justificável @ 26 sem. (VPL=0, aprox.) | B21: =MAX(0,((26*(B13-B12)-B11)*(1-Premissas!$B$11)-((Premissas!$B$80+Premissas!$B$81+Premissas!$B$82+Premissas!$B$83)/10))*B20/(1+(Premissas!$B$84+Premissas!$B$85/10)*B20-Premissas!$C$35/(1+Premissas!$B$10)^10)) -> 12419489 | C21: =MAX(0,((26*(C13-C12)-C11)*(1-Premissas!$B$11)-((Premissas!$C$80+Premissas!$C$81+Premissas!$C$82+Premissas!$C$83)/10))*C20/(1+(Premissas!$C$84+Premissas!$C$85/10)*C20-Premissas!$C$36/(1+Premissas!$B$10)^10)) -> 7568858.7 | D21: =MAX(0,((26*(D13-D12)-D11)*(1-Premissas!$B$11)-((Premissas!$D$80+Premissas!$D$81+Premissas!$D$82+Premissas!$D$83)/10))*D20/(1+(Premissas!$D$84+Premissas!$D$85/10)*D20-Premissas!$C$35/(1+Premissas!$B$10)^10)) -> 2953740 | E21: =MAX(0,((26*(E13-E12)-E11)*(1-Premissas!$B$11)-((Premissas!$E$80+Premissas!$E$81+Premissas!$E$82+Premissas!$E$83)/10))*E20/(1+(Premissas!$E$84+Premissas!$E$85/10)*E20-Premissas!$C$36/(1+Premissas!$B$10)^10)) -> 200401.97 | F21: =MAX(0,((26*(F13-F12)-F11)*(1-Premissas!$B$11)-((Premissas!$F$80+Premissas!$F$81+Premissas!$F$82+Premissas!$F$83)/10))*F20/(1+(Premissas!$F$84+Premissas!$F$85/10)*F20-Premissas!$C$35/(1+Premissas!$B$10)^10)) -> 0 | G21: =MAX(0,((26*(G13-G12)-G11)*(1-Premissas!$B$11)-((Premissas!$G$80+Premissas!$G$81+Premissas!$G$82+Premissas!$G$83)/10))*G20/(1+(Premissas!$G$84+Premissas!$G$85/10)*G20-Premissas!$C$36/(1+Premissas!$B$10)^10)) -> 0
A22: CAPEX máximo justificável @ 30 sem. (VPL=0, aprox.) | B22: =MAX(0,((30*(B13-B12)-B11)*(1-Premissas!$B$11)-((Premissas!$B$80+Premissas!$B$81+Premissas!$B$82+Premissas!$B$83)/10))*B20/(1+(Premissas!$B$84+Premissas!$B$85/10)*B20-Premissas!$C$35/(1+Premissas!$B$10)^10)) -> 17127342 | C22: =MAX(0,((30*(C13-C12)-C11)*(1-Premissas!$B$11)-((Premissas!$C$80+Premissas!$C$81+Premissas!$C$82+Premissas!$C$83)/10))*C20/(1+(Premissas!$C$84+Premissas!$C$85/10)*C20-Premissas!$C$36/(1+Premissas!$B$10)^10)) -> 11468382 | D22: =MAX(0,((30*(D13-D12)-D11)*(1-Premissas!$B$11)-((Premissas!$D$80+Premissas!$D$81+Premissas!$D$82+Premissas!$D$83)/10))*D20/(1+(Premissas!$D$84+Premissas!$D$85/10)*D20-Premissas!$C$35/(1+Premissas!$B$10)^10)) -> 5486712.9 | E22: =MAX(0,((30*(E13-E12)-E11)*(1-Premissas!$B$11)-((Premissas!$E$80+Premissas!$E$81+Premissas!$E$82+Premissas!$E$83)/10))*E20/(1+(Premissas!$E$84+Premissas!$E$85/10)*E20-Premissas!$C$36/(1+Premissas!$B$10)^10)) -> 2228386.8 | F22: =MAX(0,((30*(F13-F12)-F11)*(1-Premissas!$B$11)-((Premissas!$F$80+Premissas!$F$81+Premissas!$F$82+Premissas!$F$83)/10))*F20/(1+(Premissas!$F$84+Premissas!$F$85/10)*F20-Premissas!$C$35/(1+Premissas!$B$10)^10)) -> 891808.34 | G22: =MAX(0,((30*(G13-G12)-G11)*(1-Premissas!$B$11)-((Premissas!$G$80+Premissas!$G$81+Premissas!$G$82+Premissas!$G$83)/10))*G20/(1+(Premissas!$G$84+Premissas!$G$85/10)*G20-Premissas!$C$36/(1+Premissas!$B$10)^10)) -> 0
A23: Aprox.: considera tarifa de mercado em todas as semanas (sem comissão) e imposto sobre EBITDA (conservador).
A25: 2. Comparativo executivo (cenário Base, 72 pax onde aplicável)
A26: Critério | B26: Comprar usado (C_USADO) | C26: Construir novo (C_NOVO) | D26: Charter (72 pax) | E26: Comprar usado 48 pax (B_USADO)
A27: Investimento inicial | B27: =Projecao!$C$205 -> 21400000 | C27: =Projecao!$C$82 -> 47709000 | D27: =0 -> 0 | E27: =Projecao!$C$451 -> 10600000
A28: Tempo até operação | B28: 9–15 meses | C28: 30–40 meses | D28: Imediato (reserva 12–18 meses antes) | E28: 6–12 meses
A29: Risco | B29: Médio-alto (casco, retrofit, ativo) | C29: Alto (estaleiro, prazo, capital) | D29: Baixo (disponibilidade/preço) | E29: Médio
A30: OPEX ano 3 | B30: =Projecao!$C$203 -> 5188596 | C30: =Projecao!$C$80 -> 5125442.8 | D30: Embutido na tarifa | E30: =Projecao!$C$449 -> 3712936.3
A31: Flexibilidade | B31: Baixa | C31: Muito baixa | D31: Alta (navio, data, destino) | E31: Baixa
A32: Controle do produto | B32: Alto | C32: Total | D32: Médio (co-branding) | E32: Alto
A33: Potencial de receita externa | B33: Sim (charter/cabines) | C33: Sim (charter/cabines) | D33: Não | E33: Sim
A34: Valor residual ano 10 | B34: =Projecao!$C$206 -> 10700000 | C34: =Projecao!$C$83 -> 26239950 | D34: =0 -> 0 | E34: =Projecao!$C$452 -> 5300000
A35: Break-even EBITDA (semanas/ano) | B35: =Projecao!$C$204 -> 18.266043 | C35: =Projecao!$C$81 -> 15.763871 | D35: n/a | E35: =Projecao!$C$450 -> 24.924682
A36: Semanas p/ possuir = fretar (w*) | B36: =C14 -> 31.992325 | C36: =B14 -> 41.664627 | D36: referência | E36: =E14 -> 38.319572
A37: ROI 10 anos | B37: =Projecao!$C$198 -> -0.20057545 | C37: =Projecao!$C$75 -> -0.1463918 | D37: n/a | E37: =Projecao!$C$444 -> -0.89647648
A38: TIR 10 anos (desalavancada) | B38: =Projecao!$C$195 -> -0.026968782 | C38: =Projecao!$C$72 -> -0.017419323 | D38: n/a | E38: =Projecao!$C$441 -> -0.13555315
A39: VPL @ hurdle | B39: =Projecao!$C$196 -> -13109788 | C39: =Projecao!$C$73 -> -31517619 | D39: =0 -> 0 | E39: =Projecao!$C$442 -> -10853228

Sheet Financiamento
A1: Financiamento — impacto da alavancagem (cenário Base)
A2: Dívida sacada na entrega (ano 0), amortização linear com balloon no ano 10; juros sobre saldo inicial. Benefício fiscal dos juros considerado (×34%) limitado ao EBIT positivo.
B4: C · 36 cab/72 pax · USADO — 100% equity / 0% dívida
B5: LTV (dívida / CAPEX) | C5: 0
B6: Ano | C6: -2 | D6: -1 | E6: 0 | F6: 1 | G6: 2 | H6: 3 | I6: 4 | J6: 5 | K6: 6 | L6: 7 | M6: 8 | N6: 9 | O6: 10
B7: FCL desalavancado (link Projecao) | C7: =Projecao!C192 -> 0 | D7: =Projecao!D192 -> 0 | E7: =Projecao!E192 -> -21400000 | F7: =Projecao!F192 -> 593050.02 | G7: =Projecao!G192 -> 1158531.4 | H7: =Projecao!H192 -> 683268.89 | I7: =Projecao!I192 -> 1162338.2 | J7: =Projecao!J192 -> 37987.597 | ... O7: =Projecao!O192 -> 10425384
B8: Captação da dívida | C8: 0 | D8: 0 | E8: =Projecao!$C$205*$C$5 -> 0 | F8: 0 | G8: 0 | H8: 0 | I8: 0 | J8: 0 | K8: 0 | L8: 0 | M8: 0 | N8: 0 | O8: 0
B9: Saldo inicial da dívida | C9: 0 | D9: 0 | E9: 0 | F9: =E8 -> 0 | G9: =F9-F11 -> 0 | H9: =G9-G11 -> 0 | I9: =H9-H11 -> 0 | J9: =I9-I11 -> 0 | K9: =J9-J11 -> 0 | L9: =K9-K11 -> 0 | M9: =L9-L11 -> 0 | N9: =M9-M11 -> 0 | O9: =N9-N11 -> 0
B10: Juros | C10: =-C9*Premissas!$B$23 -> 0 | D10: =-D9*Premissas!$B$23 -> 0 | E10: =-E9*Premissas!$B$23 -> 0 | F10: =-F9*Premissas!$B$23 -> 0 | G10: =-G9*Premissas!$B$23 -> 0 | H10: =-H9*Premissas!$B$23 -> 0 | I10: =-I9*Premissas!$B$23 -> 0 | J10: =-J9*Premissas!$B$23 -> 0 | ... O10: =-O9*Premissas!$B$23 -> 0
B11: Amortização (inclui balloon no ano 10) | C11: 0 | D11: 0 | E11: 0 | F11: =-IF(F$6<Premissas!$B$24,E8*(1-Premissas!$B$25)/Premissas!$B$24,F9) -> 0 | G11: =-IF(G$6<Premissas!$B$24,E8*(1-Premissas!$B$25)/Premissas!$B$24,G9) -> 0 | H11: =-IF(H$6<Premissas!$B$24,E8*(1-Premissas!$B$25)/Premissas!$B$24,H9) -> 0 | I11: =-IF(I$6<Premissas!$B$24,E8*(1-Premissas!$B$25)/Premissas!$B$24,I9) -> 0 | J11: =-IF(J$6<Premissas!$B$24,E8*(1-Premissas!$B$25)/Premissas!$B$24,J9) -> 0 | K11: =-IF(K$6<Premissas!$B$24,E8*(1-Premissas!$B$25)/Premissas!$B$24,K9) -> 0 | L11: =-IF(L$6<Premissas!$B$24,E8*(1-Premissas!$B$25)/Premissas!$B$24,L9) -> 0 | M11: =-IF(M$6<Premissas!$B$24,E8*(1-Premissas!$B$25)/Premissas!$B$24,M9) -> 0 | N11: =-IF(N$6<Premissas!$B$24,E8*(1-Premissas!$B$25)/Premissas!$B$24,N9) -> 0 | O11: =-IF(O$6<Premissas!$B$24,E8*(1-Premissas!$B$25)/Premissas!$B$24,O9) -> 0
B12: Benefício fiscal dos juros | C12: 0 | D12: 0 | E12: 0 | F12: =MIN(-F10,MAX(0,Projecao!F186))*Premissas!$B$11 -> 0 | G12: =MIN(-G10,MAX(0,Projecao!G186))*Premissas!$B$11 -> 0 | H12: =MIN(-H10,MAX(0,Projecao!H186))*Premissas!$B$11 -> 0 | I12: =MIN(-I10,MAX(0,Projecao!I186))*Premissas!$B$11 -> 0 | J12: =MIN(-J10,MAX(0,Projecao!J186))*Premissas!$B$11 -> 0 | K12: =MIN(-K10,MAX(0,Projecao!K186))*Premissas!$B$11 -> 0 | L12: =MIN(-L10,MAX(0,Projecao!L186))*Premissas!$B$11 -> 0 | M12: =MIN(-M10,MAX(0,Projecao!M186))*Premissas!$B$11 -> 0 | ... O12: =MIN(-O10,MAX(0,Projecao!O186))*Premissas!$B$11 -> 0
B13: FLUXO DO ACIONISTA | C13: =C7+C8+C10+C11+C12 -> 0 | D13: =D7+D8+D10+D11+D12 -> 0 | E13: =E7+E8+E10+E11+E12 -> -21400000 | F13: =F7+F8+F10+F11+F12 -> 593050.02 | G13: =G7+G8+G10+G11+G12 -> 1158531.4 | H13: =H7+H8+H10+H11+H12 -> 683268.89 | I13: =I7+I8+I10+I11+I12 -> 1162338.2 | J13: =J7+J8+J10+J11+J12 -> 37987.597 | ... O13: =O7+O8+O10+O11+O12 -> 10425384
B14: DSCR (EBITDA − impostos) / serviço da dívida (sem balloon) | C14: 0 | D14: 0 | E14: 0 | F14: =IF(F9=0,0,(Projecao!F183+Projecao!F187)/(-F10+E8*(1-Premissas!$B$25)/Premissas!$B$24)) -> 0 | G14: =IF(G9=0,0,(Projecao!G183+Projecao!G187)/(-G10+E8*(1-Premissas!$B$25)/Premissas!$B$24)) -> 0 | H14: =IF(H9=0,0,(Projecao!H183+Projecao!H187)/(-H10+E8*(1-Premissas!$B$25)/Premissas!$B$24)) -> 0 | I14: =IF(I9=0,0,(Projecao!I183+Projecao!I187)/(-I10+E8*(1-Premissas!$B$25)/Premissas!$B$24)) -> 0 | J14: =IF(J9=0,0,(Projecao!J183+Projecao!J187)/(-J10+E8*(1-Premissas!$B$25)/Premissas!$B$24)) -> 0 | K14: =IF(K9=0,0,(Projecao!K183+Projecao!K187)/(-K10+E8*(1-Premissas!$B$25)/Premissas!$B$24)) -> 0 | L14: =IF(L9=0,0,(Projecao!L183+Projecao!L187)/(-L10+E8*(1-Premissas!$B$25)/Premissas!$B$24)) -> 0 | M14: =IF(M9=0,0,(Projecao!M183+Projecao!M187)/(-M10+E8*(1-Premissas!$B$25)/Premissas!$B$24)) -> 0 | N14: =IF(N9=0,0,(Projecao!N183+Projecao!N187)/(-N10+E8*(1-Premissas!$B$25)/Premissas!$B$24)) -> 0 | O14: =IF(O9=0,0,(Projecao!O183+Projecao!O187)/(-O10+E8*(1-Premissas!$B$25)/Premissas!$B$24)) -> 0
B15: Equity investido (pico) | C15: =-SUM(C13:E13) -> 21400000
B16: TIR do acionista | C16: =IFERROR(IRR(C13:O13,0.05),IFERROR(IRR(C13:O13,-0.1),IF(SUM(C13:O13)<0,"negativa","n/d"))) -> -0.026968782
B17: DSCR mínimo (anos 1–10) | C17: n/a
B18: Serviço da dívida ano 2 (juros + amortização) | C18: =-(G10+G11) -> 0
B19: Pior FCL do acionista em operação (anos 1–9) | C19: =MIN(F13:N13) -> 37987.597
B22: C · 36 cab/72 pax · USADO — 50% equity / 50% dívida
B23: LTV (dívida / CAPEX) | C23: 0.5
B24: Ano | C24: -2 | D24: -1 | E24: 0 | F24: 1 | G24: 2 | H24: 3 | I24: 4 | J24: 5 | K24: 6 | L24: 7 | M24: 8 | N24: 9 | O24: 10
B25: FCL desalavancado (link Projecao) | C25: =Projecao!C192 -> 0 | D25: =Projecao!D192 -> 0 | E25: =Projecao!E192 -> -21400000 | F25: =Projecao!F192 -> 593050.02 | G25: =Projecao!G192 -> 1158531.4 | H25: =Projecao!H192 -> 683268.89 | I25: =Projecao!I192 -> 1162338.2 | J25: =Projecao!J192 -> 37987.597 | ... O25: =Projecao!O192 -> 10425384
B26: Captação da dívida | C26: 0 | D26: 0 | E26: =Projecao!$C$205*$C$23 -> 10700000 | F26: 0 | G26: 0 | H26: 0 | I26: 0 | J26: 0 | K26: 0 | L26: 0 | M26: 0 | N26: 0 | O26: 0
B27: Saldo inicial da dívida | C27: 0 | D27: 0 | E27: 0 | F27: =E26 -> 10700000 | G27: =F27-F29 -> 11449000 | H27: =G27-G29 -> 12198000 | I27: =H27-H29 -> 12947000 | J27: =I27-I29 -> 13696000 | K27: =J27-J29 -> 14445000 | L27: =K27-K29 -> 15194000 | M27: =L27-L29 -> 15943000 | N27: =M27-M29 -> 16692000 | O27: =N27-N29 -> 17441000
B28: Juros | C28: =-C27*Premissas!$B$23 -> 0 | D28: =-D27*Premissas!$B$23 -> 0 | E28: =-E27*Premissas!$B$23 -> 0 | F28: =-F27*Premissas!$B$23 -> -642000 | G28: =-G27*Premissas!$B$23 -> -686940 | H28: =-H27*Premissas!$B$23 -> -731880 | I28: =-I27*Premissas!$B$23 -> -776820 | J28: =-J27*Premissas!$B$23 -> -821760 | ... O28: =-O27*Premissas!$B$23 -> -1046460
B29: Amortização (inclui balloon no ano 10) | C29: 0 | D29: 0 | E29: 0 | F29: =-IF(F$24<Premissas!$B$24,E26*(1-Premissas!$B$25)/Premissas!$B$24,F27) -> -749000 | G29: =-IF(G$24<Premissas!$B$24,E26*(1-Premissas!$B$25)/Premissas!$B$24,G27) -> -749000 | H29: =-IF(H$24<Premissas!$B$24,E26*(1-Premissas!$B$25)/Premissas!$B$24,H27) -> -749000 | I29: =-IF(I$24<Premissas!$B$24,E26*(1-Premissas!$B$25)/Premissas!$B$24,I27) -> -749000 | J29: =-IF(J$24<Premissas!$B$24,E26*(1-Premissas!$B$25)/Premissas!$B$24,J27) -> -749000 | K29: =-IF(K$24<Premissas!$B$24,E26*(1-Premissas!$B$25)/Premissas!$B$24,K27) -> -749000 | L29: =-IF(L$24<Premissas!$B$24,E26*(1-Premissas!$B$25)/Premissas!$B$24,L27) -> -749000 | M29: =-IF(M$24<Premissas!$B$24,E26*(1-Premissas!$B$25)/Premissas!$B$24,M27) -> -749000 | N29: =-IF(N$24<Premissas!$B$24,E26*(1-Premissas!$B$25)/Premissas!$B$24,N27) -> -749000 | O29: =-IF(O$24<Premissas!$B$24,E26*(1-Premissas!$B$25)/Premissas!$B$24,O27) -> -17441000
B30: Benefício fiscal dos juros | C30: 0 | D30: 0 | E30: 0 | F30: =MIN(-F28,MAX(0,Projecao!F186))*Premissas!$B$11 -> 0 | G30: =MIN(-G28,MAX(0,Projecao!G186))*Premissas!$B$11 -> 159156.76 | H30: =MIN(-H28,MAX(0,Projecao!H186))*Premissas!$B$11 -> 163666.98 | I30: =MIN(-I28,MAX(0,Projecao!I186))*Premissas!$B$11 -> 168033.04 | J30: =MIN(-J28,MAX(0,Projecao!J186))*Premissas!$B$11 -> 172243.64 | K30: =MIN(-K28,MAX(0,Projecao!K186))*Premissas!$B$11 -> 176286.94 | L30: =MIN(-L28,MAX(0,Projecao!L186))*Premissas!$B$11 -> 180150.59 | M30: =MIN(-M28,MAX(0,Projecao!M186))*Premissas!$B$11 -> 183821.68 | ... O30: =MIN(-O28,MAX(0,Projecao!O186))*Premissas!$B$11 -> 190531.6
B31: FLUXO DO ACIONISTA | C31: =C25+C26+C28+C29+C30 -> 0 | D31: =D25+D26+D28+D29+D30 -> 0 | E31: =E25+E26+E28+E29+E30 -> -10700000 | F31: =F25+F26+F28+F29+F30 -> -797949.98 | G31: =G25+G26+G28+G29+G30 -> -118251.87 | H31: =H25+H26+H28+H29+H30 -> -633944.13 | I31: =I25+I26+I28+I29+I30 -> -195448.75 | J31: =J25+J26+J28+J29+J30 -> -1360528.8 | ... O31: =O25+O26+O28+O29+O30 -> -7871544.9
B32: DSCR (EBITDA − impostos) / serviço da dívida (sem balloon) | C32: 0 | D32: 0 | E32: 0 | F32: =IF(F27=0,0,(Projecao!F183+Projecao!F187)/(-F28+E26*(1-Premissas!$B$25)/Premissas!$B$24)) -> 0.58019412 | G32: =IF(G27=0,0,(Projecao!G183+Projecao!G187)/(-G28+E26*(1-Premissas!$B$25)/Premissas!$B$24)) -> 0.96031266 | H32: =IF(H27=0,0,(Projecao!H183+Projecao!H187)/(-H28+E26*(1-Premissas!$B$25)/Premissas!$B$24)) -> 0.93708234 | I32: =IF(I27=0,0,(Projecao!I183+Projecao!I187)/(-I28+E26*(1-Premissas!$B$25)/Premissas!$B$24)) -> 0.91503702 | J32: =IF(J27=0,0,(Projecao!J183+Projecao!J187)/(-J28+E26*(1-Premissas!$B$25)/Premissas!$B$24)) -> 0.89406102 | K32: =IF(K27=0,0,(Projecao!K183+Projecao!K187)/(-K28+E26*(1-Premissas!$B$25)/Premissas!$B$24)) -> 0.87405091 | L32: =IF(L27=0,0,(Projecao!L183+Projecao!L187)/(-L28+E26*(1-Premissas!$B$25)/Premissas!$B$24)) -> 0.85491382 | M32: =IF(M27=0,0,(Projecao!M183+Projecao!M187)/(-M28+E26*(1-Premissas!$B$25)/Premissas!$B$24)) -> 0.83656604 | N32: =IF(N27=0,0,(Projecao!N183+Projecao!N187)/(-N28+E26*(1-Premissas!$B$25)/Premissas!$B$24)) -> 0.81893183 | O32: =IF(O27=0,0,(Projecao!O183+Projecao!O187)/(-O28+E26*(1-Premissas!$B$25)/Premissas!$B$24)) -> 0.80194238
B33: Equity investido (pico) | C33: =-SUM(C31:E31) -> 10700000
B34: TIR do acionista | C34: =IFERROR(IRR(C31:O31,0.05),IFERROR(IRR(C31:O31,-0.1),IF(SUM(C31:O31)<0,"negativa","n/d"))) -> negativa
B35: DSCR mínimo (anos 1–10) | C35: =MIN(F32:N32) -> 0.58019412
B36: Serviço da dívida ano 2 (juros + amortização) | C36: =-(G28+G29) -> 1435940
B37: Pior FCL do acionista em operação (anos 1–9) | C37: =MIN(F31:N31) -> -1360528.8
B40: C · 36 cab/72 pax · USADO — 30% equity / 70% dívida
B41: LTV (dívida / CAPEX) | C41: 0.7
B42: Ano | C42: -2 | D42: -1 | E42: 0 | F42: 1 | G42: 2 | H42: 3 | I42: 4 | J42: 5 | K42: 6 | L42: 7 | M42: 8 | N42: 9 | O42: 10
B43: FCL desalavancado (link Projecao) | C43: =Projecao!C192 -> 0 | D43: =Projecao!D192 -> 0 | E43: =Projecao!E192 -> -21400000 | F43: =Projecao!F192 -> 593050.02 | G43: =Projecao!G192 -> 1158531.4 | H43: =Projecao!H192 -> 683268.89 | I43: =Projecao!I192 -> 1162338.2 | J43: =Projecao!J192 -> 37987.597 | ... O43: =Projecao!O192 -> 10425384
B44: Captação da dívida | C44: 0 | D44: 0 | E44: =Projecao!$C$205*$C$41 -> 14980000 | F44: 0 | G44: 0 | H44: 0 | I44: 0 | J44: 0 | K44: 0 | L44: 0 | M44: 0 | N44: 0 | O44: 0
B45: Saldo inicial da dívida | C45: 0 | D45: 0 | E45: 0 | F45: =E44 -> 14980000 | G45: =F45-F47 -> 16028600 | H45: =G45-G47 -> 17077200 | I45: =H45-H47 -> 18125800 | J45: =I45-I47 -> 19174400 | K45: =J45-J47 -> 20223000 | L45: =K45-K47 -> 21271600 | M45: =L45-L47 -> 22320200 | N45: =M45-M47 -> 23368800 | O45: =N45-N47 -> 24417400
B46: Juros | C46: =-C45*Premissas!$B$23 -> 0 | D46: =-D45*Premissas!$B$23 -> 0 | E46: =-E45*Premissas!$B$23 -> 0 | F46: =-F45*Premissas!$B$23 -> -898800 | G46: =-G45*Premissas!$B$23 -> -961716 | H46: =-H45*Premissas!$B$23 -> -1024632 | I46: =-I45*Premissas!$B$23 -> -1087548 | J46: =-J45*Premissas!$B$23 -> -1150464 | ... O46: =-O45*Premissas!$B$23 -> -1465044
B47: Amortização (inclui balloon no ano 10) | C47: 0 | D47: 0 | E47: 0 | F47: =-IF(F$42<Premissas!$B$24,E44*(1-Premissas!$B$25)/Premissas!$B$24,F45) -> -1048600 | G47: =-IF(G$42<Premissas!$B$24,E44*(1-Premissas!$B$25)/Premissas!$B$24,G45) -> -1048600 | H47: =-IF(H$42<Premissas!$B$24,E44*(1-Premissas!$B$25)/Premissas!$B$24,H45) -> -1048600 | I47: =-IF(I$42<Premissas!$B$24,E44*(1-Premissas!$B$25)/Premissas!$B$24,I45) -> -1048600 | J47: =-IF(J$42<Premissas!$B$24,E44*(1-Premissas!$B$25)/Premissas!$B$24,J45) -> -1048600 | K47: =-IF(K$42<Premissas!$B$24,E44*(1-Premissas!$B$25)/Premissas!$B$24,K45) -> -1048600 | L47: =-IF(L$42<Premissas!$B$24,E44*(1-Premissas!$B$25)/Premissas!$B$24,L45) -> -1048600 | M47: =-IF(M$42<Premissas!$B$24,E44*(1-Premissas!$B$25)/Premissas!$B$24,M45) -> -1048600 | N47: =-IF(N$42<Premissas!$B$24,E44*(1-Premissas!$B$25)/Premissas!$B$24,N45) -> -1048600 | O47: =-IF(O$42<Premissas!$B$24,E44*(1-Premissas!$B$25)/Premissas!$B$24,O45) -> -24417400
B48: Benefício fiscal dos juros | C48: 0 | D48: 0 | E48: 0 | F48: =MIN(-F46,MAX(0,Projecao!F186))*Premissas!$B$11 -> 0 | G48: =MIN(-G46,MAX(0,Projecao!G186))*Premissas!$B$11 -> 159156.76 | H48: =MIN(-H46,MAX(0,Projecao!H186))*Premissas!$B$11 -> 163666.98 | I48: =MIN(-I46,MAX(0,Projecao!I186))*Premissas!$B$11 -> 168033.04 | J48: =MIN(-J46,MAX(0,Projecao!J186))*Premissas!$B$11 -> 172243.64 | K48: =MIN(-K46,MAX(0,Projecao!K186))*Premissas!$B$11 -> 176286.94 | L48: =MIN(-L46,MAX(0,Projecao!L186))*Premissas!$B$11 -> 180150.59 | M48: =MIN(-M46,MAX(0,Projecao!M186))*Premissas!$B$11 -> 183821.68 | ... O48: =MIN(-O46,MAX(0,Projecao!O186))*Premissas!$B$11 -> 190531.6
B49: FLUXO DO ACIONISTA | C49: =C43+C44+C46+C47+C48 -> 0 | D49: =D43+D44+D46+D47+D48 -> 0 | E49: =E43+E44+E46+E47+E48 -> -6420000 | F49: =F43+F44+F46+F47+F48 -> -1354350 | G49: =G43+G44+G46+G47+G48 -> -692627.87 | H49: =H43+H44+H46+H47+H48 -> -1226296.1 | I49: =I43+I44+I46+I47+I48 -> -805776.75 | J49: =J43+J44+J46+J47+J48 -> -1988832.8 | ... O49: =O43+O44+O46+O47+O48 -> -15266529
B50: DSCR (EBITDA − impostos) / serviço da dívida (sem balloon) | C50: 0 | D50: 0 | E50: 0 | F50: =IF(F45=0,0,(Projecao!F183+Projecao!F187)/(-F46+E44*(1-Premissas!$B$25)/Premissas!$B$24)) -> 0.41442437 | G50: =IF(G45=0,0,(Projecao!G183+Projecao!G187)/(-G46+E44*(1-Premissas!$B$25)/Premissas!$B$24)) -> 0.68593762 | H50: =IF(H45=0,0,(Projecao!H183+Projecao!H187)/(-H46+E44*(1-Premissas!$B$25)/Premissas!$B$24)) -> 0.66934453 | I50: =IF(I45=0,0,(Projecao!I183+Projecao!I187)/(-I46+E44*(1-Premissas!$B$25)/Premissas!$B$24)) -> 0.65359787 | J50: =IF(J45=0,0,(Projecao!J183+Projecao!J187)/(-J46+E44*(1-Premissas!$B$25)/Premissas!$B$24)) -> 0.63861502 | K50: =IF(K45=0,0,(Projecao!K183+Projecao!K187)/(-K46+E44*(1-Premissas!$B$25)/Premissas!$B$24)) -> 0.62432208 | L50: =IF(L45=0,0,(Projecao!L183+Projecao!L187)/(-L46+E44*(1-Premissas!$B$25)/Premissas!$B$24)) -> 0.61065273 | M50: =IF(M45=0,0,(Projecao!M183+Projecao!M187)/(-M46+E44*(1-Premissas!$B$25)/Premissas!$B$24)) -> 0.59754717 | N50: =IF(N45=0,0,(Projecao!N183+Projecao!N187)/(-N46+E44*(1-Premissas!$B$25)/Premissas!$B$24)) -> 0.58495131 | O50: =IF(O45=0,0,(Projecao!O183+Projecao!O187)/(-O46+E44*(1-Premissas!$B$25)/Premissas!$B$24)) -> 0.57281599
B51: Equity investido (pico) | C51: =-SUM(C49:E49) -> 6420000
B52: TIR do acionista | C52: =IFERROR(IRR(C49:O49,0.05),IFERROR(IRR(C49:O49,-0.1),IF(SUM(C49:O49)<0,"negativa","n/d"))) -> negativa
B53: DSCR mínimo (anos 1–10) | C53: =MIN(F50:N50) -> 0.41442437
B54: Serviço da dívida ano 2 (juros + amortização) | C54: =-(G46+G47) -> 2010316
B55: Pior FCL do acionista em operação (anos 1–9) | C55: =MIN(F49:N49) -> -1988832.8
B58: C · 36 cab/72 pax · NOVO — 100% equity / 0% dívida
B59: LTV (dívida / CAPEX) | C59: 0
B60: Ano | C60: -2 | D60: -1 | E60: 0 | F60: 1 | G60: 2 | H60: 3 | I60: 4 | J60: 5 | K60: 6 | L60: 7 | M60: 8 | N60: 9 | O60: 10
B61: FCL desalavancado (link Projecao) | C61: =Projecao!C69 -> -9541800 | D61: =Projecao!D69 -> -9541800 | E61: =Projecao!E69 -> -28625400 | F61: =Projecao!F69 -> 1217383 | G61: =Projecao!G69 -> 2005838 | H61: =Projecao!H69 -> 1648770.5 | I61: =Projecao!I69 -> 2034159.6 | J61: =Projecao!J69 -> 1147633.1 | ... O61: =Projecao!O69 -> 27048939
B62: Captação da dívida | C62: 0 | D62: 0 | E62: =Projecao!$C$82*$C$59 -> 0 | F62: 0 | G62: 0 | H62: 0 | I62: 0 | J62: 0 | K62: 0 | L62: 0 | M62: 0 | N62: 0 | O62: 0
B63: Saldo inicial da dívida | C63: 0 | D63: 0 | E63: 0 | F63: =E62 -> 0 | G63: =F63-F65 -> 0 | H63: =G63-G65 -> 0 | I63: =H63-H65 -> 0 | J63: =I63-I65 -> 0 | K63: =J63-J65 -> 0 | L63: =K63-K65 -> 0 | M63: =L63-L65 -> 0 | N63: =M63-M65 -> 0 | O63: =N63-N65 -> 0
B64: Juros | C64: =-C63*Premissas!$B$23 -> 0 | D64: =-D63*Premissas!$B$23 -> 0 | E64: =-E63*Premissas!$B$23 -> 0 | F64: =-F63*Premissas!$B$23 -> 0 | G64: =-G63*Premissas!$B$23 -> 0 | H64: =-H63*Premissas!$B$23 -> 0 | I64: =-I63*Premissas!$B$23 -> 0 | J64: =-J63*Premissas!$B$23 -> 0 | ... O64: =-O63*Premissas!$B$23 -> 0
B65: Amortização (inclui balloon no ano 10) | C65: 0 | D65: 0 | E65: 0 | F65: =-IF(F$60<Premissas!$B$24,E62*(1-Premissas!$B$25)/Premissas!$B$24,F63) -> 0 | G65: =-IF(G$60<Premissas!$B$24,E62*(1-Premissas!$B$25)/Premissas!$B$24,G63) -> 0 | H65: =-IF(H$60<Premissas!$B$24,E62*(1-Premissas!$B$25)/Premissas!$B$24,H63) -> 0 | I65: =-IF(I$60<Premissas!$B$24,E62*(1-Premissas!$B$25)/Premissas!$B$24,I63) -> 0 | J65: =-IF(J$60<Premissas!$B$24,E62*(1-Premissas!$B$25)/Premissas!$B$24,J63) -> 0 | K65: =-IF(K$60<Premissas!$B$24,E62*(1-Premissas!$B$25)/Premissas!$B$24,K63) -> 0 | L65: =-IF(L$60<Premissas!$B$24,E62*(1-Premissas!$B$25)/Premissas!$B$24,L63) -> 0 | M65: =-IF(M$60<Premissas!$B$24,E62*(1-Premissas!$B$25)/Premissas!$B$24,M63) -> 0 | N65: =-IF(N$60<Premissas!$B$24,E62*(1-Premissas!$B$25)/Premissas!$B$24,N63) -> 0 | O65: =-IF(O$60<Premissas!$B$24,E62*(1-Premissas!$B$25)/Premissas!$B$24,O63) -> 0
B66: Benefício fiscal dos juros | C66: 0 | D66: 0 | E66: 0 | F66: =MIN(-F64,MAX(0,Projecao!F63))*Premissas!$B$11 -> 0 | G66: =MIN(-G64,MAX(0,Projecao!G63))*Premissas!$B$11 -> 0 | H66: =MIN(-H64,MAX(0,Projecao!H63))*Premissas!$B$11 -> 0 | I66: =MIN(-I64,MAX(0,Projecao!I63))*Premissas!$B$11 -> 0 | J66: =MIN(-J64,MAX(0,Projecao!J63))*Premissas!$B$11 -> 0 | K66: =MIN(-K64,MAX(0,Projecao!K63))*Premissas!$B$11 -> 0 | L66: =MIN(-L64,MAX(0,Projecao!L63))*Premissas!$B$11 -> 0 | M66: =MIN(-M64,MAX(0,Projecao!M63))*Premissas!$B$11 -> 0 | ... O66: =MIN(-O64,MAX(0,Projecao!O63))*Premissas!$B$11 -> 0
B67: FLUXO DO ACIONISTA | C67: =C61+C62+C64+C65+C66 -> -9541800 | D67: =D61+D62+D64+D65+D66 -> -9541800 | E67: =E61+E62+E64+E65+E66 -> -28625400 | F67: =F61+F62+F64+F65+F66 -> 1217383 | G67: =G61+G62+G64+G65+G66 -> 2005838 | H67: =H61+H62+H64+H65+H66 -> 1648770.5 | I67: =I61+I62+I64+I65+I66 -> 2034159.6 | J67: =J61+J62+J64+J65+J66 -> 1147633.1 | ... O67: =O61+O62+O64+O65+O66 -> 27048939
B68: DSCR (EBITDA − impostos) / serviço da dívida (sem balloon) | C68: 0 | D68: 0 | E68: 0 | F68: =IF(F63=0,0,(Projecao!F60+Projecao!F64)/(-F64+E62*(1-Premissas!$B$25)/Premissas!$B$24)) -> 0 | G68: =IF(G63=0,0,(Projecao!G60+Projecao!G64)/(-G64+E62*(1-Premissas!$B$25)/Premissas!$B$24)) -> 0 | H68: =IF(H63=0,0,(Projecao!H60+Projecao!H64)/(-H64+E62*(1-Premissas!$B$25)/Premissas!$B$24)) -> 0 | I68: =IF(I63=0,0,(Projecao!I60+Projecao!I64)/(-I64+E62*(1-Premissas!$B$25)/Premissas!$B$24)) -> 0 | J68: =IF(J63=0,0,(Projecao!J60+Projecao!J64)/(-J64+E62*(1-Premissas!$B$25)/Premissas!$B$24)) -> 0 | K68: =IF(K63=0,0,(Projecao!K60+Projecao!K64)/(-K64+E62*(1-Premissas!$B$25)/Premissas!$B$24)) -> 0 | L68: =IF(L63=0,0,(Projecao!L60+Projecao!L64)/(-L64+E62*(1-Premissas!$B$25)/Premissas!$B$24)) -> 0 | M68: =IF(M63=0,0,(Projecao!M60+Projecao!M64)/(-M64+E62*(1-Premissas!$B$25)/Premissas!$B$24)) -> 0 | N68: =IF(N63=0,0,(Projecao!N60+Projecao!N64)/(-N64+E62*(1-Premissas!$B$25)/Premissas!$B$24)) -> 0 | O68: =IF(O63=0,0,(Projecao!O60+Projecao!O64)/(-O64+E62*(1-Premissas!$B$25)/Premissas!$B$24)) -> 0
B69: Equity investido (pico) | C69: =-SUM(C67:E67) -> 47709000
B70: TIR do acionista | C70: =IFERROR(IRR(C67:O67,0.05),IFERROR(IRR(C67:O67,-0.1),IF(SUM(C67:O67)<0,"negativa","n/d"))) -> -0.017419323
B71: DSCR mínimo (anos 1–10) | C71: n/a
B72: Serviço da dívida ano 2 (juros + amortização) | C72: =-(G64+G65) -> 0
B73: Pior FCL do acionista em operação (anos 1–9) | C73: =MIN(F67:N67) -> -150606.21
B76: C · 36 cab/72 pax · NOVO — 50% equity / 50% dívida
B77: LTV (dívida / CAPEX) | C77: 0.5
B78: Ano | C78: -2 | D78: -1 | E78: 0 | F78: 1 | G78: 2 | H78: 3 | I78: 4 | J78: 5 | K78: 6 | L78: 7 | M78: 8 | N78: 9 | O78: 10
B79: FCL desalavancado (link Projecao) | C79: =Projecao!C69 -> -9541800 | D79: =Projecao!D69 -> -9541800 | E79: =Projecao!E69 -> -28625400 | F79: =Projecao!F69 -> 1217383 | G79: =Projecao!G69 -> 2005838 | H79: =Projecao!H69 -> 1648770.5 | I79: =Projecao!I69 -> 2034159.6 | J79: =Projecao!J69 -> 1147633.1 | ... O79: =Projecao!O69 -> 27048939
B80: Captação da dívida | C80: 0 | D80: 0 | E80: =Projecao!$C$82*$C$77 -> 23854500 | F80: 0 | G80: 0 | H80: 0 | I80: 0 | J80: 0 | K80: 0 | L80: 0 | M80: 0 | N80: 0 | O80: 0
B81: Saldo inicial da dívida | C81: 0 | D81: 0 | E81: 0 | F81: =E80 -> 23854500 | G81: =F81-F83 -> 25524315 | H81: =G81-G83 -> 27194130 | I81: =H81-H83 -> 28863945 | J81: =I81-I83 -> 30533760 | K81: =J81-J83 -> 32203575 | L81: =K81-K83 -> 33873390 | M81: =L81-L83 -> 35543205 | N81: =M81-M83 -> 37213020 | O81: =N81-N83 -> 38882835
B82: Juros | C82: =-C81*Premissas!$B$23 -> 0 | D82: =-D81*Premissas!$B$23 -> 0 | E82: =-E81*Premissas!$B$23 -> 0 | F82: =-F81*Premissas!$B$23 -> -1431270 | G82: =-G81*Premissas!$B$23 -> -1531458.9 | H82: =-H81*Premissas!$B$23 -> -1631647.8 | I82: =-I81*Premissas!$B$23 -> -1731836.7 | J82: =-J81*Premissas!$B$23 -> -1832025.6 | ... O82: =-O81*Premissas!$B$23 -> -2332970.1
B83: Amortização (inclui balloon no ano 10) | C83: 0 | D83: 0 | E83: 0 | F83: =-IF(F$78<Premissas!$B$24,E80*(1-Premissas!$B$25)/Premissas!$B$24,F81) -> -1669815 | G83: =-IF(G$78<Premissas!$B$24,E80*(1-Premissas!$B$25)/Premissas!$B$24,G81) -> -1669815 | H83: =-IF(H$78<Premissas!$B$24,E80*(1-Premissas!$B$25)/Premissas!$B$24,H81) -> -1669815 | I83: =-IF(I$78<Premissas!$B$24,E80*(1-Premissas!$B$25)/Premissas!$B$24,I81) -> -1669815 | J83: =-IF(J$78<Premissas!$B$24,E80*(1-Premissas!$B$25)/Premissas!$B$24,J81) -> -1669815 | K83: =-IF(K$78<Premissas!$B$24,E80*(1-Premissas!$B$25)/Premissas!$B$24,K81) -> -1669815 | L83: =-IF(L$78<Premissas!$B$24,E80*(1-Premissas!$B$25)/Premissas!$B$24,L81) -> -1669815 | M83: =-IF(M$78<Premissas!$B$24,E80*(1-Premissas!$B$25)/Premissas!$B$24,M81) -> -1669815 | N83: =-IF(N$78<Premissas!$B$24,E80*(1-Premissas!$B$25)/Premissas!$B$24,N81) -> -1669815 | O83: =-IF(O$78<Premissas!$B$24,E80*(1-Premissas!$B$25)/Premissas!$B$24,O81) -> -38882835
B84: Benefício fiscal dos juros | C84: 0 | D84: 0 | E84: 0 | F84: =MIN(-F82,MAX(0,Projecao!F63))*Premissas!$B$11 -> 0 | G84: =MIN(-G82,MAX(0,Projecao!G63))*Premissas!$B$11 -> 53902.569 | H84: =MIN(-H82,MAX(0,Projecao!H63))*Premissas!$B$11 -> 65039.357 | I84: =MIN(-I82,MAX(0,Projecao!I63))*Premissas!$B$11 -> 76200.781 | J84: =MIN(-J82,MAX(0,Projecao!J63))*Premissas!$B$11 -> 87379.842 | K84: =MIN(-K82,MAX(0,Projecao!K63))*Premissas!$B$11 -> 98569.141 | L84: =MIN(-L82,MAX(0,Projecao!L63))*Premissas!$B$11 -> 109760.86 | M84: =MIN(-M82,MAX(0,Projecao!M63))*Premissas!$B$11 -> 120946.73 | ... O84: =MIN(-O82,MAX(0,Projecao!O63))*Premissas!$B$11 -> 143265.6
B85: FLUXO DO ACIONISTA | C85: =C79+C80+C82+C83+C84 -> -9541800 | D85: =D79+D80+D82+D83+D84 -> -9541800 | E85: =E79+E80+E82+E83+E84 -> -4770900 | F85: =F79+F80+F82+F83+F84 -> -1883702 | G85: =G79+G80+G82+G83+G84 -> -1141533.3 | H85: =H79+H80+H82+H83+H84 -> -1587653 | I85: =I79+I80+I82+I83+I84 -> -1291291.3 | J85: =J79+J80+J82+J83+J84 -> -2266827.6 | ... O85: =O79+O80+O82+O83+O84 -> -14023601
B86: DSCR (EBITDA − impostos) / serviço da dívida (sem balloon) | C86: 0 | D86: 0 | E86: 0 | F86: =IF(F81=0,0,(Projecao!F60+Projecao!F64)/(-F82+E80*(1-Premissas!$B$25)/Premissas!$B$24)) -> 0.46948988 | G86: =IF(G81=0,0,(Projecao!G60+Projecao!G64)/(-G82+E80*(1-Premissas!$B$25)/Premissas!$B$24)) -> 0.70332607 | H86: =IF(H81=0,0,(Projecao!H60+Projecao!H64)/(-H82+E80*(1-Premissas!$B$25)/Premissas!$B$24)) -> 0.68853051 | I86: =IF(I81=0,0,(Projecao!I60+Projecao!I64)/(-I82+E80*(1-Premissas!$B$25)/Premissas!$B$24)) -> 0.67462056 | J86: =IF(J81=0,0,(Projecao!J60+Projecao!J64)/(-J82+E80*(1-Premissas!$B$25)/Premissas!$B$24)) -> 0.66151632 | K86: =IF(K81=0,0,(Projecao!K60+Projecao!K64)/(-K82+E80*(1-Premissas!$B$25)/Premissas!$B$24)) -> 0.64914657 | L86: =IF(L81=0,0,(Projecao!L60+Projecao!L64)/(-L82+E80*(1-Premissas!$B$25)/Premissas!$B$24)) -> 0.63744759 | M86: =IF(M81=0,0,(Projecao!M60+Projecao!M64)/(-M82+E80*(1-Premissas!$B$25)/Premissas!$B$24)) -> 0.62636213 | N86: =IF(N81=0,0,(Projecao!N60+Projecao!N64)/(-N82+E80*(1-Premissas!$B$25)/Premissas!$B$24)) -> 0.61583861 | O86: =IF(O81=0,0,(Projecao!O60+Projecao!O64)/(-O82+E80*(1-Premissas!$B$25)/Premissas!$B$24)) -> 0.60583038
B87: Equity investido (pico) | C87: =-SUM(C85:E85) -> 23854500
B88: TIR do acionista | C88: =IFERROR(IRR(C85:O85,0.05),IFERROR(IRR(C85:O85,-0.1),IF(SUM(C85:O85)<0,"negativa","n/d"))) -> negativa
B89: DSCR mínimo (anos 1–10) | C89: =MIN(F86:N86) -> 0.46948988
B90: Serviço da dívida ano 2 (juros + amortização) | C90: =-(G82+G83) -> 3201273.9
B91: Pior FCL do acionista em operação (anos 1–9) | C91: =MIN(F85:N85) -> -3654066.6
B94: C · 36 cab/72 pax · NOVO — 30% equity / 70% dívida
B95: LTV (dívida / CAPEX) | C95: 0.7
B96: Ano | C96: -2 | D96: -1 | E96: 0 | F96: 1 | G96: 2 | H96: 3 | I96: 4 | J96: 5 | K96: 6 | L96: 7 | M96: 8 | N96: 9 | O96: 10
B97: FCL desalavancado (link Projecao) | C97: =Projecao!C69 -> -9541800 | D97: =Projecao!D69 -> -9541800 | E97: =Projecao!E69 -> -28625400 | F97: =Projecao!F69 -> 1217383 | G97: =Projecao!G69 -> 2005838 | H97: =Projecao!H69 -> 1648770.5 | I97: =Projecao!I69 -> 2034159.6 | J97: =Projecao!J69 -> 1147633.1 | ... O97: =Projecao!O69 -> 27048939
B98: Captação da dívida | C98: 0 | D98: 0 | E98: =Projecao!$C$82*$C$95 -> 33396300 | F98: 0 | G98: 0 | H98: 0 | I98: 0 | J98: 0 | K98: 0 | L98: 0 | M98: 0 | N98: 0 | O98: 0
B99: Saldo inicial da dívida | C99: 0 | D99: 0 | E99: 0 | F99: =E98 -> 33396300 | G99: =F99-F101 -> 35734041 | H99: =G99-G101 -> 38071782 | I99: =H99-H101 -> 40409523 | J99: =I99-I101 -> 42747264 | K99: =J99-J101 -> 45085005 | L99: =K99-K101 -> 47422746 | M99: =L99-L101 -> 49760487 | N99: =M99-M101 -> 52098228 | O99: =N99-N101 -> 54435969
B100: Juros | C100: =-C99*Premissas!$B$23 -> 0 | D100: =-D99*Premissas!$B$23 -> 0 | E100: =-E99*Premissas!$B$23 -> 0 | F100: =-F99*Premissas!$B$23 -> -2003778 | G100: =-G99*Premissas!$B$23 -> -2144042.5 | H100: =-H99*Premissas!$B$23 -> -2284306.9 | I100: =-I99*Premissas!$B$23 -> -2424571.4 | J100: =-J99*Premissas!$B$23 -> -2564835.8 | ... O100: =-O99*Premissas!$B$23 -> -3266158.1
B101: Amortização (inclui balloon no ano 10) | C101: 0 | D101: 0 | E101: 0 | F101: =-IF(F$96<Premissas!$B$24,E98*(1-Premissas!$B$25)/Premissas!$B$24,F99) -> -2337741 | G101: =-IF(G$96<Premissas!$B$24,E98*(1-Premissas!$B$25)/Premissas!$B$24,G99) -> -2337741 | H101: =-IF(H$96<Premissas!$B$24,E98*(1-Premissas!$B$25)/Premissas!$B$24,H99) -> -2337741 | I101: =-IF(I$96<Premissas!$B$24,E98*(1-Premissas!$B$25)/Premissas!$B$24,I99) -> -2337741 | J101: =-IF(J$96<Premissas!$B$24,E98*(1-Premissas!$B$25)/Premissas!$B$24,J99) -> -2337741 | K101: =-IF(K$96<Premissas!$B$24,E98*(1-Premissas!$B$25)/Premissas!$B$24,K99) -> -2337741 | L101: =-IF(L$96<Premissas!$B$24,E98*(1-Premissas!$B$25)/Premissas!$B$24,L99) -> -2337741 | M101: =-IF(M$96<Premissas!$B$24,E98*(1-Premissas!$B$25)/Premissas!$B$24,M99) -> -2337741 | N101: =-IF(N$96<Premissas!$B$24,E98*(1-Premissas!$B$25)/Premissas!$B$24,N99) -> -2337741 | O101: =-IF(O$96<Premissas!$B$24,E98*(1-Premissas!$B$25)/Premissas!$B$24,O99) -> -54435969
B102: Benefício fiscal dos juros | C102: 0 | D102: 0 | E102: 0 | F102: =MIN(-F100,MAX(0,Projecao!F63))*Premissas!$B$11 -> 0 | G102: =MIN(-G100,MAX(0,Projecao!G63))*Premissas!$B$11 -> 53902.569 | H102: =MIN(-H100,MAX(0,Projecao!H63))*Premissas!$B$11 -> 65039.357 | I102: =MIN(-I100,MAX(0,Projecao!I63))*Premissas!$B$11 -> 76200.781 | J102: =MIN(-J100,MAX(0,Projecao!J63))*Premissas!$B$11 -> 87379.842 | K102: =MIN(-K100,MAX(0,Projecao!K63))*Premissas!$B$11 -> 98569.141 | L102: =MIN(-L100,MAX(0,Projecao!L63))*Premissas!$B$11 -> 109760.86 | M102: =MIN(-M100,MAX(0,Projecao!M63))*Premissas!$B$11 -> 120946.73 | ... O102: =MIN(-O100,MAX(0,Projecao!O63))*Premissas!$B$11 -> 143265.6
B103: FLUXO DO ACIONISTA | C103: =C97+C98+C100+C101+C102 -> -9541800 | D103: =D97+D98+D100+D101+D102 -> -9541800 | E103: =E97+E98+E100+E101+E102 -> 4770900 | F103: =F97+F98+F100+F101+F102 -> -3124136 | G103: =G97+G98+G100+G101+G102 -> -2422042.8 | H103: =H97+H98+H100+H101+H102 -> -2908238.1 | I103: =I97+I98+I100+I101+I102 -> -2651952 | J103: =J97+J98+J100+J101+J102 -> -3667563.9 | ... O103: =O97+O98+O100+O101+O102 -> -30509923
B104: DSCR (EBITDA − impostos) / serviço da dívida (sem balloon) | C104: 0 | D104: 0 | E104: 0 | F104: =IF(F99=0,0,(Projecao!F60+Projecao!F64)/(-F100+E98*(1-Premissas!$B$25)/Premissas!$B$24)) -> 0.33534991 | G104: =IF(G99=0,0,(Projecao!G60+Projecao!G64)/(-G100+E98*(1-Premissas!$B$25)/Premissas!$B$24)) -> 0.50237577 | H104: =IF(H99=0,0,(Projecao!H60+Projecao!H64)/(-H100+E98*(1-Premissas!$B$25)/Premissas!$B$24)) -> 0.49180751 | I104: =IF(I99=0,0,(Projecao!I60+Projecao!I64)/(-I100+E98*(1-Premissas!$B$25)/Premissas!$B$24)) -> 0.48187183 | J104: =IF(J99=0,0,(Projecao!J60+Projecao!J64)/(-J100+E98*(1-Premissas!$B$25)/Premissas!$B$24)) -> 0.47251165 | K104: =IF(K99=0,0,(Projecao!K60+Projecao!K64)/(-K100+E98*(1-Premissas!$B$25)/Premissas!$B$24)) -> 0.46367612 | L104: =IF(L99=0,0,(Projecao!L60+Projecao!L64)/(-L100+E98*(1-Premissas!$B$25)/Premissas!$B$24)) -> 0.45531971 | M104: =IF(M99=0,0,(Projecao!M60+Projecao!M64)/(-M100+E98*(1-Premissas!$B$25)/Premissas!$B$24)) -> 0.44740152 | N104: =IF(N99=0,0,(Projecao!N60+Projecao!N64)/(-N100+E98*(1-Premissas!$B$25)/Premissas!$B$24)) -> 0.43988472 | O104: =IF(O99=0,0,(Projecao!O60+Projecao!O64)/(-O100+E98*(1-Premissas!$B$25)/Premissas!$B$24)) -> 0.43273599
B105: Equity investido (pico) | C105: =-SUM(C103:E103) -> 14312700
B106: TIR do acionista | C106: =IFERROR(IRR(C103:O103,0.05),IFERROR(IRR(C103:O103,-0.1),IF(SUM(C103:O103)<0,"negativa","n/d"))) -> negativa
B107: DSCR mínimo (anos 1–10) | C107: =MIN(F104:N104) -> 0.33534991
B108: Serviço da dívida ano 2 (juros + amortização) | C108: =-(G100+G101) -> 4481783.5
B109: Pior FCL do acionista em operação (anos 1–9) | C109: =MIN(F103:N103) -> -5094878.4
B112: B · 24 cab/48 pax · USADO — 100% equity / 0% dívida
B113: LTV (dívida / CAPEX) | C113: 0
...

Sheet Fontes
A1: Fontes principais (detalhe completo nos dossiês de pesquisa .md)
A3: Variety Voyager — especificações e custo €29M (2012) | B3: https://cruiseindustrynews.com/cruise-news/2012/06/variety-voyager-joins-preferred-hotels-a-resorts-collection ; https://www.cruisemapper.com/ships/Variety-Voyager-1344 ; https://www.superyachts.com/fleet/variety-voyager-9170/specs/
A4: Tarifas de charter Variety / mini-cruisers | B4: Ver dossiê research_charter.md (Goolets, 12knots, brokers de charter, Variety Cruises)
A5: Anúncios de navios usados | B5: Ver Vessel Market Scan (GRS/ShipSelector #1048634, #1064418, #1091239; Northrop & Johnson — Running on Waves; Apollo Duck)
A6: Preços de construção nova | B6: Silver Origin (cruisemapper), Coral Adventurer, Hondius (croatiaweek), Ultramarine (intellinews), World Explorer (tradewinds), NG Endurance (Lindblad 10-K)
A7: Salários de tripulação | B7: https://uksa.org/news-and-guides/superyacht-salary-guide/ ; https://www.yachtbuyer.com/en-us/advice/how-much-does-a-yacht-crew-cost
A8: Combustível MGO Pireu | B8: https://shipandbunker.com/prices/emea/medabs/gr-pir-piraeus
A9: Taxa de cruzeiro grega | B9: https://greekherald.com.au/?p=185728 ; https://eurofast.eu/greece-introduces-cruise-passenger-tax-to-address-overtourism/
A10: P&I / seguros | B10: https://www.hellenicshippingnews.com/?p=1035333 ; https://www.oceanindependence.com/articles/how-much-does-a-superyacht-cost/
A11: Financiamento marítimo Grécia 2025 | B11: https://www.hellenicshippingnews.com/greek-shipping-financing-grew-by-11-5-in-2025-now-standing-at-almost-60-billion-petrofin-research-shows/
A12: ECA (Lindblad/Ulstein) | B12: https://www.sec.gov/Archives/edgar/data/1512499/000143774919006986/lindb20190411_8k.htm
A13: EURIBOR / SOFR | B13: https://www.global-rates.com/en/interest-rates/euribor/historical/2026/ ; https://www.sofrrate.com/sofr-rate/2026-10
A14: CFC Brasil | B14: https://www.internationaltaxreview.com/article/b1f9jpywnh5qwh/brazil-new-regulations-for-brazilian-cfc-rules
... A17: Câmbio | B17: https://www.poundsterlinglive.com/history/EUR-USD-2026 ; https://longforecast.com/eur-to-brl
